Workbook

Sheet Vaciado
D1: 2024 | E1: 2025 | F1: 2026 | H1: 24/25 | I1: 25/26 | O1: MUS$
C2: Total de Clientes | D2: =Flujos!B8 -> 130 | E2: =Flujos!C8 -> 387.5 | F2: =Flujos!D8 -> 794.5 | H2: =(E2-D2)/D2 -> 1.9807692 | I2: =(F2-E2)/E2 -> 1.0503226 | L2: Valor Estocástico | O2: ='Para reporte'!G92 -> 716.63374 | P2: Corresponde al menor valor posible (MUS$)
C3: Ingresos (MUS$) | D3: =Flujos!B12 -> 1564.5643 | E3: =Flujos!C12 -> 3364.821 | F3: =Flujos!D12 -> 5160.3447 | H3: =(E3-D3)/D3 -> 1.1506441 | I3: =(F3-E3)/E3 -> 0.53361639
D5: VAN Chile (MUS$) | E5: ='MAP VALUE'!R29 -> 2183.3686 | G5: VAN (MUS$) Int. | H5: =NPV(D29,Flujos!B100:D100) -> 6982.4394 | J5: =E5+H5 -> 9165.8081
B7: Rango de usuarios (unidades de usuarios) | G7: Plan de ventas (unidades de clientes)
B8: ID | C8: Rango de usuarios | G8: Tipo de cliente | H8: 2024
H9: Enero | I9: Febrero | J9: Marzo | K9: Abril | L9: Mayo | M9: Junio | N9: Julio | O9: Agosto | P9: Septiembre | Q9: Octubre | R9: Noviembre | S9: Diciembre
B10: A | C10: 1 | D10: 25 | G10: =B10 -> A | H10: 1 | I10: 0 | J10: 1 | K10: 3 | L10: 8 | M10: 8 | N10: 12 | O10: 16 | P10: 16 | Q10: 20 | R10: 20 | S10: 20
B11: B | C11: 1 | D11: 500 | G11: =B11 -> B | H11: 0 | I11: 0 | J11: 1 | K11: 2 | L11: 8 | M11: 8 | N11: 12 | O11: 12 | P11: 12 | Q11: 12 | R11: 12 | S11: 12
B12: C | C12: =D11+1 -> 501 | D12: 1000 | G12: =B12 -> C | H12: 0 | I12: 0 | J12: 0 | K12: 1 | L12: 2 | M12: 2 | N12: 4 | O12: 4 | P12: 4 | Q12: 4 | R12: 4 | S12: 4
B13: D | C13: =D12+1 -> 1001 | D13: + | G13: =B13 -> D | H13: 0 | I13: 0 | J13: 0 | K13: 1 | L13: 1 | M13: 1 | N13: 2 | O13: 2 | P13: 2 | Q13: 2 | R13: 2 | S13: 2
B14: E | G14: =B14 -> E
C16: Valor UF | D16: 37000 | G16: Valor Paq. UF | H16: 2024 | T16: 2025 y 2026
C17: CLP/USD | D17: 900 | H17: Enero | I17: Febrero | J17: Marzo | K17: Abril | L17: Mayo | M17: Junio | N17: Julio | O17: Agosto | P17: Septiembre | Q17: Octubre | R17: Noviembre | S17: Diciembre
G18: =B10 -> A | H18: 30 | I18: 30 | J18: 30 | K18: 30 | L18: 30 | M18: 30 | N18: 30 | O18: 30 | P18: 30 | Q18: 30 | R18: 30 | S18: 30 | T18: 30
D19: MUS$ | G19: =B11 -> B | H19: 100 | I19: 100 | J19: 100 | K19: 100 | L19: 100 | M19: 100 | N19: 100 | O19: 100 | P19: 100 | Q19: 100 | R19: 100 | S19: 100 | T19: 100
C20: Inversión por recuperar | D20: 0 | G20: =B12 -> C | H20: 350 | I20: 350 | J20: 350 | K20: 350 | L20: 350 | M20: 350 | N20: 350 | O20: 350 | P20: 350 | Q20: 350 | R20: 350 | S20: 350 | T20: 350
C21: Cuentas Socios | D21: =63200/D17 -> 70.222222 | G21: =B13 -> D | H21: 1000 | I21: 1000 | J21: 1000 | K21: 1000 | L21: 1000 | M21: 1000 | N21: 1000 | O21: 1000 | P21: 1000 | Q21: 1000 | R21: 1000 | S21: 1000 | T21: 1000
C22: Pasivos de L. Plazo | D22: 0 | G22: =B14 -> E
B24: Beta | C24: 1.28 | D24: Information System | G24: Tipo de cliente | H24: MoM
B25: BCP | C25: 3 años | D25: 0.055 | H25: 2025 | I25: 2026
B26: US T. | C26: 3 años | D26: 0.0442 | G26: =B10 -> A | H26: 0.01 | I26: 0.01
B27: IPSA | C27: 3 años | D27: 0.2 | G27: =B11 -> B | H27: 0.01 | I27: 0.01
C28: Prima por riesgo | D28: 0.1 | G28: =B12 -> C | H28: 0.01 | I28: 0.01
C29: Tasa de descuento: | D29: =((D26+(C24*(D27-D26)))+(D25-D26))+D28 -> 0.354424 | G29: =B13 -> D | H29: 0.01 | I29: 0.01
G30: =B14 -> E | H30: 0.01 | I30: 0.01
C32: Recurrencia | D32: 12 | E32: meses | G32: Piloto | H32: 2024
C33: CHURN | D33: 0.5 | E33: mensual | H33: Enero | I33: Febrero | J33: Marzo | K33: Abril | L33: Mayo | M33: Junio | N33: Julio | O33: Agosto | P33: Septiembre | Q33: Octubre | R33: Noviembre | S33: Diciembre
G34: Piloto | H34: 0 | I34: 0 | J34: 0 | K34: 0 | L34: 0 | M34: 0 | N34: 0 | O34: 0 | P34: 0 | Q34: 0 | R34: 0 | S34: 0
C35: Costos por cliente | D35: US$
C36: Servidor por cliente: | D36: 125 | G36: Ciclo de conversión en meses | K36: % de conversión a clientes del Piloto
G37: 3 | K37: 0.5
C38: Costos mensuales | D38: US$ | E38: MUS$ | G38: MoM de la experiencia piloto
C39: Costos de Cloud mensual: | D39: 125 | E39: =D39/1000 -> 0.125 | G39: 2025 | H39: 0
C40: Costos de Hosting mensual: | D40: 63 | E40: =D40/1000 -> 0.063 | G40: 2026 | H40: 0
C41: Costos de correos mensual: | D41: 125 | E41: =D41/1000 -> 0.125
C42: Costos de Herramientas mensual: | D42: 125 | E42: =D42/1000 -> 0.125
C43: Costos de Licencias mensual: | D43: 125 | E43: =D43/1000 -> 0.125 | I43: 2024 | J43: 2025 | K43: 2026
C44: Otros gastos I+D: | D44: 1000 | E44: =D44/1000 -> 1 | H44: Impuesto a la renta | I44: 0.125 | J44: 0.15 | K44: 0.15
C45: Compra de equipos | D45: 1000 | E45: =D45/1000 -> 1
D46: CLP$ | E46: MUS$
C47: Gasto de Marketing y Difusión | D47: 1000000 | E47: =(D47/1000)/D17 -> 1.1111111
C49: Gastos del CAC s/ RR.HH. | D49: CLP$ | E49: MUS$
C50: Viaticos y viajes: | D50: 500000 | E50: =(D50/1000)/D17 -> 0.55555556
C51: Comisión Partner: | D51: 0.15
F54: Mes de entrada | G54: Reajuste anual | I54: Max. Clientes
C55: Planilla de RRHH (Bruto mensual) | D55: MCLP$ | E55: MUS$
C56: CCO | D56: 1400 | E56: =D56/$D$17 -> 1.5555556 | F56: 1 | G56: 0.05
C57: KAM | D57: =1200 -> 1200 | E57: =D57/$D$17 -> 1.3333333 | F57: 1 | G57: 0.05 | I57: 1000
C58: CTO | D58: 4500 | E58: =D58/$D$17 -> 5 | F58: 1 | G58: 0.05
C59: Desarrollador | D59: 2000 | E59: =D59/$D$17 -> 2.2222222 | F59: 1 | G59: 0.05
C60: Soporte | D60: 1500 | E60: =D60/$D$17 -> 1.6666667 | F60: 13 | G60: 0.05 | I60: 1000
C61: Operador | D61: =1000 -> 1000 | E61: =D61/$D$17 -> 1.1111111 | F61: 1 | G61: 0.05 | I61: 1000
C62: Expertos Revisión | D62: 1250 | E62: =D62/$D$17 -> 1.3888889 | F62: 9 | G62: 0.05
C63: CEO | D63: 5000 | E63: =D63/$D$17 -> 5.5555556 | F63: 1 | G63: 0.05
C64: CFO | D64: 3000 | E64: =D64/$D$17 -> 3.3333333 | F64: 1 | G64: 0.05
C65: Contadora | D65: 1000 | E65: =D65/$D$17 -> 1.1111111 | F65: 1 | G65: 0.05
C67: Comisiones: | D67: % de Ing. | F67: Condiciones | G67: MCL$ | H67: MUS$
C68: Comisión del CEO | D68: 0.05 | F68: Min. Ventas | G68: 55000 | H68: =G68/D17 -> 61.111111
C69: Comisión Operador | D69: 0.01 | F69: Max. Comisión | G69: 0.07 | H69: de las ventas
C70: Comisión CTO | D70: 0.035 | G70: Se aplican a KAM y CCO
C71: Comisión KAM | D71: 0.035
C72: Comisión CCO | D72: 0.035 | E72: C/ KAM | F72: 0.05 | G72: S/KAM
C74: País | D74: Comisión | E74: Veces Ingresos Chile | F74: días pago comisión
C75: Brasil | D75: 0.15 | E75: 1.5 | F75: 90
C76: Colombia | D76: 0.2 | E76: 0.7 | F76: 90
D77: % de los ingresos
C79: Días de cuentas por cobrar Chile:
C80: 90 | D80: días de pago clientes

Sheet Indicadores
A1: Variables | C1: Unidad. | D1: Enero | E1: Febrero | F1: Marzo | G1: Abril | H1: Mayo | I1: Junio | J1: Julio | K1: Agosto | L1: Septiembre | M1: Octubre | N1: Noviembre | O1: Diciembre
A2: Total de clientes | B2: =Vaciado!B10 -> A | C2: #
B3: =Vaciado!B11 -> B | C3: #
B4: =Vaciado!B12 -> C | C4: #
B5: =Vaciado!B13 -> D | C5: #
B6: =Vaciado!B14 -> E | C6: #
A7: Precio Promedio Chile | B7: =Vaciado!B10 -> A | C7: UF
B8: =Vaciado!B11 -> B | C8: UF
B9: =Vaciado!B12 -> C | C9: UF
B10: =Vaciado!B13 -> D | C10: UF
B11: =Vaciado!B14 -> E | C11: UF
A12: Variable | B12: Servidor por cliente | C12: US$
B13: Costos de Cloud mensual | C13: US$
B14: Costos de Hosting mensual | C14: US$
B15: Costos de correos mensual | C15: US$
B16: Costos de Herramientas mensual | C16: US$
B17: Costos de Licencias mensual | C17: US$
B18: Otros gastos I+D | C18: US$
B19: Compra de equipos | C19: US$
A20: MKT | B20: Gasto de Marketing y Difusión | C20: CLP$
B21: Viaticos y viajes | C21: CLP$
B22: Comisión Partner | C22: %
A23: RRHH | B23: CCO | C23: MCLP$
B24: KAM | C24: MCLP$
B25: CTO | C25: MCLP$
B26: Desarrollador | C26: MCLP$
B27: Soporte | C27: MCLP$
B28: Operador | C28: MCLP$
B29: Expertos Revisión | C29: MCLP$
B30: CEO | C30: MCLP$
B31: CFO | C31: MCLP$
B32: Contadora | C32: MCLP$
A33: Comisiones | B33: Comisión del CEO | C33: %
B34: Comisión Operador | C34: %
B35: Comisión CTO | C35: %
B36: Comisión KAM | C36: %
B37: Comisión CCO | C37: %
A38: Brasil | B38: Ingresos reales acumulados | C38: MUS$
B39: Pagos directos acumulados | C39: MUS$
A40: Colombia | B40: Ingresos reales acumulados | C40: MUS$
B41: Costos directos acumulados | C41: MUS$

Sheet Dashboard
B2: MUS$ | C2: 2024 | D2: 2025 | E2: 2026 | I2: MUS$ | J2: Ene | K2: Feb | L2: Mar | M2: Abr | N2: May | O2: Jun | P2: Jul | Q2: Ago | R2: Sept | S2: Oct | T2: Nov | U2: Dic | V2: 2024 | W2: 2025 | X2: 2026
B3: Ventas Chile | C3: ='Para reporte'!J28 -> 1564.5643 | D3: ='Para reporte'!K28 -> 3364.821 | E3: ='Para reporte'!L28 -> 5160.3447 | I3: Ventas Chile 2024 | J3: =Flujos!E12 -> 1.2333333 | K3: =Flujos!F12 -> 0 | L3: =Flujos!G12 -> 5.3444444 | M3: =Flujos!H12 -> 67.422222 | N3: =Flujos!I12 -> 112.64444 | O3: =Flujos!J12 -> 112.64444 | P3: =Flujos!K12 -> 203.91111 | Q3: =Flujos!L12 -> 208.84444 | ... U3: =Flujos!P12 -> 216.11987 | V3: =SUM(J3:U3) -> 1564.5643 | W3: ='Para reporte'!K13 -> 3364.821 | X3: ='Para reporte'!L13 -> 5160.3447
B4: Ventas Internacionales | C4: =Flujos!B95 -> 1760.1349 | D4: =Flujos!C85 -> 6412.4651 | E4: =Flujos!D85 -> 10365.22 | I4: Vtas Acum. Chile | J4: =J3 -> 1.2333333 | K4: =J4+K3 -> 1.2333333 | L4: =K4+L3 -> 6.5777778 | M4: =L4+M3 -> 74 | N4: =M4+N3 -> 186.64444 | O4: =N4+O3 -> 299.28889 | P4: =O4+P3 -> 503.2 | Q4: =P4+Q3 -> 712.04444 | R4: =Q4+R3 -> 920.88889 | ... U4: =T4+U3 -> 1564.5643 | V4: =U4 -> 1564.5643 | W4: =W3 -> 3364.821 | X4: =X3 -> 5160.3447
B5: Total de Ventas | C5: =C3+C4 -> 3324.6992 | D5: =D3+D4 -> 9777.2861 | E5: =E3+E4 -> 15525.565 | I5: YTD /Target ScaleX | J5: =($C$10/12) -> 355.10974 | K5: =($C$10/12)+J5 -> 710.21948 | L5: =($C$10/12)+K5 -> 1065.3292 | M5: =($C$10/12)+L5 -> 1420.439 | N5: =($C$10/12)+M5 -> 1775.5487 | O5: =($C$10/12)+N5 -> 2130.6584 | P5: =($C$10/12)+O5 -> 2485.7682 | Q5: =($C$10/12)+P5 -> 2840.8779 | R5: =($C$10/12)+Q5 -> 3195.9877 | ... U5: =($C$10/12)+T5 -> 4261.3169 | V5: =U5 -> 4261.3169 | W5: =D10 -> 4389.1564 | X5: =E10 -> 4520.8311
I6: Clientes nuevos acum. Chile | J6: =P.Comercial!H10 -> 1 | K6: =P.Comercial!I10+J6 -> 1 | L6: =P.Comercial!J10+K6 -> 3 | M6: =P.Comercial!K10+L6 -> 10 | N6: =P.Comercial!L10+M6 -> 29 | O6: =P.Comercial!M10+N6 -> 48 | P6: =P.Comercial!N10+O6 -> 78 | Q6: =P.Comercial!O10+P6 -> 112 | R6: =P.Comercial!P10+Q6 -> 146 | ... U6: =P.Comercial!S10+T6 -> 260 | V6: ='Para reporte'!J3 -> 260 | W6: ='Para reporte'!K3 -> 515 | X6: ='Para reporte'!L3 -> 814
B7: MUS$ sobre o bajo el eq. s/Chile | C7: =Metas!C15 -> 157.6428 | D7: =Metas!D15 -> 655.71173 | E7: =Metas!E15 -> 1177.6093 | I7: Clientes para target ScaleX | J7: =J5/'Unit Economics'!$C$3 -> 59.125781 | K7: =K5/'Unit Economics'!$C$3 -> 118.25156 | L7: =L5/'Unit Economics'!$C$3 -> 177.37734 | M7: =M5/'Unit Economics'!$C$3 -> 236.50313 | N7: =N5/'Unit Economics'!$C$3 -> 295.62891 | O7: =O5/'Unit Economics'!$C$3 -> 354.75469 | P7: =P5/'Unit Economics'!$C$3 -> 413.88047 | Q7: =Q5/'Unit Economics'!$C$3 -> 473.00625 | ... U7: =U5/'Unit Economics'!$C$3 -> 709.50938 | V7: =V5/'Unit Economics'!C3 -> 709.50938 | W7: =W5/'Unit Economics'!D3 -> 866.13814 | X7: =X5/'Unit Economics'!E3 -> 1077.13
B8: Down/Upside | C8: =Metas!C16 -> 1.112048 | D8: =Metas!D16 -> 1.2420396 | E8: =Metas!E16 -> 1.2956785
B10: ScaleX target | C10: =Metas!E7 -> 4261.3169 | D10: =Metas!E8 -> 4389.1564 | E10: =Metas!E9 -> 4520.8311
B11: Down/Upside ventas s/Chile | C11: =(C3-C10)/C3 -> -1.7236444 | D11: =(D3-D10)/D3 -> -0.30442492 | E11: =(E3-E10)/E3 -> 0.12392846
B12: Down/Upside ventas total | C12: =(C5-C10)/C5 -> -0.28171503 | D12: =(D5-D10)/D5 -> 0.55108643 | E12: =(E5-E10)/E5 -> 0.70881375
B15: MUS$ | C15: 2024 | D15: 2025 | E15: 2026
B16: Max Capital de Trabajo | C16: ='Unit Economics'!C22 -> 208.96388 | D16: ='Unit Economics'!D22 -> 161.27352 | E16: ='Unit Economics'!E22 -> 154.56499
B17: Var % anual | D17: =(D16-C16)/C16 -> -0.22822299 | E17: =(E16-D16)/D16 -> -0.041597254
B18: Bootstraping | C18: =IF(C16>'Unit Economics'!C21,'Unit Economics'!C20,'Unit Economics'!C21) -> 208.96388 | D18: =D16 -> 161.27352 | E18: =E16 -> 154.56499
B19: Bootstraping menos remanente d/equilibrio | C19: =C7-C18 -> -51.321082 | D19: =D7-D18 -> 494.43821 | E19: =E7-E18 -> 1023.0443
B21: Cifras en MUS$ | C21: 2024 | D21: 2025 | E21: 2026 | F21: Target
B22: Total de Ingresos | C22: ='Para reporte'!J47 -> 1564.5643 | D22: ='Para reporte'!K47 -> 3364.821 | E22: ='Para reporte'!L47 -> 5160.3447 | F22: > MUS$1.000 (3 año)
B23: Costos Operacionales | C23: ='Para reporte'!J48 -> 121.79428 | D23: ='Para reporte'!K48 -> 268.29195 | E23: ='Para reporte'!L48 -> 389.09051
B24: Gross Profit (%) | C24: =(C22-C23)/C22 -> 0.92215451 | D24: =(D22-D23)/D22 -> 0.92026561 | E24: =(E22-E23)/E22 -> 0.9245999 | F24: > 90%
B25: Gastos del CAC | C25: ='Para reporte'!J49 -> 385.07704 | D25: ='Para reporte'!K49 -> 783.32729 | E25: ='Para reporte'!L49 -> 1180.1625
B26: CAC por c/ cliente nuevo (MUS$) | C26: =Metas!C22 -> 1.4810655 | D26: =Metas!D22 -> 1.5210239 | E26: =Metas!E22 -> 1.4498311 | F26: < CAC MUS$ | G26: 10
B27: Gastos de Adm. y ventas | C27: ='Para reporte'!J50 -> 328.98422 | D27: ='Para reporte'!K50 -> 429.33039 | E27: ='Para reporte'!L50 -> 529.95657
B28: EBITDA | C28: ='Para reporte'!J51 -> 728.70878 | D28: ='Para reporte'!K51 -> 1883.8714 | E28: ='Para reporte'!L51 -> 3061.1351 | F28: > MUS$0
B29: EBITDA en % de los ingresos | C29: ='Para reporte'!J52 -> 0.46575828 | D29: ='Para reporte'!K52 -> 0.55987269 | E29: ='Para reporte'!L52 -> 0.59320361 | F29: > | G29: 0
C31: Proyectado | D31: Target
B32: Bootstraping 3y (MUS$) | C32: =C18+D18+E18 -> 524.80239 | D32: < MUS$ | E32: 350
B33: Breakeven (meses) | C33: =SUM(Flujos!E56:AN56) -> 3 | D33: < x meses | E33: 4
B34: Payback (meses) | C34: =SUM(Flujos!E58:AN58) -> 10 | D34: < x meses | E34: 12

Sheet Unit Economics
C2: 2024 | D2: 2025 | E2: 2026 | F2: Proyecto
B3: Ticket promedio (MUS$) | C3: ='Para reporte'!J23 -> 6.006005 | D3: ='Para reporte'!K23 -> 5.0675016 | E3: ='Para reporte'!L23 -> 4.1971083 | F3: ='Para reporte'!M16 -> 4.6841829 | G3: Ingresos / Cliente nuevos | L3: =C15 -> 1564.5643 | M3: =D15 -> 3364.821 | N3: =E15 -> 5160.3447 | O3: =L3+M3+N3 -> 10089.73
B4: Recurrencia (veces) | C4: =Flujos!B10/Flujos!B4 -> 1.0019231 | D4: =Flujos!C10/Flujos!C4 -> 1.2893204 | E4: =Flujos!D10/Flujos!D4 -> 1.5104423 | F4: =((Flujos!B10+Flujos!C10+Flujos!D10)/(Flujos!B4+Flujos!C4+Flujos!D4)) -> 1.3555695 | G4: veces / cliente | L4: =C16 -> 0.0014969608 | M4: =D16 -> 0.20742359 | N4: =E16 -> 0.37716047 | O4: =O5/O3 -> 0.26230269
B5: CAC (MUS$) | C5: ='Para reporte'!J42/'Para reporte'!J3 -> 1.4810655 | D5: ='Para reporte'!K42/'Para reporte'!K3 -> 1.5210239 | E5: ='Para reporte'!L42/'Para reporte'!L3 -> 1.4498311 | F5: ='Para reporte'!M42/'Para reporte'!M3 -> 1.4780156 | G5: Costo de adqusición por cada cliente nuevo | L5: =L3*L4 -> 2.3420915 | M5: =M3*M4 -> 697.94326 | N5: =N3*N4 -> 1946.278 | O5: =SUM(L5:N5) -> 2646.5634
B6: ARPU (%) | C6: ='Para reporte'!J52 -> 0.46575828 | D6: ='Para reporte'!K52 -> 0.55987269 | E6: ='Para reporte'!L52 -> 0.59320361 | F6: ='Unit Economics'!C24 -> 0.46575828 | G6: % de los ingresos que deja cada cliente | L6: =(C10*12) -> 260 | M6: =(D10*12) -> 515 | N6: =(E10*12) -> 814
C9: 2024 | D9: 2025 | E9: 2026 | F9: Proyecto
B10: Adqusición de clientes | C10: =(Flujos!B4+Flujos!B5)/12 -> 21.666667 | D10: =(Flujos!C4+Flujos!C5)/12 -> 42.916667 | E10: =(Flujos!D4+Flujos!D5)/12 -> 67.833333 | F10: ='MAP VALUE'!C7 -> 44.138889 | G10: Clientes nuevos por mes
B11: MoM | C11: =(POWER(('Para reporte'!J3/1),(1/11)))-1 -> 0.65784159 | D11: =(POWER(('Para reporte'!K3/'Para reporte'!J3),(1/11)))-1 -> 0.064106015 | E11: =(POWER(('Para reporte'!L3/'Para reporte'!K3),(1/11)))-1 -> 0.042495739 | F11: ='MAP VALUE'!D4 -> 0.18523831 | G11: tasa de crecimiento mensual de clientes
B12: CHURN | C12: =(POWER((-'Para reporte'!J6/1),(1/11)))-1 -> 0.55659872 | D12: =(POWER((-'Para reporte'!K6/1),(1/11)))-1 -> 0.65638606 | E12: =(POWER((-'Para reporte'!L6/1),(1/11)))-1 -> 0.72677541 | F12: ='MAP VALUE'!G7 -> 0.64658673 | G12: tasa mensual de pérdida de clientes
C14: 2024 | D14: 2025 | E14: 2026 | F14: Proyecto | L14: =C15+D15+E15 -> 10089.73 | M14: Total | N14: =L14/$L$14 -> 1 | P14: 0.47147173
B15: Ingresos totales Chile (MUS$) | C15: =Flujos!B12 -> 1564.5643 | D15: =Flujos!C12 -> 3364.821 | E15: =Flujos!D12 -> 5160.3447 | F15: =C15+D15+E15 -> 10089.73 | L15: =(C15*C16)+(D15*D16)+(E15*E16) -> 2646.5634 | M15: Recurrentes | N15: =L15/$L$14 -> 0.26230269 | O15: =O16 -> 1589 | P15: =P16 -> 4.6841829 | Q15: =O15*P15*P14 -> 3509.2427
B16: MRR | C16: =P.Comercial!C73/P.Comercial!C48 -> 0.0014969608 | D16: =P.Comercial!D73/P.Comercial!D48 -> 0.20742359 | E16: =P.Comercial!E73/P.Comercial!E48 -> 0.37716047 | G16: Ingresos recurrentes mensuales como % de los ingresos totales | L16: =L14-L15 -> 7443.1667 | M16: Nuevos | N16: =L16/$L$14 -> 0.73769731 | O16: ='MAP VALUE'!D11 -> 1589 | P16: ='MAP VALUE'!B11 -> 4.6841829 | Q16: =O16*P16 -> 7443.1667
B17: Gross Profitt | C17: ='Para reporte'!J38 -> 0.92215451 | D17: ='Para reporte'!K38 -> 0.92026561 | E17: ='Para reporte'!L38 -> 0.9245999 | F17: ='MAP VALUE'!J11 -> 0.92234001 | G17: % de los ingresos que son los costos operacionales
B18: CASH BURN RATE | C18: =('Para reporte'!J36+'Para reporte'!J42+'Para reporte'!J50)/360 -> 2.3218209 | D18: =('Para reporte'!K36+'Para reporte'!K42+'Para reporte'!K50)/360 -> 4.113749 | E18: =('Para reporte'!L36+'Para reporte'!L42+'Para reporte'!L50)/360 -> 5.8311377 | F18: ='MAP VALUE'!F26 -> 2.3218209 | G18: MUS$ gastos por día
B19: Ciclo Productivo (días) | C19: =Vaciado!$C$80 -> 90 | D19: =Vaciado!$C$80 -> 90 | E19: =Vaciado!$C$80 -> 90 | F19: ='MAP VALUE'!H26 -> 90 | G19: Tiempo entre la adqusición y monetización de un cliente
B20: Capital de trabajo A | C20: =C18*C19 -> 208.96388 | D20: =D18*D19 -> 370.23741 | E20: =E18*E19 -> 524.80239 | F20: =C20 -> 208.96388 | G20: Monto para cubrir un ciclo productivo
B21: Capital de trabajo B | C21: =Flujos!E72 -> -182.63922 | F21: =C21 -> -182.63922 | G21: Flujos negativos del período
B22: Max Capital de Trabajo | C22: =MAX(C21,C20) -> 208.96388 | D22: =MAX(D21,D20)-C22 -> 161.27352 | E22: =MAX(E21,E20)-D22-C22 -> 154.56499 | F22: =MAX(F20,F21) -> 208.96388 | G22: Max. Capital de trabajo encontrado aplicando dos metodologías
B23: Gross Profit | C23: ='Para reporte'!J38 -> 0.92215451 | D23: ='Para reporte'!K38 -> 0.92026561 | E23: ='Para reporte'!L38 -> 0.9245999 | F23: =F17 -> 0.92234001 | G23: Resultado operacional / ingresos (Chile)
B24: Margen de EBITDA | C24: ='Para reporte'!J52 -> 0.46575828 | D24: ='Para reporte'!K52 -> 0.55987269 | E24: ='Para reporte'!L52 -> 0.59320361 | F24: ='MAP VALUE'!G17 -> 0.46575828 | G24: EBITDA / ingresos (Chile)
B26: MUS$ | C26: 2024 | D26: 2025 | E26: 2026
B27: Ingresos Chile | C27: =C15 -> 1564.5643 | D27: =D15 -> 3364.821 | E27: =E15 -> 5160.3447
B28: Ingresos Brasil | C28: =Flujos!B95 -> 1760.1349 | D28: =Flujos!C95 -> 4372.1353 | E28: =Flujos!D95 -> 7067.1956
B29: Ingresos Colombia | C29: =Flujos!B96 -> 821.39626 | D29: =Flujos!C96 -> 2040.3298 | E29: =Flujos!D96 -> 3298.0246
B30: Ingresos Totales | C30: =C27+C28+C29 -> 4146.0954 | D30: =D27+D28+D29 -> 9777.2861 | E30: =E27+E28+E29 -> 15525.565
B32: % de Ingresos Chile | C32: =C27/$C$30 -> 0.37735849 | D32: =D27/$D$30 -> 0.34414673 | E32: =E27/$E$30 -> 0.33237726
B33: % de Ingresos Brasil | C33: =C28/$C$30 -> 0.4245283 | D33: =D28/$D$30 -> 0.44717268 | E33: =E28/$E$30 -> 0.45519733
B34: % de Ingresos Colombia | C34: =C29/$C$30 -> 0.19811321 | D34: =D29/$D$30 -> 0.20868059 | E34: =E29/$E$30 -> 0.21242542
B36: % Ingreso nacional | C36: =C32 -> 0.37735849 | D36: =D32 -> 0.34414673 | E36: =E32 -> 0.33237726
B37: % Ingreso Internacional | C37: =C33+C34 -> 0.62264151 | D37: =D33+D34 -> 0.65585327 | E37: =E33+E34 -> 0.66762274

Sheet MAP VALUE
A1: Cifras en MUS$ (miles de dólares de Estados Unidos)
D3: MoM | R3: BREAKEVEN: | S3: =Dashboard!C33 -> 3 | T3: Meses
D4: 0.18523831 | R4: PAYBACK: | S4: =Dashboard!C34 -> 10 | T4: Meses
C6: Adquisición Mensual | D6: X | E6: Horizonte de eval. (años) | F6: X | G6: CHURN (mensual real) | H6: X | I6: Frecuencia de compra (meses) | N6: US.T | P6: BCP 3 años | R6: IPSA Anual
C7: =AVERAGE('Unit Economics'!C10:E10) -> 44.138889 | E7: 3 | G7: =AVERAGE('Unit Economics'!C12:E12) -> 0.64658673 | I7: 12 | N7: =Vaciado!D26 -> 0.0442 | P7: =Vaciado!D25 -> 0.055 | R7: =Vaciado!D27 -> 0.2
P9: Beta
B10: Ticket Promedio | C10: X | D10: Clientes Monetizados | E10: X | F10: Recurrencia | G10: = | H10: Ingresos | I10: X | J10: G.P. | K10: = | L10: Resultado Op. | P10: =Vaciado!D24 -> Information System
B11: ='Para reporte'!M16 -> 4.6841829 | D11: =(C7*(12*E7)) -> 1589 | F11: =((Flujos!B10+Flujos!C10+Flujos!D10)/(Flujos!B4+Flujos!C4+Flujos!D4)) -> 1.3555695 | H11: =B11*D11*F11 -> 10089.73 | J11: =AVERAGE('Unit Economics'!C17:E17) -> 0.92234001 | L11: =(H11*J11) -> 9306.1616 | P11: =Vaciado!C24 -> 1.28
D12: x
D13: CAC | I13: (-) | J13: Gastos del CAC | K13: = | L13: Resultado d/CAC | P13: Tasa de descuento
D14: ='Unit Economics'!F5 -> 1.4780156 | J14: =D14*D11 -> 2348.5668 | L14: =L11-J14 -> 6957.5948 | P14: =(N7+(P11*(R7-N7)))+(P7-N7) -> 0.254424
C16: Ingresos - CAC | E16: LTV | G16: ARPU | I16: (-) | J16: Gastos de Administración | K16: = | L16: EBITDA | P16: CASTIGO x RIESGO
C17: =B11-D14 -> 3.2061673 | E17: =C17*F11 -> 4.3461827 | G17: ='Unit Economics'!C24 -> 0.46575828 | J17: =SUM(Dashboard!C27:E27) -> 1288.2712 | L17: =L14-J17 -> 5669.3236 | P17: =Vaciado!D28 -> 0.1
I19: / (1- … ) | J19: Impuestos efectivos | K19: x | L19: Flujos d/Impuestos | N19: Tasa de descuento nominal
J20: ='Para reporte'!O65 -> 0.11459869 | L20: =L17*(1-J20) -> 5019.6266 | N20: =P14+P17 -> 0.354424
I22: (-) | J22: Capital de Trabajo x Flujos | K22: - | L22: Flujos s/ Inv. Inicial | M22: X | N22: Tasa de descuento real | O22: = | P22: VAN de los flujos | Q22: - | R22: Pasivos & Obligaciones
J23: =-'Para reporte'!J63 -> 182.63922 | L23: =L20-J23 -> 4836.9873 | N23: ='Para reporte'!Q66 -> 0.47135031 | P23: =L23*N23 -> 2279.9155 | R23: =(Vaciado!D21+Vaciado!D22) -> 70.222222
F25: Cash Burn Rate | G25: X | H25: Ciclo Productivo | I25: = | J25: Capital de Trabajo x Ciclo Op. | Q25: - | R25: Bootstraping | T25: Inversión Total (MUS$) | W25: =T26/R29 -> 0.12786943
F26: ='Unit Economics'!C18 -> 2.3218209 | H26: ='Unit Economics'!C19 -> 90 | J26: =F26*H26 -> 208.96388 | R26: =J26-J23 -> 26.324662 | T26: =J26+R23 -> 279.18611
Q28: = | R28: Valor | S28: =R29/'Unit Economics'!C15 -> 1.3955122 | T28: Ingresos primer año
R29: =P23-R23-R26 -> 2183.3686 | S29: =R29/'Para reporte'!J51 -> 2.9962156 | T29: EBITDA primer año
L32: País | M32: Comisión | N32: Veces Ingresos Chile | O32: días pago ingresos | P32: VALOR (VAN) adicional | R32: VAN Internacional | T32: Valor Total (MUS$) | W32: =T33/R29 -> 4.1980122
L33: Brasil | M33: =Vaciado!D75 -> 0.15 | N33: =Vaciado!E75 -> 1.5 | O33: =Vaciado!F75 -> 90 | P33: =Flujos!E106 -> 4881.6539 | R33: =P33+P34 -> 6982.4394 | T33: =R29+P33+P34 -> 9165.8081
L34: Colombia | M34: =Vaciado!D76 -> 0.2 | N34: =Vaciado!E76 -> 0.7 | O34: =Vaciado!F76 -> 90 | P34: =Flujos!E112 -> 2100.7856
T36: Empresa valorizada por A.Maureira & Co.

Sheet Cap.Table
B3: (MUS$) | C3: Common | D3: Loan | E3: Seed 1 | F3: Seed 2 | G3: VC | H3: Options | I3: Total | J3: Fully Diluted
B4: Bárbara Pantoja P. | C4: =10000/Vaciado!D17 -> 11.111111 | I4: =SUM(C4:H4) -> 11.111111 | J4: =I4/$I$7 -> 0.33333333
B5: Rodrigo Hermosilla P. | C5: =C4 -> 11.111111 | I5: =SUM(C5:H5) -> 11.111111 | J5: =I5/$I$7 -> 0.33333333
B6: Lionel Valenzuela O. | C6: =C4 -> 11.111111 | I6: =SUM(C6:H6) -> 11.111111 | J6: =I6/$I$7 -> 0.33333333
B7: Total | C7: =SUM(C4:C6) -> 33.333333 | D7: =SUM(D4:D6) -> 0 | E7: =SUM(E4:E6) -> 0 | F7: =SUM(F4:F6) -> 0 | G7: =SUM(G4:G6) -> 0 | H7: =SUM(H4:H6) -> 0 | I7: =SUM(I4:I6) -> 33.333333 | J7: =SUM(J4:J6) -> 1
B10: (MUS$) | C10: Common | D10: Loan | E10: Seed 1 | F10: Seed 2 | G10: VC | H10: Options | I10: Total | J10: Fully Diluted
B11: =B4 -> Bárbara Pantoja P. | C11: =C4 -> 11.111111 | I11: =SUM(C11:H11) -> 11.111111 | J11: =L11 -> 0.29071019 | L11: =(1/3)-(J16/3) -> 0.29071019
B12: =B5 -> Rodrigo Hermosilla P. | C12: =C5 -> 11.111111 | I12: =SUM(C12:H12) -> 11.111111 | J12: =L11 -> 0.29071019
B13: =B6 -> Lionel Valenzuela O. | C13: =C6 -> 11.111111 | I13: =SUM(C13:H13) -> 11.111111 | J13: =L11 -> 0.29071019
B14: FONDO 1 | E14: 100 | I14: =SUM(C14:H14) -> 100 | J14: 0
B15: FONDO 2 | E15: 100 | I15: =SUM(C15:H15) -> 100 | J15: 0
B16: Venture Capital | G16: ='MAP VALUE'!T26 -> 279.18611 | I16: =SUM(C16:H16) -> 279.18611 | J16: =I16/I19 -> 0.12786943
B17: Total | C17: =SUM(C11:C16) -> 33.333333 | D17: =SUM(D11:D16) -> 0 | E17: =SUM(E11:E16) -> 200 | F17: =SUM(F11:F16) -> 0 | G17: =SUM(G11:G16) -> 279.18611 | H17: =SUM(H11:H16) -> 0 | I17: =SUM(I11:I16) -> 512.51944 | J17: =SUM(J11:J16) -> 1
H19: Valor Postmoney | I19: =Vaciado!E5 -> 2183.3686

Sheet Para reporte
B2: ID | C2: Rango de usuarios | E2: Valor Paquete | J2: 2024 | K2: 2025 | L2: 2026 | P2: 2024 | Q2: 2025 | R2: 2026
E3: UF | F3: MUS$ | I3: Clientes nuevos | J3: =SUM(P.Comercial!H10:S10) -> 260 | K3: =SUM(P.Comercial!T10:AE10) -> 515 | L3: =SUM(P.Comercial!AF10:AQ10) -> 814 | M3: =SUM(J3:L3) -> 1589 | O3: Ingresos por clientes nuevos | P3: =J26 -> 1562.2222 | Q3: =K26 -> 2666.8778 | R3: =L26 -> 3214.0667
B4: =Vaciado!B10 -> A | C4: =Vaciado!C10 -> 1 | D4: =Vaciado!D10 -> 25 | E4: =Vaciado!T18 -> 30 | F4: =((E4*Vaciado!$D$16)/Vaciado!$D$17)/1000 -> 1.2333333 | I4: Clientes x Exp. Piloto | J4: =SUM(P.Comercial!H14:S14) -> 0 | K4: =SUM(P.Comercial!T14:AE14) -> 0 | L4: =SUM(P.Comercial!AF14:AQ14) -> 0 | O4: Ingresos recurrentes | P4: =J27 -> 2.3420915 | Q4: =K27 -> 697.94326 | R4: =L27 -> 1946.278
B5: =Vaciado!B11 -> B | C5: =Vaciado!C11 -> 1 | D5: =Vaciado!D11 -> 500 | E5: =Vaciado!T19 -> 100 | F5: =((E5*Vaciado!$D$16)/Vaciado!$D$17)/1000 -> 4.1111111 | I5: Total de Clientes Adquiridos | J5: =J3+J4 -> 260 | K5: =K3+K4 -> 515 | L5: =L3+L4 -> 814 | O5: CAC total | P5: =-J42 -> -385.07704 | Q5: =-K42 -> -783.32729 | R5: =-L42 -> -1180.1625
B6: =Vaciado!B12 -> C | C6: =Vaciado!C12 -> 501 | D6: =Vaciado!D12 -> 1000 | E6: =Vaciado!T20 -> 350 | F6: =((E6*Vaciado!$D$16)/Vaciado!$D$17)/1000 -> 14.388889 | I6: CHURN de Clientes | J6: =SUM(P.Comercial!H26:S26) -> -130 | K6: =SUM(P.Comercial!T26:AE26) -> -257.5 | L6: =SUM(P.Comercial!AF26:AQ26) -> -407
B7: =Vaciado!B13 -> D | C7: =Vaciado!C13 -> 1001 | D7: =Vaciado!D13 -> + | E7: =Vaciado!T21 -> 1000 | F7: =((E7*Vaciado!$D$16)/Vaciado!$D$17)/1000 -> 41.111111 | I7: Clientes acumulados | J7: =J5+J6 -> 130 | K7: =K5+K6+J7 -> 387.5 | L7: =L5+L6+K7 -> 794.5
B8: =Vaciado!B14 -> E | C8: =Vaciado!C14 -> 0 | D8: =Vaciado!D14 -> 0 | E8: =Vaciado!T22 -> 0 | F8: =((E8*Vaciado!$D$16)/Vaciado!$D$17)/1000 -> 0
J9: 2024 | K9: 2025 | L9: 2026
I10: Total de servicios | J10: =SUM(P.Comercial!H44:S44) -> 260.5 | K10: =SUM(P.Comercial!T44:AE44) -> 664 | L10: =SUM(P.Comercial!AF44:AQ44) -> 1229.5 | M10: =SUM(J10:L10) -> 2154
B11: Tipo de cliente | C11: Total de Clientes | F11: Total Adquiridos | G11: % de la Cartera
C12: 2024 | D12: 2025 | E12: 2026 | I12: Cifras en MUS$ | J12: 2024 | K12: 2025 | L12: 2026
B13: =Vaciado!B10 -> A | C13: =SUM(P.Comercial!H5:S5) -> 125 | D13: =SUM(P.Comercial!T5:AE5) -> 289 | E13: =SUM(P.Comercial!AF5:AQ5) -> 526 | F13: =SUM(C13:E13) -> 940 | G13: =IF(F13=0,0,F13/$F$18) -> 0.59156702 | I13: Ingresos totales | J13: =SUM(P.Comercial!H52:S52) -> 1564.5643 | K13: =SUM(P.Comercial!T52:AE52) -> 3364.821 | L13: =SUM(P.Comercial!AF52:AQ52) -> 5160.3447 | M13: =SUM(J13:L13) -> 10089.73
B14: =Vaciado!B11 -> B | C14: =SUM(P.Comercial!H6:S6) -> 91 | D14: =SUM(P.Comercial!T6:AE6) -> 154 | E14: =SUM(P.Comercial!AF6:AQ6) -> 216 | F14: =SUM(C14:E14) -> 461 | G14: =IF(F14=0,0,F14/$F$18) -> 0.29011957
B15: =Vaciado!B12 -> C | C15: =SUM(P.Comercial!H7:S7) -> 29 | D15: =SUM(P.Comercial!T7:AE7) -> 48 | E15: =SUM(P.Comercial!AF7:AQ7) -> 48 | F15: =SUM(C15:E15) -> 125 | G15: =IF(F15=0,0,F15/$F$18) -> 0.078665828 | I15: Cifras en MUS$ | J15: 2024 | K15: 2025 | L15: 2026 | M15: Proyecto
B16: =Vaciado!B13 -> D | C16: =SUM(P.Comercial!H8:S8) -> 15 | D16: =SUM(P.Comercial!T8:AE8) -> 24 | E16: =SUM(P.Comercial!AF8:AQ8) -> 24 | F16: =SUM(C16:E16) -> 63 | G16: =IF(F16=0,0,F16/$F$18) -> 0.039647577 | I16: Ticket promedio | J16: =IF(J10=0,0,J13/J10) -> 6.006005 | K16: =IF(K10=0,0,K13/K10) -> 5.0675016 | L16: =IF(L10=0,0,L13/L10) -> 4.1971083 | M16: =IF(M10=0,0,M13/M10) -> 4.6841829
B17: =Vaciado!B14 -> E | C17: =SUM(P.Comercial!H9:S9) -> 0 | D17: =SUM(P.Comercial!T9:AE9) -> 0 | E17: =SUM(P.Comercial!AF9:AQ9) -> 0 | F17: =SUM(C17:E17) -> 0 | G17: =IF(F17=0,0,F17/$F$18) -> 0 | J17: =J13/J3 -> 6.0175551 | K17: =K13/K3 -> 6.5336331 | L17: =L13/L3 -> 6.3394898 | M17: =M13/M3 -> 6.3497357
B18: Totales | C18: =SUM(C13:C17) -> 260 | D18: =SUM(D13:D17) -> 515 | E18: =SUM(E13:E17) -> 814 | F18: =SUM(F13:F17) -> 1589 | G18: =IF(F18=0,0,F18/$F$18) -> 1
I19: Cifras en MUS$ | J19: 2024 | K19: 2025 | L19: 2026 | M19: Proyecto
B20: Exp. Piloto | C20: Total de Clientes Adquiridos de Piloto | F20: Total Adquiridos | I20: Ticket promedio C. nuevos | J20: =IF(P.Comercial!C57=0,0,P.Comercial!C57/'Para reporte'!J3) -> 6.008547 | K20: =IF(P.Comercial!D57=0,0,P.Comercial!D57/'Para reporte'!K3) -> 5.1784035 | L20: =IF(P.Comercial!E57=0,0,P.Comercial!E57/'Para reporte'!L3) -> 3.9484848 | M20: =IF(P.Comercial!F57=0,0,P.Comercial!F57/'Para reporte'!M3) -> 0
C21: 2024 | D21: 2025 | E21: 2026 | I21: Ticket promedio C. Exp. P. | J21: =IF(J4=0,0,P.Comercial!C65/'Para reporte'!J4) -> 0 | K21: =IF(K4=0,0,P.Comercial!D65/'Para reporte'!K4) -> 0 | L21: =IF(L4=0,0,P.Comercial!E65/'Para reporte'!L4) -> 0 | M21: =IF(M4=0,0,P.Comercial!F65/'Para reporte'!M4) -> 0
B22: Piloto | C22: =SUM(P.Comercial!H14:S14) -> 0 | D22: =SUM(P.Comercial!T14:AE14) -> 0 | E22: =SUM(P.Comercial!AF14:AQ14) -> 0 | F22: =SUM(C22:E22) -> 0 | I22: Ticket promedio recurrentes | J22: =IF((J10-J5)=0,0,P.Comercial!C73/(J10-J5)) -> 4.6841829 | K22: =IF((K10-K5)=0,0,P.Comercial!D73/(K10-K5)) -> 4.6841829 | L22: =IF((L10-L5)=0,0,P.Comercial!E73/(L10-L5)) -> 4.6841829 | M22: =IF((M10-M5)=0,0,P.Comercial!F73/(M10-M5)) -> 0
I23: Ticket promedio ponderado | J23: =J16 -> 6.006005 | K23: =K16 -> 5.0675016 | L23: =L16 -> 4.1971083 | M23: =M16 -> 4.6841829
B25: Tipo de cliente | C25: Precio en MUS$ | D25: % de la Cartera | E25: Precio Prom MUS$ | I25: Cifras en MUS$ | J25: 2024 | K25: 2025 | L25: 2026
I26: Ingresos clientes nuevos | J26: =J20*J3 -> 1562.2222 | K26: =K20*K3 -> 2666.8778 | L26: =L20*L3 -> 3214.0667
B27: =Vaciado!B10 -> A | C27: =F4 -> 1.2333333 | D27: =G13 -> 0.59156702 | E27: =C27*D27 -> 0.72959933 | I27: Ingresos Recurrentes | J27: =(J10*J16)-J26 -> 2.3420915 | K27: =(K10*K16)-K26 -> 697.94326 | L27: =(L10*L16)-L26 -> 1946.278
B28: =Vaciado!B11 -> B | C28: =F5 -> 4.1111111 | D28: =G14 -> 0.29011957 | E28: =C28*D28 -> 1.1927138 | I28: Total de Ingresos | J28: =J26+J27 -> 1564.5643 | K28: =K26+K27 -> 3364.821 | L28: =L26+L27 -> 5160.3447
B29: =Vaciado!B12 -> C | C29: =F6 -> 14.388889 | D29: =G15 -> 0.078665828 | E29: =C29*D29 -> 1.1319139
B30: =Vaciado!B13 -> D | C30: =F7 -> 41.111111 | D30: =G16 -> 0.039647577 | E30: =C30*D30 -> 1.6299559
B31: =Vaciado!B14 -> E | C31: =F8 -> 0 | D31: =G17 -> 0 | E31: =C31*D31 -> 0 | I31: % del total de ingresos | J31: 2024 | K31: 2025 | L31: 2026
B32: Precio promedio ponderado | E32: =SUM(E27:E31) -> 4.6841829 | I32: Ingresos recurrentes | J32: =IF(J28=0,0,J27/J28) -> 0.0014969608 | K32: =IF(K28=0,0,K27/K28) -> 0.20742359 | L32: =IF(L28=0,0,L27/L28) -> 0.37716047
I34: Cifras en MUS$ | J34: 2024 | K34: 2025 | L34: 2026
D35: MUS$ | I35: Total de Ingresos | J35: =Flujos!B12 -> 1564.5643 | K35: =Flujos!C12 -> 3364.821 | L35: =Flujos!D12 -> 5160.3447
B36: Costos fijos mensuales | D36: =Vaciado!E39+Vaciado!E40+Vaciado!E41+Vaciado!E42+Vaciado!E43+Vaciado!E44+Vaciado!E45+Vaciado!E47+Vaciado!E50+Vaciado!E56+Vaciado!E57+Vaciado!E58+Vaciado!E59+Vaciado!E60+Vaciado!E61+Vaciado!E62+Vaciado!E63+Vaciado!E64+Vaciado!E65 -> 28.507444 | I36: Costos Operacionales | J36: =Flujos!B20 -> 121.79428 | K36: =Flujos!C20 -> 268.29195 | L36: =Flujos!D20 -> 389.09051 | N36: =J36/J35 -> 0.077845495
B37: Costos fijos anuales | D37: =D36*12 -> 342.08933 | I37: Resultado Operacional | J37: =J35-J36 -> 1442.77 | K37: =K35-K36 -> 3096.5291 | L37: =L35-L36 -> 4771.2542
I38: Gross Profit (%) | J38: =IF(J35=0,0,J37/J35) -> 0.92215451 | K38: =IF(K35=0,0,K37/K35) -> 0.92026561 | L38: =IF(L35=0,0,L37/L35) -> 0.9245999
C39: Ticket promedio: | D39: ='Unit Economics'!C3 -> 6.006005
C40: % Comprometido: | D40: =Vaciado!D68+Vaciado!D69+Vaciado!D70+Vaciado!D71+Vaciado!D72+Vaciado!D51 -> 0.315 | I40: Cifras en MUS$ | J40: 2024 | K40: 2025 | L40: 2026 | M40: Total
C41: Costos Unitarios: | D41: =Vaciado!D36/1000 -> 0.125 | I41: Total de Ingresos | J41: =Flujos!B12 -> 1564.5643 | K41: =Flujos!C12 -> 3364.821 | L41: =Flujos!D12 -> 5160.3447 | M41: =J41+K41+L41 -> 10089.73
C42: Costos variable por unidad: | D42: =D39*D40+D41 -> 2.0168916 | I42: Gastos del CAC | J42: =Flujos!B28 -> 385.07704 | K42: =Flujos!C28 -> 783.32729 | L42: =Flujos!D28 -> 1180.1625 | M42: =J42+K42+L42 -> 2348.5668
I43: Resultado d/ de CAC | J43: =J41-J42 -> 1179.4873 | K43: =K41-K42 -> 2581.4937 | L43: =L41-L42 -> 3980.1822 | M43: =M41-M42 -> 7741.1632
C44: Ciclo Productivo: | D44: =Vaciado!G37 -> 3 | E44: meses | I44: CAC en % de los ingresos | J44: =IF(J41=0,0,J42/J41) -> 0.24612413 | K44: =IF(K41=0,0,K42/K41) -> 0.2327991 | L44: =IF(L41=0,0,L42/L41) -> 0.22869839
C46: Cliente | D46: CT | E46: CT | F46: IT | I46: Cifras en MUS$ | J46: 2024 | K46: 2025 | L46: 2026
C47: 7.5034086 | D47: =E47-F47 -> 55.590385 | E47: =((D44*D36)+(C47*D42)) -> 100.65589 | F47: =C47*D39 -> 45.06551 | I47: Total de Ingresos | J47: =Flujos!B12 -> 1564.5643 | K47: =Flujos!C12 -> 3364.821 | L47: =Flujos!D12 -> 5160.3447
I48: Costos Operacionales | J48: =Flujos!B20 -> 121.79428 | K48: =Flujos!C20 -> 268.29195 | L48: =Flujos!D20 -> 389.09051
I49: Gastos del CAC | J49: =Flujos!B28 -> 385.07704 | K49: =Flujos!C28 -> 783.32729 | L49: =Flujos!D28 -> 1180.1625
B50: Gastos del CAC | I50: Gastos de Adm. y ventas | J50: =Flujos!B44 -> 328.98422 | K50: =Flujos!C44 -> 429.33039 | L50: =Flujos!D44 -> 529.95657 | M50: =J50+K50+L50 -> 1288.2712
B51: Viaticos y viajes (MUS$) | D51: =Vaciado!E50 -> 0.55555556 | I51: EBITDA | J51: =J47-J48-J49-J50 -> 728.70878 | K51: =K47-K48-K49-K50 -> 1883.8714 | L51: =L47-L48-L49-L50 -> 3061.1351 | M51: =J51+K51+L51 -> 5673.7153
B52: Sueldo bruto CCO (MUS$) | D52: =Vaciado!E56 -> 1.5555556 | I52: EBITDA en % de los ingresos | J52: =IF(J47=0,0,J51/J47) -> 0.46575828 | K52: =IF(K47=0,0,K51/K47) -> 0.55987269 | L52: =IF(L47=0,0,L51/L47) -> 0.59320361
B53: Sueldo bruto KAM (MUS$) | D53: =Vaciado!E57 -> 1.3333333
B54: Comisión Partner (%) | D54: =Vaciado!D51 -> 0.15 | I54: Cifras en MUS$ | J54: Lunch | K54: 2024 | L54: 2025 | M54: 2026
B55: Comisión KAM (%)* | D55: =Vaciado!D71 -> 0.035 | I55: Total de Ingresos | K55: =J47 -> 1564.5643 | L55: =K47 -> 3364.821 | M55: =L47 -> 5160.3447
B56: Comisión CCO (%)* | D56: =Vaciado!D72 -> 0.035 | I56: Costos Operacionales | K56: =J48 -> 121.79428 | L56: =K48 -> 268.29195 | M56: =L48 -> 389.09051
I57: Gastos del CAC | K57: =J49 -> 385.07704 | L57: =K49 -> 783.32729 | M57: =L49 -> 1180.1625
B58: Planilla de Recursos Humanos (MUS$) | I58: Gastos de Adm. y ventas | K58: =J50 -> 328.98422 | L58: =K50 -> 429.33039 | M58: =L50 -> 529.95657
B59: Sueldo Bruto CEO | D59: =Vaciado!E63 -> 5.5555556 | I59: EBITDA | K59: =K55-K56-K57-K58 -> 728.70878 | L59: =L55-L56-L57-L58 -> 1883.8714 | M59: =M55-M56-M57-M58 -> 3061.1351 | N59: =K59+L59+M59 -> 5673.7153
B60: Sueldo Bruto CFO | D60: =Vaciado!E64 -> 3.3333333 | I60: Capital de Trabajo | J60: ='Unit Economics'!C21 -> -182.63922 | M60: =-J60 -> 182.63922
B61: Sueldo Bruto CCO | D61: =Vaciado!E56 -> 1.5555556 | I61: V. de desecho
B62: Sueldo Bruto CTO | D62: =Vaciado!E58 -> 5 | I62: Impuesto a la renta | K62: =IF(K59<0,0,K59*Vaciado!I44) -> 91.088597 | L62: =IF(L59<0,0,L59*Vaciado!J44) -> 282.58071 | M62: =IF(M59<0,0,M59*Vaciado!K44) -> 459.17027
B63: Sueldo Bruto KAM | D63: =Vaciado!E57 -> 1.3333333 | I63: Flujo de Caja (Chile) | J63: =SUM(J60:J60) -> -182.63922 | K63: =K59-K62 -> 637.62018 | L63: =L59-L62 -> 1601.2907 | M63: =M59-M62+M60+M61 -> 2784.6041
B64: Sueldo Bruto Desarrollador | D64: =Vaciado!E59 -> 2.2222222
B65: Sueldo Bruto Soporte | D65: =Vaciado!E60 -> 1.6666667 | I65: Planilla de RR.HH. | J65: 2024 | K65: 2025 | L65: 2026 | N65: =K62+L62+M62-M60 -> 650.20035 | O65: =N65/N59 -> 0.11459869 | Q65: Tasa de descuento real
B66: Sueldo Bruto Operador | D66: =Vaciado!E61 -> 1.1111111 | I66: CEO (Bruto) | J66: =SUM(Flujos!E38:P38) -> 66.666667 | K66: =SUM(Flujos!Q38:AB38) -> 70 | L66: =SUM(Flujos!AC38:AN38) -> 73.5 | O66: =SUM(J63:M63) -> 4840.8757 | P66: =NPV(Vaciado!D29,'Para reporte'!K63:M63)+J63 -> 2281.7483 | Q66: =P66/O66 -> 0.47135031
B67: Revisión de expertos | D67: =Vaciado!E62 -> 1.3888889 | I67: CEO Comisión | J67: =SUM(Flujos!E43:P43) -> 78.228216 | K67: =SUM(Flujos!Q43:AB43) -> 168.24105 | L67: =SUM(Flujos!AC43:AN43) -> 258.01723
B68: Contadora | D68: =Vaciado!E65 -> 1.1111111 | I68: Total CEO | J68: =J66+J67 -> 144.89488 | K68: =K66+K67 -> 238.24105 | L68: =L66+L67 -> 331.51723
B69: Comisión del CEO (%) | D69: =Vaciado!D68 -> 0.05 | I69: % de los ingresos | J69: =IF(J47=0,0,J68/J47) -> 0.092610372 | K69: =IF(K47=0,0,K68/K47) -> 0.070803484 | L69: =IF(L47=0,0,L68/L47) -> 0.064243235
B70: Comisión CTO (%) | D70: =Vaciado!D70 -> 0.035 | I70: CTO (Bruto) | J70: =SUM(Flujos!E39:P39) -> 60 | K70: =SUM(Flujos!Q39:AB39) -> 63 | L70: =SUM(Flujos!AC39:AN39) -> 66.15
B71: Comisión del Operador (%) | D71: =Vaciado!D69 -> 0.01 | I71: CTO Comisión | J71: =SUM(Flujos!E19:P19) -> 54.759751 | K71: =SUM(Flujos!Q19:AB19) -> 117.76874 | L71: =SUM(Flujos!AC19:AN19) -> 180.61206
I72: Total CTO | J72: =J70+J71 -> 114.75975 | K72: =K70+K71 -> 180.76874 | L72: =L70+L71 -> 246.76206
I73: % de los ingresos | J73: =IF(J47=0,0,J72/$J$47) -> 0.073349334 | K73: =IF(K47=0,0,K72/$K$47) -> 0.053723135 | L73: =IF(L47=0,0,L72/$L$47) -> 0.047818911 | N73: =SUM(Flujos!E40:P40) -> 26.666667 | O73: =SUM(Flujos!Q40:AB40) -> 28 | P73: =SUM(Flujos!AC40:AN40) -> 29.4 | Q73: =Flujos!A40 -> Desarrollador
I74: CCO (Bruto) | J74: =SUM(Flujos!E23:P23) -> 18.666667 | K74: =SUM(Flujos!Q23:AB23) -> 19.6 | L74: =SUM(Flujos!AC23:AN23) -> 20.58
I75: CCO Comisión | J75: =SUM(Flujos!E25:P25) -> 54.529529 | K75: =SUM(Flujos!Q25:AB25) -> 117.76874 | L75: =SUM(Flujos!AC25:AN25) -> 180.61206 | N75: =SUM(Flujos!E42:P42) -> 13.333333 | O75: =SUM(Flujos!Q42:AB42) -> 14 | P75: =SUM(Flujos!AC42:AN42) -> 14.7 | Q75: =Flujos!A42 -> Contadora
I76: Total CCO | J76: =J74+J75 -> 73.196195 | K76: =K74+K75 -> 137.36874 | L76: =L74+L75 -> 201.19206
I77: % de los ingresos | J77: =IF(J47=0,0,J76/J47) -> 0.046783756 | K77: =IF(K47=0,0,K76/K47) -> 0.040824975 | L77: =IF(L47=0,0,L76/L47) -> 0.038988106
I78: CFO (Bruto) | J78: =SUM(Flujos!E41:P41) -> 40 | K78: =SUM(Flujos!Q41:AB41) -> 42 | L78: =SUM(Flujos!AC41:AN41) -> 44.1
I79: % de los ingresos | J79: =IF(J47=0,0,J78/J47) -> 0.025566223 | K79: =IF(K47=0,0,K78/K47) -> 0.01248209 | L79: =IF(L47=0,0,L78/L47) -> 0.0085459408
I80: C-Level (Bruto) | J80: =J66+J70+J74+J78 -> 185.33333 | K80: =K66+K70+K74+K78 -> 194.6 | L80: =L66+L70+L74+L78 -> 204.33
I81: C-Level Comisión | J81: =J67+J71+J75 -> 187.5175 | K81: =K67+K71+K75 -> 403.77852 | L81: =L67+L71+L75 -> 619.24136
I82: Total C-Level | J82: =J80+J81 -> 372.85083 | K82: =K80+K81 -> 598.37852 | L82: =L80+L81 -> 823.57136
I83: % de los ingresos | J83: =IF(J47=0,0,J82/J47) -> 0.23830968 | K83: =IF(K47=0,0,K82/K47) -> 0.17783369 | L83: =IF(L47=0,0,L82/L47) -> 0.15959619
I85: Cifras en MUS$ | J85: Lunch | K85: 2024 | L85: 2025 | M85: 2026
I86: Estocastical flow | K86: =Flujos!B50 -> 555.0989 | L86: =Flujos!C50 -> 936.42491 | M86: =Flujos!D50 -> 501.28332
I87: Inversión inicial y Desech. | J87: =SUM(J60:J61) -> -182.63922 | K87: =SUM(K60:K61) -> 0 | L87: =SUM(L60:L61) -> 0 | M87: =SUM(M60:M61) -> 182.63922
I88: Impuestos | K88: =-K62 -> -91.088597 | L88: =-L62 -> -282.58071 | M88: =-M62 -> -459.17027
I89: Flow | J89: =J87 -> -182.63922 | K89: =K86+K87+K88 -> 464.0103 | L89: =L86+L87+L88 -> 653.8442 | M89: =M86+M87+M88 -> 224.75227
F92: VNA | G92: =NPV((Vaciado!D29-Vaciado!D28),'Para reporte'!K89:M89)+'Para reporte'!J89 -> 716.63374 | I92: Cifras en MUS$ | J92: Lunch | K92: 2024 | L92: 2025 | M92: 2026
I93: Total de Ingresos | K93: =K55+J136 -> 4146.0954 | L93: =L55+K136 -> 9777.2861 | M93: =M55+L136 -> 15525.565
I94: Costos Operacionales | K94: =K56 -> 121.79428 | L94: =L56 -> 268.29195 | M94: =M56 -> 389.09051
I95: Gastos del CAC | K95: =K57+J137 -> 956.14301 | L95: =L57+K137 -> 2011.487 | M95: =M57+L137 -> 3063.6883
I96: Gastos de Adm. y ventas | K96: =K58 -> 328.98422 | L96: =L58 -> 429.33039 | M96: =M58 -> 529.95657
I97: EBITDA | K97: =K93-K94-K95-K96 -> 2739.1739 | L97: =L93-L94-L95-L96 -> 7068.1768 | M97: =M93-M94-M95-M96 -> 11542.83
I98: Inversión por recuperar | J98: =-Vaciado!D20 -> 0
I99: Cuentas Socios | J99: =-Vaciado!D21 -> -70.222222
I100: Pasivos de L. Plazo | J100: =-Vaciado!D22 -> 0
I101: Capital de Trabajo | J101: =-Dashboard!C32 -> -524.80239 | M101: =-J101 -> 524.80239
I102: V. de desecho
I103: Impuesto a la renta | K103: =IF(K97<0,0,K97*Vaciado!I44) -> 342.39674 | L103: =IF(L97<0,0,L97*Vaciado!J44) -> 1060.2265 | M103: =IF(M97<0,0,M97*Vaciado!K44) -> 1731.4244
I104: Flujo de Caja | J104: =SUM(J98:J101) -> -595.02462 | K104: =K97-K103 -> 2396.7772 | L104: =L97-L103 -> 6007.9503 | M104: =M97-M103+M101+M102 -> 10336.208
I107: Cifras en MUS$ | J107: 2024 | K107: % del total
I108: Costos Operacionales | J108: =J48 -> 121.79428 | K108: =J108/$J$112 -> 0.14571212
I109: Gastos de Adm. y ventas | J109: =J50 -> 328.98422 | K109: =J109/$J$112 -> 0.3935898
...

Sheet Flujos
E1: 1 | F1: 2 | G1: 3 | H1: 4 | I1: 5 | J1: 6 | K1: 7 | L1: 8 | M1: 9 | N1: 10 | O1: 11 | P1: 12 | Q1: 13 | R1: 14 | S1: 15 | T1: 16 | U1: 17 | V1: 18 | W1: 19 | X1: 20 | Y1: 21 | Z1: 22 | AA1: 23 | AB1: 24 | AC1: 25 | AD1: 26 | AE1: 27 | AF1: 28 | AG1: 29 | AH1: 30 | AI1: 31 | AJ1: 32 | AK1: 33 | AL1: 34 | AM1: 35 | AN1: 36
E2: 2024 | Q2: 2025 | AC2: 2026
B3: 2024 | C3: 2025 | D3: 2026 | E3: Enero | F3: Febrero | G3: Marzo | H3: Abril | I3: Mayo | J3: Junio | K3: Julio | L3: Agosto | M3: Septiembre | N3: Octubre | O3: Noviembre | P3: Diciembre | Q3: Enero | R3: Febrero | S3: Marzo | T3: Abril | U3: Mayo | V3: Junio | W3: Julio | X3: Agosto | Y3: Septiembre | Z3: Octubre | AA3: Noviembre | AB3: Diciembre | AC3: Enero | AD3: Febrero | AE3: Marzo | AF3: Abril | AG3: Mayo | AH3: Junio | AI3: Julio | AJ3: Agosto | AK3: Septiembre | AL3: Octubre | AM3: Noviembre | AN3: Diciembre
A4: Clientes nuevos | B4: =SUM(E4:P4) -> 260 | C4: =SUM(Q4:AB4) -> 515 | D4: =SUM(AC4:AN4) -> 814 | E4: =P.Comercial!H10 -> 1 | F4: =P.Comercial!I10 -> 0 | G4: =P.Comercial!J10 -> 2 | H4: =P.Comercial!K10 -> 7 | I4: =P.Comercial!L10 -> 19 | J4: =P.Comercial!M10 -> 19 | K4: =P.Comercial!N10 -> 30 | L4: =P.Comercial!O10 -> 34 | ... AN4: =P.Comercial!AQ10 -> 96
A5: Clientes Ex. Piloto | B5: =SUM(E5:P5) -> 0 | C5: =SUM(Q5:AB5) -> 0 | D5: =SUM(AC5:AN5) -> 0 | E5: =P.Comercial!H24 -> 0 | F5: =P.Comercial!I24 -> 0 | G5: =P.Comercial!J24 -> 0 | H5: =P.Comercial!K24 -> 0 | I5: =P.Comercial!L24 -> 0 | J5: =P.Comercial!M24 -> 0 | K5: =P.Comercial!N24 -> 0 | L5: =P.Comercial!O24 -> 0 | ... AN5: =P.Comercial!AQ24 -> 0
A6: Churn | B6: =SUM(E6:P6) -> -130 | C6: =SUM(Q6:AB6) -> -257.5 | D6: =SUM(AC6:AN6) -> -407 | E6: =P.Comercial!H26 -> -0.5 | F6: =P.Comercial!I26 -> 0 | G6: =P.Comercial!J26 -> -1 | H6: =P.Comercial!K26 -> -3.5 | I6: =P.Comercial!L26 -> -9.5 | J6: =P.Comercial!M26 -> -9.5 | K6: =P.Comercial!N26 -> -15 | L6: =P.Comercial!O26 -> -17 | ... AN6: =P.Comercial!AQ26 -> -48
A7: Base de clientes | B7: =SUM(E7:P7) -> 130 | C7: =SUM(Q7:AB7) -> 257.5 | D7: =SUM(AC7:AN7) -> 407 | E7: =E4+E5+E6 -> 0.5 | F7: =F4+F5+F6 -> 0 | G7: =G4+G5+G6 -> 1 | H7: =H4+H5+H6 -> 3.5 | I7: =I4+I5+I6 -> 9.5 | J7: =J4+J5+J6 -> 9.5 | K7: =K4+K5+K6 -> 15 | L7: =L4+L5+L6 -> 17 | ... AN7: =AN4+AN5+AN6 -> 48
A8: Clientes acumulados | B8: =P8 -> 130 | C8: =AB8 -> 387.5 | D8: =AN8 -> 794.5 | E8: =E7 -> 0.5 | F8: =E8+F7 -> 0.5 | G8: =F8+G7 -> 1.5 | H8: =G8+H7 -> 5 | I8: =H8+I7 -> 14.5 | J8: =I8+J7 -> 24 | K8: =J8+K7 -> 39 | L8: =K8+L7 -> 56 | M8: =L8+M7 -> 73 | ... AN8: =AM8+AN7 -> 794.5
A9: Servicios recurrentes | B9: =SUM(E9:P9) -> 0.5 | C9: =SUM(Q9:AB9) -> 149 | D9: =SUM(AC9:AN9) -> 415.5 | E9: =P.Comercial!H30 -> 0 | F9: =P.Comercial!I30 -> 0 | G9: =P.Comercial!J30 -> 0 | H9: =P.Comercial!K30 -> 0 | I9: =P.Comercial!L30 -> 0 | J9: =P.Comercial!M30 -> 0 | K9: =P.Comercial!N30 -> 0 | L9: =P.Comercial!O30 -> 0 | ... AN9: =P.Comercial!AQ30 -> 47.5
A10: Total de servicios | B10: =SUM(E10:P10) -> 260.5 | C10: =SUM(Q10:AB10) -> 664 | D10: =SUM(AC10:AN10) -> 1229.5 | E10: =E4+E5+E9 -> 1 | F10: =F4+F5+F9 -> 0 | G10: =G4+G5+G9 -> 2 | H10: =H4+H5+H9 -> 7 | I10: =I4+I5+I9 -> 19 | J10: =J4+J5+J9 -> 19 | K10: =K4+K5+K9 -> 30 | L10: =L4+L5+L9 -> 34 | ... AN10: =AN4+AN5+AN9 -> 143.5
A12: Total de Ingresos | B12: =SUM(E12:P12) -> 1564.5643 | C12: =SUM(Q12:AB12) -> 3364.821 | D12: =SUM(AC12:AN12) -> 5160.3447 | E12: =P.Comercial!H52 -> 1.2333333 | F12: =P.Comercial!I52 -> 0 | G12: =P.Comercial!J52 -> 5.3444444 | H12: =P.Comercial!K52 -> 67.422222 | I12: =P.Comercial!L52 -> 112.64444 | J12: =P.Comercial!M52 -> 112.64444 | K12: =P.Comercial!N52 -> 203.91111 | L12: =P.Comercial!O52 -> 208.84444 | ... AN12: =P.Comercial!AQ52 -> 542.34313
A14: =Vaciado!C36 -> Servidor por cliente: | B14: =SUM(E14:P14) -> 32.5 | C14: =SUM(Q14:AB14) -> 64.375 | D14: =SUM(AC14:AN14) -> 101.75 | E14: =(E4+E5)*(Vaciado!$D$36/1000) -> 0.125 | F14: =(F4+F5)*(Vaciado!$D$36/1000) -> 0 | G14: =(G4+G5)*(Vaciado!$D$36/1000) -> 0.25 | H14: =(H4+H5)*(Vaciado!$D$36/1000) -> 0.875 | I14: =(I4+I5)*(Vaciado!$D$36/1000) -> 2.375 | J14: =(J4+J5)*(Vaciado!$D$36/1000) -> 2.375 | K14: =(K4+K5)*(Vaciado!$D$36/1000) -> 3.75 | L14: =(L4+L5)*(Vaciado!$D$36/1000) -> 4.25 | ... AN14: =(AN4+AN5)*(Vaciado!$D$36/1000) -> 12
A15: =Vaciado!C60 -> Soporte | B15: =SUM(E15:P15) -> 0 | C15: =SUM(Q15:AB15) -> 21 | D15: =SUM(AC15:AN15) -> 22.05 | E15: =(INT(E8/Vaciado!$I$60)+1)*(IF(Vaciado!$F$60>Flujos!E1,0,Vaciado!$E$60)) -> 0 | F15: =(INT(F8/Vaciado!$I$60)+1)*(IF(Vaciado!$F$60>Flujos!F1,0,Vaciado!$E$60)) -> 0 | G15: =(INT(G8/Vaciado!$I$60)+1)*(IF(Vaciado!$F$60>Flujos!G1,0,Vaciado!$E$60)) -> 0 | H15: =(INT(H8/Vaciado!$I$60)+1)*(IF(Vaciado!$F$60>Flujos!H1,0,Vaciado!$E$60)) -> 0 | I15: =(INT(I8/Vaciado!$I$60)+1)*(IF(Vaciado!$F$60>Flujos!I1,0,Vaciado!$E$60)) -> 0 | J15: =(INT(J8/Vaciado!$I$60)+1)*(IF(Vaciado!$F$60>Flujos!J1,0,Vaciado!$E$60)) -> 0 | K15: =(INT(K8/Vaciado!$I$60)+1)*(IF(Vaciado!$F$60>Flujos!K1,0,Vaciado!$E$60)) -> 0 | L15: =(INT(L8/Vaciado!$I$60)+1)*(IF(Vaciado!$F$60>Flujos!L1,0,Vaciado!$E$60)) -> 0 | ... P15: =(INT(P8/Vaciado!$I$60)+1)*(IF(Vaciado!$F$60>Flujos!P1,0,Vaciado!$E$60)) -> 0 | Q15: =(INT(Q8/Vaciado!$I$60)+1)*(IF(Vaciado!$F$60>Flujos!Q1,0,(Vaciado!$E$60*(1+Vaciado!$G$60)))) -> 1.75 | R15: =(INT(R8/Vaciado!$I$60)+1)*(IF(Vaciado!$F$60>Flujos!R1,0,(Vaciado!$E$60*(1+Vaciado!$G$60)))) -> 1.75 | S15: =(INT(S8/Vaciado!$I$60)+1)*(IF(Vaciado!$F$60>Flujos!S1,0,(Vaciado!$E$60*(1+Vaciado!$G$60)))) -> 1.75 | T15: =(INT(T8/Vaciado!$I$60)+1)*(IF(Vaciado!$F$60>Flujos!T1,0,(Vaciado!$E$60*(1+Vaciado!$G$60)))) -> 1.75 | U15: =(INT(U8/Vaciado!$I$60)+1)*(IF(Vaciado!$F$60>Flujos!U1,0,(Vaciado!$E$60*(1+Vaciado!$G$60)))) -> 1.75 | V15: =(INT(V8/Vaciado!$I$60)+1)*(IF(Vaciado!$F$60>Flujos!V1,0,(Vaciado!$E$60*(1+Vaciado!$G$60)))) -> 1.75 | W15: =(INT(W8/Vaciado!$I$60)+1)*(IF(Vaciado!$F$60>Flujos!W1,0,(Vaciado!$E$60*(1+Vaciado!$G$60)))) -> 1.75 | X15: =(INT(X8/Vaciado!$I$60)+1)*(IF(Vaciado!$F$60>Flujos!X1,0,(Vaciado!$E$60*(1+Vaciado!$G$60)))) -> 1.75 | ... AB15: =(INT(AB8/Vaciado!$I$60)+1)*(IF(Vaciado!$F$60>Flujos!AB1,0,(Vaciado!$E$60*(1+Vaciado!$G$60)))) -> 1.75 | AC15: =(INT(AC8/Vaciado!$I$60)+1)*(IF(Vaciado!$F$60>Flujos!AC1,0,(Vaciado!$E$60*((1+Vaciado!$G$60)^2)))) -> 1.8375 | AD15: =(INT(AD8/Vaciado!$I$60)+1)*(IF(Vaciado!$F$60>Flujos!AD1,0,(Vaciado!$E$60*((1+Vaciado!$G$60)^2)))) -> 1.8375 | AE15: =(INT(AE8/Vaciado!$I$60)+1)*(IF(Vaciado!$F$60>Flujos!AE1,0,(Vaciado!$E$60*((1+Vaciado!$G$60)^2)))) -> 1.8375 | AF15: =(INT(AF8/Vaciado!$I$60)+1)*(IF(Vaciado!$F$60>Flujos!AF1,0,(Vaciado!$E$60*((1+Vaciado!$G$60)^2)))) -> 1.8375 | AG15: =(INT(AG8/Vaciado!$I$60)+1)*(IF(Vaciado!$F$60>Flujos!AG1,0,(Vaciado!$E$60*((1+Vaciado!$G$60)^2)))) -> 1.8375 | AH15: =(INT(AH8/Vaciado!$I$60)+1)*(IF(Vaciado!$F$60>Flujos!AH1,0,(Vaciado!$E$60*((1+Vaciado!$G$60)^2)))) -> 1.8375 | AI15: =(INT(AI8/Vaciado!$I$60)+1)*(IF(Vaciado!$F$60>Flujos!AI1,0,(Vaciado!$E$60*((1+Vaciado!$G$60)^2)))) -> 1.8375 | AJ15: =(INT(AJ8/Vaciado!$I$60)+1)*(IF(Vaciado!$F$60>Flujos!AJ1,0,(Vaciado!$E$60*((1+Vaciado!$G$60)^2)))) -> 1.8375 | ... AN15: =(INT(AN8/Vaciado!$I$60)+1)*(IF(Vaciado!$F$60>Flujos!AN1,0,(Vaciado!$E$60*((1+Vaciado!$G$60)^2)))) -> 1.8375
A16: =Vaciado!C61 -> Operador | B16: =SUM(E16:P16) -> 13.333333 | C16: =SUM(Q16:AB16) -> 14 | D16: =SUM(AC16:AN16) -> 14.7 | E16: =(INT(E8/Vaciado!$I$61)+1)*(IF(Vaciado!$F$61>Flujos!E1,0,Vaciado!$E$61)) -> 1.1111111 | F16: =(INT(F8/Vaciado!$I$61)+1)*(IF(Vaciado!$F$61>Flujos!F1,0,Vaciado!$E$61)) -> 1.1111111 | G16: =(INT(G8/Vaciado!$I$61)+1)*(IF(Vaciado!$F$61>Flujos!G1,0,Vaciado!$E$61)) -> 1.1111111 | H16: =(INT(H8/Vaciado!$I$61)+1)*(IF(Vaciado!$F$61>Flujos!H1,0,Vaciado!$E$61)) -> 1.1111111 | I16: =(INT(I8/Vaciado!$I$61)+1)*(IF(Vaciado!$F$61>Flujos!I1,0,Vaciado!$E$61)) -> 1.1111111 | J16: =(INT(J8/Vaciado!$I$61)+1)*(IF(Vaciado!$F$61>Flujos!J1,0,Vaciado!$E$61)) -> 1.1111111 | K16: =(INT(K8/Vaciado!$I$61)+1)*(IF(Vaciado!$F$61>Flujos!K1,0,Vaciado!$E$61)) -> 1.1111111 | L16: =(INT(L8/Vaciado!$I$61)+1)*(IF(Vaciado!$F$61>Flujos!L1,0,Vaciado!$E$61)) -> 1.1111111 | ... P16: =(INT(P8/Vaciado!$I$61)+1)*(IF(Vaciado!$F$61>Flujos!P1,0,Vaciado!$E$61)) -> 1.1111111 | Q16: =(INT(Q8/Vaciado!$I$61)+1)*(IF(Vaciado!$F$61>Flujos!Q1,0,(Vaciado!$E$61*(1+Vaciado!$G$61)))) -> 1.1666667 | R16: =(INT(R8/Vaciado!$I$61)+1)*(IF(Vaciado!$F$61>Flujos!R1,0,(Vaciado!$E$61*(1+Vaciado!$G$61)))) -> 1.1666667 | S16: =(INT(S8/Vaciado!$I$61)+1)*(IF(Vaciado!$F$61>Flujos!S1,0,(Vaciado!$E$61*(1+Vaciado!$G$61)))) -> 1.1666667 | T16: =(INT(T8/Vaciado!$I$61)+1)*(IF(Vaciado!$F$61>Flujos!T1,0,(Vaciado!$E$61*(1+Vaciado!$G$61)))) -> 1.1666667 | U16: =(INT(U8/Vaciado!$I$61)+1)*(IF(Vaciado!$F$61>Flujos!U1,0,(Vaciado!$E$61*(1+Vaciado!$G$61)))) -> 1.1666667 | V16: =(INT(V8/Vaciado!$I$61)+1)*(IF(Vaciado!$F$61>Flujos!V1,0,(Vaciado!$E$61*(1+Vaciado!$G$61)))) -> 1.1666667 | W16: =(INT(W8/Vaciado!$I$61)+1)*(IF(Vaciado!$F$61>Flujos!W1,0,(Vaciado!$E$61*(1+Vaciado!$G$61)))) -> 1.1666667 | X16: =(INT(X8/Vaciado!$I$61)+1)*(IF(Vaciado!$F$61>Flujos!X1,0,(Vaciado!$E$61*(1+Vaciado!$G$61)))) -> 1.1666667 | ... AB16: =(INT(AB8/Vaciado!$I$61)+1)*(IF(Vaciado!$F$61>Flujos!AB1,0,(Vaciado!$E$61*(1+Vaciado!$G$61)))) -> 1.1666667 | AC16: =(INT(AC8/Vaciado!$I$61)+1)*(IF(Vaciado!$F$61>Flujos!AC1,0,(Vaciado!$E$61*((1+Vaciado!$G$61)^2)))) -> 1.225 | AD16: =(INT(AD8/Vaciado!$I$61)+1)*(IF(Vaciado!$F$61>Flujos!AD1,0,(Vaciado!$E$61*((1+Vaciado!$G$61)^2)))) -> 1.225 | AE16: =(INT(AE8/Vaciado!$I$61)+1)*(IF(Vaciado!$F$61>Flujos!AE1,0,(Vaciado!$E$61*((1+Vaciado!$G$61)^2)))) -> 1.225 | AF16: =(INT(AF8/Vaciado!$I$61)+1)*(IF(Vaciado!$F$61>Flujos!AF1,0,(Vaciado!$E$61*((1+Vaciado!$G$61)^2)))) -> 1.225 | AG16: =(INT(AG8/Vaciado!$I$61)+1)*(IF(Vaciado!$F$61>Flujos!AG1,0,(Vaciado!$E$61*((1+Vaciado!$G$61)^2)))) -> 1.225 | AH16: =(INT(AH8/Vaciado!$I$61)+1)*(IF(Vaciado!$F$61>Flujos!AH1,0,(Vaciado!$E$61*((1+Vaciado!$G$61)^2)))) -> 1.225 | AI16: =(INT(AI8/Vaciado!$I$61)+1)*(IF(Vaciado!$F$61>Flujos!AI1,0,(Vaciado!$E$61*((1+Vaciado!$G$61)^2)))) -> 1.225 | AJ16: =(INT(AJ8/Vaciado!$I$61)+1)*(IF(Vaciado!$F$61>Flujos!AJ1,0,(Vaciado!$E$61*((1+Vaciado!$G$61)^2)))) -> 1.225 | ... AN16: =(INT(AN8/Vaciado!$I$61)+1)*(IF(Vaciado!$F$61>Flujos!AN1,0,(Vaciado!$E$61*((1+Vaciado!$G$61)^2)))) -> 1.225
A17: =Vaciado!C62 -> Expertos Revisión | B17: =SUM(E17:P17) -> 5.5555556 | C17: =SUM(Q17:AB17) -> 17.5 | D17: =SUM(AC17:AN17) -> 18.375 | E17: =IF(Vaciado!$F$62>Flujos!E1,0,Vaciado!$E$62) -> 0 | F17: =IF(Vaciado!$F$62>Flujos!F1,0,Vaciado!$E$62) -> 0 | G17: =IF(Vaciado!$F$62>Flujos!G1,0,Vaciado!$E$62) -> 0 | H17: =IF(Vaciado!$F$62>Flujos!H1,0,Vaciado!$E$62) -> 0 | I17: =IF(Vaciado!$F$62>Flujos!I1,0,Vaciado!$E$62) -> 0 | J17: =IF(Vaciado!$F$62>Flujos!J1,0,Vaciado!$E$62) -> 0 | K17: =IF(Vaciado!$F$62>Flujos!K1,0,Vaciado!$E$62) -> 0 | L17: =IF(Vaciado!$F$62>Flujos!L1,0,Vaciado!$E$62) -> 0 | ... P17: =IF(Vaciado!$F$62>Flujos!P1,0,Vaciado!$E$62) -> 1.3888889 | Q17: =IF(Vaciado!$F$62>Flujos!Q1,0,(Vaciado!$E$62*(1+Vaciado!$G$62))) -> 1.4583333 | R17: =IF(Vaciado!$F$62>Flujos!R1,0,(Vaciado!$E$62*(1+Vaciado!$G$62))) -> 1.4583333 | S17: =IF(Vaciado!$F$62>Flujos!S1,0,(Vaciado!$E$62*(1+Vaciado!$G$62))) -> 1.4583333 | T17: =IF(Vaciado!$F$62>Flujos!T1,0,(Vaciado!$E$62*(1+Vaciado!$G$62))) -> 1.4583333 | U17: =IF(Vaciado!$F$62>Flujos!U1,0,(Vaciado!$E$62*(1+Vaciado!$G$62))) -> 1.4583333 | V17: =IF(Vaciado!$F$62>Flujos!V1,0,(Vaciado!$E$62*(1+Vaciado!$G$62))) -> 1.4583333 | W17: =IF(Vaciado!$F$62>Flujos!W1,0,(Vaciado!$E$62*(1+Vaciado!$G$62))) -> 1.4583333 | X17: =IF(Vaciado!$F$62>Flujos!X1,0,(Vaciado!$E$62*(1+Vaciado!$G$62))) -> 1.4583333 | ... AB17: =IF(Vaciado!$F$62>Flujos!AB1,0,(Vaciado!$E$62*(1+Vaciado!$G$62))) -> 1.4583333 | AC17: =IF(Vaciado!$F$62>Flujos!AC1,0,(Vaciado!$E$62*((1+Vaciado!$G$62)^2))) -> 1.53125 | AD17: =IF(Vaciado!$F$62>Flujos!AD1,0,(Vaciado!$E$62*((1+Vaciado!$G$62)^2))) -> 1.53125 | AE17: =IF(Vaciado!$F$62>Flujos!AE1,0,(Vaciado!$E$62*((1+Vaciado!$G$62)^2))) -> 1.53125 | AF17: =IF(Vaciado!$F$62>Flujos!AF1,0,(Vaciado!$E$62*((1+Vaciado!$G$62)^2))) -> 1.53125 | AG17: =IF(Vaciado!$F$62>Flujos!AG1,0,(Vaciado!$E$62*((1+Vaciado!$G$62)^2))) -> 1.53125 | AH17: =IF(Vaciado!$F$62>Flujos!AH1,0,(Vaciado!$E$62*((1+Vaciado!$G$62)^2))) -> 1.53125 | AI17: =IF(Vaciado!$F$62>Flujos!AI1,0,(Vaciado!$E$62*((1+Vaciado!$G$62)^2))) -> 1.53125 | AJ17: =IF(Vaciado!$F$62>Flujos!AJ1,0,(Vaciado!$E$62*((1+Vaciado!$G$62)^2))) -> 1.53125 | ... AN17: =IF(Vaciado!$F$62>Flujos!AN1,0,(Vaciado!$E$62*((1+Vaciado!$G$62)^2))) -> 1.53125
A18: =Vaciado!C69 -> Comisión Operador | B18: =SUM(E18:P18) -> 15.645643 | C18: =SUM(Q18:AB18) -> 33.64821 | D18: =SUM(AC18:AN18) -> 51.603447 | E18: =IF(Vaciado!$F$61>Flujos!E1,0,P.Comercial!H52*Vaciado!$D$69) -> 0.012333333 | F18: =IF(Vaciado!$F$61>Flujos!F1,0,P.Comercial!I52*Vaciado!$D$69) -> 0 | G18: =IF(Vaciado!$F$61>Flujos!G1,0,P.Comercial!J52*Vaciado!$D$69) -> 0.053444444 | H18: =IF(Vaciado!$F$61>Flujos!H1,0,P.Comercial!K52*Vaciado!$D$69) -> 0.67422222 | I18: =IF(Vaciado!$F$61>Flujos!I1,0,P.Comercial!L52*Vaciado!$D$69) -> 1.1264444 | J18: =IF(Vaciado!$F$61>Flujos!J1,0,P.Comercial!M52*Vaciado!$D$69) -> 1.1264444 | K18: =IF(Vaciado!$F$61>Flujos!K1,0,P.Comercial!N52*Vaciado!$D$69) -> 2.0391111 | L18: =IF(Vaciado!$F$61>Flujos!L1,0,P.Comercial!O52*Vaciado!$D$69) -> 2.0884444 | ... AN18: =IF(Vaciado!$F$61>Flujos!AN1,0,P.Comercial!AQ52*Vaciado!$D$69) -> 5.4234313
A19: =Vaciado!C70 -> Comisión CTO | B19: =SUM(E19:P19) -> 54.759751 | C19: =SUM(Q19:AB19) -> 117.76874 | D19: =SUM(AC19:AN19) -> 180.61206 | E19: =IF(Vaciado!$F$58>Flujos!E1,0,P.Comercial!H52*Vaciado!$D$70) -> 0.043166667 | F19: =IF(Vaciado!$F$58>Flujos!F1,0,P.Comercial!I52*Vaciado!$D$70) -> 0 | G19: =IF(Vaciado!$F$58>Flujos!G1,0,P.Comercial!J52*Vaciado!$D$70) -> 0.18705556 | H19: =IF(Vaciado!$F$58>Flujos!H1,0,P.Comercial!K52*Vaciado!$D$70) -> 2.3597778 | I19: =IF(Vaciado!$F$58>Flujos!I1,0,P.Comercial!L52*Vaciado!$D$70) -> 3.9425556 | J19: =IF(Vaciado!$F$58>Flujos!J1,0,P.Comercial!M52*Vaciado!$D$70) -> 3.9425556 | K19: =IF(Vaciado!$F$58>Flujos!K1,0,P.Comercial!N52*Vaciado!$D$70) -> 7.1368889 | L19: =IF(Vaciado!$F$58>Flujos!L1,0,P.Comercial!O52*Vaciado!$D$70) -> 7.3095556 | ... AN19: =IF(Vaciado!$F$58>Flujos!AN1,0,P.Comercial!AQ52*Vaciado!$D$70) -> 18.98201
A20: Total Costos Operacionales | B20: =SUM(B14:B19) -> 121.79428 | C20: =SUM(C14:C19) -> 268.29195 | D20: =SUM(D14:D19) -> 389.09051 | E20: =SUM(E14:E19) -> 1.2916111 | F20: =SUM(F14:F19) -> 1.1111111 | G20: =SUM(G14:G19) -> 1.6016111 | H20: =SUM(H14:H19) -> 5.0201111 | I20: =SUM(I14:I19) -> 8.5551111 | ... AN20: =SUM(AN14:AN19) -> 40.999191
A22: =Vaciado!C50 -> Viaticos y viajes: | B22: =SUM(E22:P22) -> 6.6666667 | C22: =SUM(Q22:AB22) -> 6.6666667 | D22: =SUM(AC22:AN22) -> 6.6666667 | E22: =Vaciado!$E$50 -> 0.55555556 | F22: =Vaciado!$E$50 -> 0.55555556 | G22: =Vaciado!$E$50 -> 0.55555556 | H22: =Vaciado!$E$50 -> 0.55555556 | I22: =Vaciado!$E$50 -> 0.55555556 | J22: =Vaciado!$E$50 -> 0.55555556 | K22: =Vaciado!$E$50 -> 0.55555556 | L22: =Vaciado!$E$50 -> 0.55555556 | ... AN22: =Vaciado!$E$50 -> 0.55555556
A23: =Vaciado!C56 -> CCO | B23: =SUM(E23:P23) -> 18.666667 | C23: =SUM(Q23:AB23) -> 19.6 | D23: =SUM(AC23:AN23) -> 20.58 | E23: =IF(Vaciado!$F$56>Flujos!E1,0,Vaciado!$E$56) -> 1.5555556 | F23: =IF(Vaciado!$F$56>Flujos!F1,0,Vaciado!$E$56) -> 1.5555556 | G23: =IF(Vaciado!$F$56>Flujos!G1,0,Vaciado!$E$56) -> 1.5555556 | H23: =IF(Vaciado!$F$56>Flujos!H1,0,Vaciado!$E$56) -> 1.5555556 | I23: =IF(Vaciado!$F$56>Flujos!I1,0,Vaciado!$E$56) -> 1.5555556 | J23: =IF(Vaciado!$F$56>Flujos!J1,0,Vaciado!$E$56) -> 1.5555556 | K23: =IF(Vaciado!$F$56>Flujos!K1,0,Vaciado!$E$56) -> 1.5555556 | L23: =IF(Vaciado!$F$56>Flujos!L1,0,Vaciado!$E$56) -> 1.5555556 | ... P23: =IF(Vaciado!$F$56>Flujos!P1,0,Vaciado!$E$56) -> 1.5555556 | Q23: =IF(Vaciado!$F$56>Flujos!Q1,0,(Vaciado!$E$56*(1+Vaciado!$G$56))) -> 1.6333333 | R23: =IF(Vaciado!$F$56>Flujos!R1,0,(Vaciado!$E$56*(1+Vaciado!$G$56))) -> 1.6333333 | S23: =IF(Vaciado!$F$56>Flujos!S1,0,(Vaciado!$E$56*(1+Vaciado!$G$56))) -> 1.6333333 | T23: =IF(Vaciado!$F$56>Flujos!T1,0,(Vaciado!$E$56*(1+Vaciado!$G$56))) -> 1.6333333 | U23: =IF(Vaciado!$F$56>Flujos!U1,0,(Vaciado!$E$56*(1+Vaciado!$G$56))) -> 1.6333333 | V23: =IF(Vaciado!$F$56>Flujos!V1,0,(Vaciado!$E$56*(1+Vaciado!$G$56))) -> 1.6333333 | W23: =IF(Vaciado!$F$56>Flujos!W1,0,(Vaciado!$E$56*(1+Vaciado!$G$56))) -> 1.6333333 | X23: =IF(Vaciado!$F$56>Flujos!X1,0,(Vaciado!$E$56*(1+Vaciado!$G$56))) -> 1.6333333 | ... AB23: =IF(Vaciado!$F$56>Flujos!AB1,0,(Vaciado!$E$56*(1+Vaciado!$G$56))) -> 1.6333333 | AC23: =IF(Vaciado!$F$56>Flujos!AC1,0,(Vaciado!$E$56*((1+Vaciado!$G$56)^2))) -> 1.715 | AD23: =IF(Vaciado!$F$56>Flujos!AD1,0,(Vaciado!$E$56*((1+Vaciado!$G$56)^2))) -> 1.715 | AE23: =IF(Vaciado!$F$56>Flujos!AE1,0,(Vaciado!$E$56*((1+Vaciado!$G$56)^2))) -> 1.715 | AF23: =IF(Vaciado!$F$56>Flujos!AF1,0,(Vaciado!$E$56*((1+Vaciado!$G$56)^2))) -> 1.715 | AG23: =IF(Vaciado!$F$56>Flujos!AG1,0,(Vaciado!$E$56*((1+Vaciado!$G$56)^2))) -> 1.715 | AH23: =IF(Vaciado!$F$56>Flujos!AH1,0,(Vaciado!$E$56*((1+Vaciado!$G$56)^2))) -> 1.715 | AI23: =IF(Vaciado!$F$56>Flujos!AI1,0,(Vaciado!$E$56*((1+Vaciado!$G$56)^2))) -> 1.715 | AJ23: =IF(Vaciado!$F$56>Flujos!AJ1,0,(Vaciado!$E$56*((1+Vaciado!$G$56)^2))) -> 1.715 | ... AN23: =IF(Vaciado!$F$56>Flujos!AN1,0,(Vaciado!$E$56*((1+Vaciado!$G$56)^2))) -> 1.715
A24: =Vaciado!C57 -> KAM | B24: =SUM(E24:P24) -> 16 | C24: =SUM(Q24:AB24) -> 16.8 | D24: =SUM(AC24:AN24) -> 17.64 | E24: =(INT(E8/Vaciado!$I$57)+1)*(IF(Vaciado!$F$57>Flujos!E1,0,Vaciado!$E$57)) -> 1.3333333 | F24: =(INT(F8/Vaciado!$I$57)+1)*(IF(Vaciado!$F$57>Flujos!F1,0,Vaciado!$E$57)) -> 1.3333333 | G24: =(INT(G8/Vaciado!$I$57)+1)*(IF(Vaciado!$F$57>Flujos!G1,0,Vaciado!$E$57)) -> 1.3333333 | H24: =(INT(H8/Vaciado!$I$57)+1)*(IF(Vaciado!$F$57>Flujos!H1,0,Vaciado!$E$57)) -> 1.3333333 | I24: =(INT(I8/Vaciado!$I$57)+1)*(IF(Vaciado!$F$57>Flujos!I1,0,Vaciado!$E$57)) -> 1.3333333 | J24: =(INT(J8/Vaciado!$I$57)+1)*(IF(Vaciado!$F$57>Flujos!J1,0,Vaciado!$E$57)) -> 1.3333333 | K24: =(INT(K8/Vaciado!$I$57)+1)*(IF(Vaciado!$F$57>Flujos!K1,0,Vaciado!$E$57)) -> 1.3333333 | L24: =(INT(L8/Vaciado!$I$57)+1)*(IF(Vaciado!$F$57>Flujos!L1,0,Vaciado!$E$57)) -> 1.3333333 | ... P24: =(INT(P8/Vaciado!$I$57)+1)*(IF(Vaciado!$F$57>Flujos!P1,0,Vaciado!$E$57)) -> 1.3333333 | Q24: =(INT(Q8/Vaciado!$I$57)+1)*(IF(Vaciado!$F$57>Flujos!Q1,0,(Vaciado!$E$57*(1+Vaciado!$G$57)))) -> 1.4 | R24: =(INT(R8/Vaciado!$I$57)+1)*(IF(Vaciado!$F$57>Flujos!R1,0,(Vaciado!$E$57*(1+Vaciado!$G$57)))) -> 1.4 | S24: =(INT(S8/Vaciado!$I$57)+1)*(IF(Vaciado!$F$57>Flujos!S1,0,(Vaciado!$E$57*(1+Vaciado!$G$57)))) -> 1.4 | T24: =(INT(T8/Vaciado!$I$57)+1)*(IF(Vaciado!$F$57>Flujos!T1,0,(Vaciado!$E$57*(1+Vaciado!$G$57)))) -> 1.4 | U24: =(INT(U8/Vaciado!$I$57)+1)*(IF(Vaciado!$F$57>Flujos!U1,0,(Vaciado!$E$57*(1+Vaciado!$G$57)))) -> 1.4 | V24: =(INT(V8/Vaciado!$I$57)+1)*(IF(Vaciado!$F$57>Flujos!V1,0,(Vaciado!$E$57*(1+Vaciado!$G$57)))) -> 1.4 | W24: =(INT(W8/Vaciado!$I$57)+1)*(IF(Vaciado!$F$57>Flujos!W1,0,(Vaciado!$E$57*(1+Vaciado!$G$57)))) -> 1.4 | X24: =(INT(X8/Vaciado!$I$57)+1)*(IF(Vaciado!$F$57>Flujos!X1,0,(Vaciado!$E$57*(1+Vaciado!$G$57)))) -> 1.4 | ... AB24: =(INT(AB8/Vaciado!$I$57)+1)*(IF(Vaciado!$F$57>Flujos!AB1,0,(Vaciado!$E$57*(1+Vaciado!$G$57)))) -> 1.4 | AC24: =(INT(AC8/Vaciado!$I$57)+1)*(IF(Vaciado!$F$57>Flujos!AC1,0,(Vaciado!$E$57*((1+Vaciado!$G$57)^2)))) -> 1.47 | AD24: =(INT(AD8/Vaciado!$I$57)+1)*(IF(Vaciado!$F$57>Flujos!AD1,0,(Vaciado!$E$57*((1+Vaciado!$G$57)^2)))) -> 1.47 | AE24: =(INT(AE8/Vaciado!$I$57)+1)*(IF(Vaciado!$F$57>Flujos!AE1,0,(Vaciado!$E$57*((1+Vaciado!$G$57)^2)))) -> 1.47 | AF24: =(INT(AF8/Vaciado!$I$57)+1)*(IF(Vaciado!$F$57>Flujos!AF1,0,(Vaciado!$E$57*((1+Vaciado!$G$57)^2)))) -> 1.47 | AG24: =(INT(AG8/Vaciado!$I$57)+1)*(IF(Vaciado!$F$57>Flujos!AG1,0,(Vaciado!$E$57*((1+Vaciado!$G$57)^2)))) -> 1.47 | AH24: =(INT(AH8/Vaciado!$I$57)+1)*(IF(Vaciado!$F$57>Flujos!AH1,0,(Vaciado!$E$57*((1+Vaciado!$G$57)^2)))) -> 1.47 | AI24: =(INT(AI8/Vaciado!$I$57)+1)*(IF(Vaciado!$F$57>Flujos!AI1,0,(Vaciado!$E$57*((1+Vaciado!$G$57)^2)))) -> 1.47 | AJ24: =(INT(AJ8/Vaciado!$I$57)+1)*(IF(Vaciado!$F$57>Flujos!AJ1,0,(Vaciado!$E$57*((1+Vaciado!$G$57)^2)))) -> 1.47 | ... AN24: =(INT(AN8/Vaciado!$I$57)+1)*(IF(Vaciado!$F$57>Flujos!AN1,0,(Vaciado!$E$57*((1+Vaciado!$G$57)^2)))) -> 1.47
A25: =Vaciado!C72 -> Comisión CCO | B25: =SUM(E25:P25) -> 54.529529 | C25: =SUM(Q25:AB25) -> 117.76874 | D25: =SUM(AC25:AN25) -> 180.61206 | E25: =IF(E26=0,IF(IF(Vaciado!$F$57>Flujos!E1,0,(IF(Flujos!E12<Vaciado!$H$68,0,P.Comercial!H52*Vaciado!$F$72)))>E12*Vaciado!$G$69,Flujos!E12*Vaciado!$G$69,IF(Vaciado!$F$57>Flujos!E1,0,(IF(Flujos!E12<Vaciado!$H$68,0,P.Comercial!H52*Vaciado!$F$72)))),IF(IF(Vaciado!$F$57>Flujos!E1,0,(IF(Flujos!E12<Vaciado!$H$68,0,P.Comercial!H52*Vaciado!$D$72)))>E12*Vaciado!$G$69,Flujos!E12*Vaciado!$G$69,IF(Vaciado!$F$57>Flujos!E1,0,(IF(Flujos!E12<Vaciado!$H$68,0,P.Comercial!H52*Vaciado!$D$72))))) -> 0 | F25: =IF(F26=0,IF(IF(Vaciado!$F$57>Flujos!F1,0,(IF(Flujos!F12<Vaciado!$H$68,0,P.Comercial!I52*Vaciado!$F$72)))>F12*Vaciado!$G$69,Flujos!F12*Vaciado!$G$69,IF(Vaciado!$F$57>Flujos!F1,0,(IF(Flujos!F12<Vaciado!$H$68,0,P.Comercial!I52*Vaciado!$F$72)))),IF(IF(Vaciado!$F$57>Flujos!F1,0,(IF(Flujos!F12<Vaciado!$H$68,0,P.Comercial!I52*Vaciado!$D$72)))>F12*Vaciado!$G$69,Flujos!F12*Vaciado!$G$69,IF(Vaciado!$F$57>Flujos!F1,0,(IF(Flujos!F12<Vaciado!$H$68,0,P.Comercial!I52*Vaciado!$D$72))))) -> 0 | G25: =IF(G26=0,IF(IF(Vaciado!$F$57>Flujos!G1,0,(IF(Flujos!G12<Vaciado!$H$68,0,P.Comercial!J52*Vaciado!$F$72)))>G12*Vaciado!$G$69,Flujos!G12*Vaciado!$G$69,IF(Vaciado!$F$57>Flujos!G1,0,(IF(Flujos!G12<Vaciado!$H$68,0,P.Comercial!J52*Vaciado!$F$72)))),IF(IF(Vaciado!$F$57>Flujos!G1,0,(IF(Flujos!G12<Vaciado!$H$68,0,P.Comercial!J52*Vaciado!$D$72)))>G12*Vaciado!$G$69,Flujos!G12*Vaciado!$G$69,IF(Vaciado!$F$57>Flujos!G1,0,(IF(Flujos!G12<Vaciado!$H$68,0,P.Comercial!J52*Vaciado!$D$72))))) -> 0 | H25: =IF(H26=0,IF(IF(Vaciado!$F$57>Flujos!H1,0,(IF(Flujos!H12<Vaciado!$H$68,0,P.Comercial!K52*Vaciado!$F$72)))>H12*Vaciado!$G$69,Flujos!H12*Vaciado!$G$69,IF(Vaciado!$F$57>Flujos!H1,0,(IF(Flujos!H12<Vaciado!$H$68,0,P.Comercial!K52*Vaciado!$F$72)))),IF(IF(Vaciado!$F$57>Flujos!H1,0,(IF(Flujos!H12<Vaciado!$H$68,0,P.Comercial!K52*Vaciado!$D$72)))>H12*Vaciado!$G$69,Flujos!H12*Vaciado!$G$69,IF(Vaciado!$F$57>Flujos!H1,0,(IF(Flujos!H12<Vaciado!$H$68,0,P.Comercial!K52*Vaciado!$D$72))))) -> 2.3597778 | I25: =IF(I26=0,IF(IF(Vaciado!$F$57>Flujos!I1,0,(IF(Flujos!I12<Vaciado!$H$68,0,P.Comercial!L52*Vaciado!$F$72)))>I12*Vaciado!$G$69,Flujos!I12*Vaciado!$G$69,IF(Vaciado!$F$57>Flujos!I1,0,(IF(Flujos!I12<Vaciado!$H$68,0,P.Comercial!L52*Vaciado!$F$72)))),IF(IF(Vaciado!$F$57>Flujos!I1,0,(IF(Flujos!I12<Vaciado!$H$68,0,P.Comercial!L52*Vaciado!$D$72)))>I12*Vaciado!$G$69,Flujos!I12*Vaciado!$G$69,IF(Vaciado!$F$57>Flujos!I1,0,(IF(Flujos!I12<Vaciado!$H$68,0,P.Comercial!L52*Vaciado!$D$72))))) -> 3.9425556 | J25: =IF(J26=0,IF(IF(Vaciado!$F$57>Flujos!J1,0,(IF(Flujos!J12<Vaciado!$H$68,0,P.Comercial!M52*Vaciado!$F$72)))>J12*Vaciado!$G$69,Flujos!J12*Vaciado!$G$69,IF(Vaciado!$F$57>Flujos!J1,0,(IF(Flujos!J12<Vaciado!$H$68,0,P.Comercial!M52*Vaciado!$F$72)))),IF(IF(Vaciado!$F$57>Flujos!J1,0,(IF(Flujos!J12<Vaciado!$H$68,0,P.Comercial!M52*Vaciado!$D$72)))>J12*Vaciado!$G$69,Flujos!J12*Vaciado!$G$69,IF(Vaciado!$F$57>Flujos!J1,0,(IF(Flujos!J12<Vaciado!$H$68,0,P.Comercial!M52*Vaciado!$D$72))))) -> 3.9425556 | K25: =IF(K26=0,IF(IF(Vaciado!$F$57>Flujos!K1,0,(IF(Flujos!K12<Vaciado!$H$68,0,P.Comercial!N52*Vaciado!$F$72)))>K12*Vaciado!$G$69,Flujos!K12*Vaciado!$G$69,IF(Vaciado!$F$57>Flujos!K1,0,(IF(Flujos!K12<Vaciado!$H$68,0,P.Comercial!N52*Vaciado!$F$72)))),IF(IF(Vaciado!$F$57>Flujos!K1,0,(IF(Flujos!K12<Vaciado!$H$68,0,P.Comercial!N52*Vaciado!$D$72)))>K12*Vaciado!$G$69,Flujos!K12*Vaciado!$G$69,IF(Vaciado!$F$57>Flujos!K1,0,(IF(Flujos!K12<Vaciado!$H$68,0,P.Comercial!N52*Vaciado!$D$72))))) -> 7.1368889 | L25: =IF(L26=0,IF(IF(Vaciado!$F$57>Flujos!L1,0,(IF(Flujos!L12<Vaciado!$H$68,0,P.Comercial!O52*Vaciado!$F$72)))>L12*Vaciado!$G$69,Flujos!L12*Vaciado!$G$69,IF(Vaciado!$F$57>Flujos!L1,0,(IF(Flujos!L12<Vaciado!$H$68,0,P.Comercial!O52*Vaciado!$F$72)))),IF(IF(Vaciado!$F$57>Flujos!L1,0,(IF(Flujos!L12<Vaciado!$H$68,0,P.Comercial!O52*Vaciado!$D$72)))>L12*Vaciado!$G$69,Flujos!L12*Vaciado!$G$69,IF(Vaciado!$F$57>Flujos!L1,0,(IF(Flujos!L12<Vaciado!$H$68,0,P.Comercial!O52*Vaciado!$D$72))))) -> 7.3095556 | ... AN25: =IF(AN26=0,IF(IF(Vaciado!$F$57>Flujos!AN1,0,(IF(Flujos!AN12<Vaciado!$H$68,0,P.Comercial!AQ52*Vaciado!$F$72)))>AN12*Vaciado!$G$69,Flujos!AN12*Vaciado!$G$69,IF(Vaciado!$F$57>Flujos!AN1,0,(IF(Flujos!AN12<Vaciado!$H$68,0,P.Comercial!AQ52*Vaciado!$F$72)))),IF(IF(Vaciado!$F$57>Flujos!AN1,0,(IF(Flujos!AN12<Vaciado!$H$68,0,P.Comercial!AQ52*Vaciado!$D$72)))>AN12*Vaciado!$G$69,Flujos!AN12*Vaciado!$G$69,IF(Vaciado!$F$57>Flujos!AN1,0,(IF(Flujos!AN12<Vaciado!$H$68,0,P.Comercial!AQ52*Vaciado!$D$72))))) -> 18.98201
A26: =Vaciado!C71 -> Comisión KAM | B26: =SUM(E26:P26) -> 54.529529 | C26: =SUM(Q26:AB26) -> 117.76874 | D26: =SUM(AC26:AN26) -> 180.61206 | E26: =IF(IF(Vaciado!$F$57>Flujos!E1,0,(IF(Flujos!E12<Vaciado!$H$68,0,P.Comercial!H52*Vaciado!$D$71)))>E12*Vaciado!$G$69,Flujos!E12*Vaciado!$G$69,IF(Vaciado!$F$57>Flujos!E1,0,(IF(Flujos!E12<Vaciado!$H$68,0,P.Comercial!H52*Vaciado!$D$71)))) -> 0 | F26: =IF(IF(Vaciado!$F$57>Flujos!F1,0,(IF(Flujos!F12<Vaciado!$H$68,0,P.Comercial!I52*Vaciado!$D$71)))>F12*Vaciado!$G$69,Flujos!F12*Vaciado!$G$69,IF(Vaciado!$F$57>Flujos!F1,0,(IF(Flujos!F12<Vaciado!$H$68,0,P.Comercial!I52*Vaciado!$D$71)))) -> 0 | G26: =IF(IF(Vaciado!$F$57>Flujos!G1,0,(IF(Flujos!G12<Vaciado!$H$68,0,P.Comercial!J52*Vaciado!$D$71)))>G12*Vaciado!$G$69,Flujos!G12*Vaciado!$G$69,IF(Vaciado!$F$57>Flujos!G1,0,(IF(Flujos!G12<Vaciado!$H$68,0,P.Comercial!J52*Vaciado!$D$71)))) -> 0 | H26: =IF(IF(Vaciado!$F$57>Flujos!H1,0,(IF(Flujos!H12<Vaciado!$H$68,0,P.Comercial!K52*Vaciado!$D$71)))>H12*Vaciado!$G$69,Flujos!H12*Vaciado!$G$69,IF(Vaciado!$F$57>Flujos!H1,0,(IF(Flujos!H12<Vaciado!$H$68,0,P.Comercial!K52*Vaciado!$D$71)))) -> 2.3597778 | I26: =IF(IF(Vaciado!$F$57>Flujos!I1,0,(IF(Flujos!I12<Vaciado!$H$68,0,P.Comercial!L52*Vaciado!$D$71)))>I12*Vaciado!$G$69,Flujos!I12*Vaciado!$G$69,IF(Vaciado!$F$57>Flujos!I1,0,(IF(Flujos!I12<Vaciado!$H$68,0,P.Comercial!L52*Vaciado!$D$71)))) -> 3.9425556 | J26: =IF(IF(Vaciado!$F$57>Flujos!J1,0,(IF(Flujos!J12<Vaciado!$H$68,0,P.Comercial!M52*Vaciado!$D$71)))>J12*Vaciado!$G$69,Flujos!J12*Vaciado!$G$69,IF(Vaciado!$F$57>Flujos!J1,0,(IF(Flujos!J12<Vaciado!$H$68,0,P.Comercial!M52*Vaciado!$D$71)))) -> 3.9425556 | K26: =IF(IF(Vaciado!$F$57>Flujos!K1,0,(IF(Flujos!K12<Vaciado!$H$68,0,P.Comercial!N52*Vaciado!$D$71)))>K12*Vaciado!$G$69,Flujos!K12*Vaciado!$G$69,IF(Vaciado!$F$57>Flujos!K1,0,(IF(Flujos!K12<Vaciado!$H$68,0,P.Comercial!N52*Vaciado!$D$71)))) -> 7.1368889 | L26: =IF(IF(Vaciado!$F$57>Flujos!L1,0,(IF(Flujos!L12<Vaciado!$H$68,0,P.Comercial!O52*Vaciado!$D$71)))>L12*Vaciado!$G$69,Flujos!L12*Vaciado!$G$69,IF(Vaciado!$F$57>Flujos!L1,0,(IF(Flujos!L12<Vaciado!$H$68,0,P.Comercial!O52*Vaciado!$D$71)))) -> 7.3095556 | ... AN26: =IF(IF(Vaciado!$F$57>Flujos!AN1,0,(IF(Flujos!AN12<Vaciado!$H$68,0,P.Comercial!AQ52*Vaciado!$D$71)))>AN12*Vaciado!$G$69,Flujos!AN12*Vaciado!$G$69,IF(Vaciado!$F$57>Flujos!AN1,0,(IF(Flujos!AN12<Vaciado!$H$68,0,P.Comercial!AQ52*Vaciado!$D$71)))) -> 18.98201
A27: =Vaciado!C51 -> Comisión Partner: | B27: =SUM(E27:P27) -> 234.68465 | C27: =SUM(Q27:AB27) -> 504.72316 | D27: =SUM(AC27:AN27) -> 774.0517 | E27: =E12*Vaciado!$D$51 -> 0.185 | F27: =F12*Vaciado!$D$51 -> 0 | G27: =G12*Vaciado!$D$51 -> 0.80166667 | H27: =H12*Vaciado!$D$51 -> 10.113333 | I27: =I12*Vaciado!$D$51 -> 16.896667 | J27: =J12*Vaciado!$D$51 -> 16.896667 | K27: =K12*Vaciado!$D$51 -> 30.586667 | L27: =L12*Vaciado!$D$51 -> 31.326667 | ... AN27: =AN12*Vaciado!$D$51 -> 81.35147
A28: Total gastos del CAC | B28: =SUM(B22:B27) -> 385.07704 | C28: =SUM(C22:C27) -> 783.32729 | D28: =SUM(D22:D27) -> 1180.1625 | E28: =SUM(E22:E27) -> 3.6294444 | F28: =SUM(F22:F27) -> 3.4444444 | G28: =SUM(G22:G27) -> 4.2461111 | H28: =SUM(H22:H27) -> 18.277333 | I28: =SUM(I22:I27) -> 28.226222 | ... AN28: =SUM(AN22:AN27) -> 123.05604
A30: =Vaciado!C39 -> Costos de Cloud mensual: | B30: =SUM(E30:P30) -> 1.5 | C30: =SUM(Q30:AB30) -> 1.5 | D30: =SUM(AC30:AN30) -> 1.5 | E30: =Vaciado!$D$39/1000 -> 0.125 | F30: =Vaciado!$D$39/1000 -> 0.125 | G30: =Vaciado!$D$39/1000 -> 0.125 | H30: =Vaciado!$D$39/1000 -> 0.125 | I30: =Vaciado!$D$39/1000 -> 0.125 | J30: =Vaciado!$D$39/1000 -> 0.125 | K30: =Vaciado!$D$39/1000 -> 0.125 | L30: =Vaciado!$D$39/1000 -> 0.125 | ... AN30: =Vaciado!$D$39/1000 -> 0.125
A31: =Vaciado!C40 -> Costos de Hosting mensual: | B31: =SUM(E31:P31) -> 0.756 | C31: =SUM(Q31:AB31) -> 0.756 | D31: =SUM(AC31:AN31) -> 0.756 | E31: =Vaciado!$D$40/1000 -> 0.063 | F31: =Vaciado!$D$40/1000 -> 0.063 | G31: =Vaciado!$D$40/1000 -> 0.063 | H31: =Vaciado!$D$40/1000 -> 0.063 | I31: =Vaciado!$D$40/1000 -> 0.063 | J31: =Vaciado!$D$40/1000 -> 0.063 | K31: =Vaciado!$D$40/1000 -> 0.063 | L31: =Vaciado!$D$40/1000 -> 0.063 | ... AN31: =Vaciado!$D$40/1000 -> 0.063
A32: =Vaciado!C41 -> Costos de correos mensual: | B32: =SUM(E32:P32) -> 1.5 | C32: =SUM(Q32:AB32) -> 1.5 | D32: =SUM(AC32:AN32) -> 1.5 | E32: =Vaciado!$D$41/1000 -> 0.125 | F32: =Vaciado!$D$41/1000 -> 0.125 | G32: =Vaciado!$D$41/1000 -> 0.125 | H32: =Vaciado!$D$41/1000 -> 0.125 | I32: =Vaciado!$D$41/1000 -> 0.125 | J32: =Vaciado!$D$41/1000 -> 0.125 | K32: =Vaciado!$D$41/1000 -> 0.125 | L32: =Vaciado!$D$41/1000 -> 0.125 | ... AN32: =Vaciado!$D$41/1000 -> 0.125
A33: =Vaciado!C42 -> Costos de Herramientas mensual: | B33: =SUM(E33:P33) -> 1.5 | C33: =SUM(Q33:AB33) -> 1.5 | D33: =SUM(AC33:AN33) -> 1.5 | E33: =Vaciado!$D$42/1000 -> 0.125 | F33: =Vaciado!$D$42/1000 -> 0.125 | G33: =Vaciado!$D$42/1000 -> 0.125 | H33: =Vaciado!$D$42/1000 -> 0.125 | I33: =Vaciado!$D$42/1000 -> 0.125 | J33: =Vaciado!$D$42/1000 -> 0.125 | K33: =Vaciado!$D$42/1000 -> 0.125 | L33: =Vaciado!$D$42/1000 -> 0.125 | ... AN33: =Vaciado!$D$42/1000 -> 0.125
A34: =Vaciado!C43 -> Costos de Licencias mensual: | B34: =SUM(E34:P34) -> 1.5 | C34: =SUM(Q34:AB34) -> 1.5 | D34: =SUM(AC34:AN34) -> 1.5 | E34: =Vaciado!$D$43/1000 -> 0.125 | F34: =Vaciado!$D$43/1000 -> 0.125 | G34: =Vaciado!$D$43/1000 -> 0.125 | H34: =Vaciado!$D$43/1000 -> 0.125 | I34: =Vaciado!$D$43/1000 -> 0.125 | J34: =Vaciado!$D$43/1000 -> 0.125 | K34: =Vaciado!$D$43/1000 -> 0.125 | L34: =Vaciado!$D$43/1000 -> 0.125 | ... AN34: =Vaciado!$D$43/1000 -> 0.125
A35: =Vaciado!C44 -> Otros gastos I+D: | B35: =SUM(E35:P35) -> 12 | C35: =SUM(Q35:AB35) -> 12 | D35: =SUM(AC35:AN35) -> 12 | E35: =Vaciado!$D$44/1000 -> 1 | F35: =Vaciado!$D$44/1000 -> 1 | G35: =Vaciado!$D$44/1000 -> 1 | H35: =Vaciado!$D$44/1000 -> 1 | I35: =Vaciado!$D$44/1000 -> 1 | J35: =Vaciado!$D$44/1000 -> 1 | K35: =Vaciado!$D$44/1000 -> 1 | L35: =Vaciado!$D$44/1000 -> 1 | ... AN35: =Vaciado!$D$44/1000 -> 1
A36: =Vaciado!C45 -> Compra de equipos | B36: =SUM(E36:P36) -> 12 | C36: =SUM(Q36:AB36) -> 12 | D36: =SUM(AC36:AN36) -> 12 | E36: =Vaciado!$D$45/1000 -> 1 | F36: =Vaciado!$D$45/1000 -> 1 | G36: =Vaciado!$D$45/1000 -> 1 | H36: =Vaciado!$D$45/1000 -> 1 | I36: =Vaciado!$D$45/1000 -> 1 | J36: =Vaciado!$D$45/1000 -> 1 | K36: =Vaciado!$D$45/1000 -> 1 | L36: =Vaciado!$D$45/1000 -> 1 | ... AN36: =Vaciado!$D$45/1000 -> 1
A37: =Vaciado!C47 -> Gasto de Marketing y Difusión | B37: =SUM(E37:P37) -> 13.333333 | C37: =SUM(Q37:AB37) -> 13.333333 | D37: =SUM(AC37:AN37) -> 13.333333 | E37: =Vaciado!$E$47 -> 1.1111111 | F37: =Vaciado!$E$47 -> 1.1111111 | G37: =Vaciado!$E$47 -> 1.1111111 | H37: =Vaciado!$E$47 -> 1.1111111 | I37: =Vaciado!$E$47 -> 1.1111111 | J37: =Vaciado!$E$47 -> 1.1111111 | K37: =Vaciado!$E$47 -> 1.1111111 | L37: =Vaciado!$E$47 -> 1.1111111 | ... AN37: =Vaciado!$E$47 -> 1.1111111
A38: =Vaciado!C63 -> CEO | B38: =SUM(E38:P38) -> 66.666667 | C38: =SUM(Q38:AB38) -> 70 | D38: =SUM(AC38:AN38) -> 73.5 | E38: =IF(Vaciado!$F$63>Flujos!E1,0,Vaciado!$E$63) -> 5.5555556 | F38: =IF(Vaciado!$F$63>Flujos!F1,0,Vaciado!$E$63) -> 5.5555556 | G38: =IF(Vaciado!$F$63>Flujos!G1,0,Vaciado!$E$63) -> 5.5555556 | H38: =IF(Vaciado!$F$63>Flujos!H1,0,Vaciado!$E$63) -> 5.5555556 | I38: =IF(Vaciado!$F$63>Flujos!I1,0,Vaciado!$E$63) -> 5.5555556 | J38: =IF(Vaciado!$F$63>Flujos!J1,0,Vaciado!$E$63) -> 5.5555556 | K38: =IF(Vaciado!$F$63>Flujos!K1,0,Vaciado!$E$63) -> 5.5555556 | L38: =IF(Vaciado!$F$63>Flujos!L1,0,Vaciado!$E$63) -> 5.5555556 | ... P38: =IF(Vaciado!$F$63>Flujos!P1,0,Vaciado!$E$63) -> 5.5555556 | Q38: =IF(Vaciado!$F$63>Flujos!Q1,0,(Vaciado!$E$63*(1+Vaciado!$G$63))) -> 5.8333333 | R38: =IF(Vaciado!$F$63>Flujos!R1,0,(Vaciado!$E$63*(1+Vaciado!$G$63))) -> 5.8333333 | S38: =IF(Vaciado!$F$63>Flujos!S1,0,(Vaciado!$E$63*(1+Vaciado!$G$63))) -> 5.8333333 | T38: =IF(Vaciado!$F$63>Flujos!T1,0,(Vaciado!$E$63*(1+Vaciado!$G$63))) -> 5.8333333 | U38: =IF(Vaciado!$F$63>Flujos!U1,0,(Vaciado!$E$63*(1+Vaciado!$G$63))) -> 5.8333333 | V38: =IF(Vaciado!$F$63>Flujos!V1,0,(Vaciado!$E$63*(1+Vaciado!$G$63))) -> 5.8333333 | W38: =IF(Vaciado!$F$63>Flujos!W1,0,(Vaciado!$E$63*(1+Vaciado!$G$63))) -> 5.8333333 | X38: =IF(Vaciado!$F$63>Flujos!X1,0,(Vaciado!$E$63*(1+Vaciado!$G$63))) -> 5.8333333 | ... AB38: =IF(Vaciado!$F$63>Flujos!AB1,0,(Vaciado!$E$63*(1+Vaciado!$G$63))) -> 5.8333333 | AC38: =IF(Vaciado!$F$63>Flujos!AC1,0,(Vaciado!$E$63*((1+Vaciado!$G$63)^2))) -> 6.125 | AD38: =IF(Vaciado!$F$63>Flujos!AD1,0,(Vaciado!$E$63*((1+Vaciado!$G$63)^2))) -> 6.125 | AE38: =IF(Vaciado!$F$63>Flujos!AE1,0,(Vaciado!$E$63*((1+Vaciado!$G$63)^2))) -> 6.125 | AF38: =IF(Vaciado!$F$63>Flujos!AF1,0,(Vaciado!$E$63*((1+Vaciado!$G$63)^2))) -> 6.125 | AG38: =IF(Vaciado!$F$63>Flujos!AG1,0,(Vaciado!$E$63*((1+Vaciado!$G$63)^2))) -> 6.125 | AH38: =IF(Vaciado!$F$63>Flujos!AH1,0,(Vaciado!$E$63*((1+Vaciado!$G$63)^2))) -> 6.125 | AI38: =IF(Vaciado!$F$63>Flujos!AI1,0,(Vaciado!$E$63*((1+Vaciado!$G$63)^2))) -> 6.125 | AJ38: =IF(Vaciado!$F$63>Flujos!AJ1,0,(Vaciado!$E$63*((1+Vaciado!$G$63)^2))) -> 6.125 | ... AN38: =IF(Vaciado!$F$63>Flujos!AN1,0,(Vaciado!$E$63*((1+Vaciado!$G$63)^2))) -> 6.125
A39: =Vaciado!C58 -> CTO | B39: =SUM(E39:P39) -> 60 | C39: =SUM(Q39:AB39) -> 63 | D39: =SUM(AC39:AN39) -> 66.15 | E39: =IF(Vaciado!$F$58>Flujos!E1,0,Vaciado!$E$58) -> 5 | F39: =IF(Vaciado!$F$58>Flujos!F1,0,Vaciado!$E$58) -> 5 | G39: =IF(Vaciado!$F$58>Flujos!G1,0,Vaciado!$E$58) -> 5 | H39: =IF(Vaciado!$F$58>Flujos!H1,0,Vaciado!$E$58) -> 5 | I39: =IF(Vaciado!$F$58>Flujos!I1,0,Vaciado!$E$58) -> 5 | J39: =IF(Vaciado!$F$58>Flujos!J1,0,Vaciado!$E$58) -> 5 | K39: =IF(Vaciado!$F$58>Flujos!K1,0,Vaciado!$E$58) -> 5 | L39: =IF(Vaciado!$F$58>Flujos!L1,0,Vaciado!$E$58) -> 5 | ... P39: =IF(Vaciado!$F$58>Flujos!P1,0,Vaciado!$E$58) -> 5 | Q39: =IF(Vaciado!$F$58>Flujos!Q1,0,(Vaciado!$E$58*(1+Vaciado!$G$58))) -> 5.25 | R39: =IF(Vaciado!$F$58>Flujos!R1,0,(Vaciado!$E$58*(1+Vaciado!$G$58))) -> 5.25 | S39: =IF(Vaciado!$F$58>Flujos!S1,0,(Vaciado!$E$58*(1+Vaciado!$G$58))) -> 5.25 | T39: =IF(Vaciado!$F$58>Flujos!T1,0,(Vaciado!$E$58*(1+Vaciado!$G$58))) -> 5.25 | U39: =IF(Vaciado!$F$58>Flujos!U1,0,(Vaciado!$E$58*(1+Vaciado!$G$58))) -> 5.25 | V39: =IF(Vaciado!$F$58>Flujos!V1,0,(Vaciado!$E$58*(1+Vaciado!$G$58))) -> 5.25 | W39: =IF(Vaciado!$F$58>Flujos!W1,0,(Vaciado!$E$58*(1+Vaciado!$G$58))) -> 5.25 | X39: =IF(Vaciado!$F$58>Flujos!X1,0,(Vaciado!$E$58*(1+Vaciado!$G$58))) -> 5.25 | ... AB39: =IF(Vaciado!$F$58>Flujos!AB1,0,(Vaciado!$E$58*(1+Vaciado!$G$58))) -> 5.25 | AC39: =IF(Vaciado!$F$58>Flujos!AC1,0,(Vaciado!$E$58*((1+Vaciado!$G$58)^2))) -> 5.5125 | AD39: =IF(Vaciado!$F$58>Flujos!AD1,0,(Vaciado!$E$58*((1+Vaciado!$G$58)^2))) -> 5.5125 | AE39: =IF(Vaciado!$F$58>Flujos!AE1,0,(Vaciado!$E$58*((1+Vaciado!$G$58)^2))) -> 5.5125 | AF39: =IF(Vaciado!$F$58>Flujos!AF1,0,(Vaciado!$E$58*((1+Vaciado!$G$58)^2))) -> 5.5125 | AG39: =IF(Vaciado!$F$58>Flujos!AG1,0,(Vaciado!$E$58*((1+Vaciado!$G$58)^2))) -> 5.5125 | AH39: =IF(Vaciado!$F$58>Flujos!AH1,0,(Vaciado!$E$58*((1+Vaciado!$G$58)^2))) -> 5.5125 | AI39: =IF(Vaciado!$F$58>Flujos!AI1,0,(Vaciado!$E$58*((1+Vaciado!$G$58)^2))) -> 5.5125 | AJ39: =IF(Vaciado!$F$58>Flujos!AJ1,0,(Vaciado!$E$58*((1+Vaciado!$G$58)^2))) -> 5.5125 | ... AN39: =IF(Vaciado!$F$58>Flujos!AN1,0,(Vaciado!$E$58*((1+Vaciado!$G$58)^2))) -> 5.5125
A40: =Vaciado!C59 -> Desarrollador | B40: =SUM(E40:P40) -> 26.666667 | C40: =SUM(Q40:AB40) -> 28 | D40: =SUM(AC40:AN40) -> 29.4 | E40: =IF(Vaciado!$F$59>Flujos!E1,0,Vaciado!$E$59) -> 2.2222222 | F40: =IF(Vaciado!$F$59>Flujos!F1,0,Vaciado!$E$59) -> 2.2222222 | G40: =IF(Vaciado!$F$59>Flujos!G1,0,Vaciado!$E$59) -> 2.2222222 | H40: =IF(Vaciado!$F$59>Flujos!H1,0,Vaciado!$E$59) -> 2.2222222 | I40: =IF(Vaciado!$F$59>Flujos!I1,0,Vaciado!$E$59) -> 2.2222222 | J40: =IF(Vaciado!$F$59>Flujos!J1,0,Vaciado!$E$59) -> 2.2222222 | K40: =IF(Vaciado!$F$59>Flujos!K1,0,Vaciado!$E$59) -> 2.2222222 | L40: =IF(Vaciado!$F$59>Flujos!L1,0,Vaciado!$E$59) -> 2.2222222 | ... P40: =IF(Vaciado!$F$59>Flujos!P1,0,Vaciado!$E$59) -> 2.2222222 | Q40: =IF(Vaciado!$F$59>Flujos!Q1,0,(Vaciado!$E$59*(1+Vaciado!$G$59))) -> 2.3333333 | R40: =IF(Vaciado!$F$59>Flujos!R1,0,(Vaciado!$E$59*(1+Vaciado!$G$59))) -> 2.3333333 | S40: =IF(Vaciado!$F$59>Flujos!S1,0,(Vaciado!$E$59*(1+Vaciado!$G$59))) -> 2.3333333 | T40: =IF(Vaciado!$F$59>Flujos!T1,0,(Vaciado!$E$59*(1+Vaciado!$G$59))) -> 2.3333333 | U40: =IF(Vaciado!$F$59>Flujos!U1,0,(Vaciado!$E$59*(1+Vaciado!$G$59))) -> 2.3333333 | V40: =IF(Vaciado!$F$59>Flujos!V1,0,(Vaciado!$E$59*(1+Vaciado!$G$59))) -> 2.3333333 | W40: =IF(Vaciado!$F$59>Flujos!W1,0,(Vaciado!$E$59*(1+Vaciado!$G$59))) -> 2.3333333 | X40: =IF(Vaciado!$F$59>Flujos!X1,0,(Vaciado!$E$59*(1+Vaciado!$G$59))) -> 2.3333333 | ... AB40: =IF(Vaciado!$F$59>Flujos!AB1,0,(Vaciado!$E$59*(1+Vaciado!$G$59))) -> 2.3333333 | AC40: =IF(Vaciado!$F$59>Flujos!AC1,0,(Vaciado!$E$59*((1+Vaciado!$G$59)^2))) -> 2.45 | AD40: =IF(Vaciado!$F$59>Flujos!AD1,0,(Vaciado!$E$59*((1+Vaciado!$G$59)^2))) -> 2.45 | AE40: =IF(Vaciado!$F$59>Flujos!AE1,0,(Vaciado!$E$59*((1+Vaciado!$G$59)^2))) -> 2.45 | AF40: =IF(Vaciado!$F$59>Flujos!AF1,0,(Vaciado!$E$59*((1+Vaciado!$G$59)^2))) -> 2.45 | AG40: =IF(Vaciado!$F$59>Flujos!AG1,0,(Vaciado!$E$59*((1+Vaciado!$G$59)^2))) -> 2.45 | AH40: =IF(Vaciado!$F$59>Flujos!AH1,0,(Vaciado!$E$59*((1+Vaciado!$G$59)^2))) -> 2.45 | AI40: =IF(Vaciado!$F$59>Flujos!AI1,0,(Vaciado!$E$59*((1+Vaciado!$G$59)^2))) -> 2.45 | AJ40: =IF(Vaciado!$F$59>Flujos!AJ1,0,(Vaciado!$E$59*((1+Vaciado!$G$59)^2))) -> 2.45 | ... AN40: =IF(Vaciado!$F$59>Flujos!AN1,0,(Vaciado!$E$59*((1+Vaciado!$G$59)^2))) -> 2.45
A41: =Vaciado!C64 -> CFO | B41: =SUM(E41:P41) -> 40 | C41: =SUM(Q41:AB41) -> 42 | D41: =SUM(AC41:AN41) -> 44.1 | E41: =IF(Vaciado!$F$64>Flujos!E1,0,Vaciado!$E$64) -> 3.3333333 | F41: =IF(Vaciado!$F$64>Flujos!F1,0,Vaciado!$E$64) -> 3.3333333 | G41: =IF(Vaciado!$F$64>Flujos!G1,0,Vaciado!$E$64) -> 3.3333333 | H41: =IF(Vaciado!$F$64>Flujos!H1,0,Vaciado!$E$64) -> 3.3333333 | I41: =IF(Vaciado!$F$64>Flujos!I1,0,Vaciado!$E$64) -> 3.3333333 | J41: =IF(Vaciado!$F$64>Flujos!J1,0,Vaciado!$E$64) -> 3.3333333 | K41: =IF(Vaciado!$F$64>Flujos!K1,0,Vaciado!$E$64) -> 3.3333333 | L41: =IF(Vaciado!$F$64>Flujos!L1,0,Vaciado!$E$64) -> 3.3333333 | ... P41: =IF(Vaciado!$F$64>Flujos!P1,0,Vaciado!$E$64) -> 3.3333333 | Q41: =IF(Vaciado!$F$64>Flujos!Q1,0,(Vaciado!$E$64*(1+Vaciado!$G$64))) -> 3.5 | R41: =IF(Vaciado!$F$64>Flujos!R1,0,(Vaciado!$E$64*(1+Vaciado!$G$64))) -> 3.5 | S41: =IF(Vaciado!$F$64>Flujos!S1,0,(Vaciado!$E$64*(1+Vaciado!$G$64))) -> 3.5 | T41: =IF(Vaciado!$F$64>Flujos!T1,0,(Vaciado!$E$64*(1+Vaciado!$G$64))) -> 3.5 | U41: =IF(Vaciado!$F$64>Flujos!U1,0,(Vaciado!$E$64*(1+Vaciado!$G$64))) -> 3.5 | V41: =IF(Vaciado!$F$64>Flujos!V1,0,(Vaciado!$E$64*(1+Vaciado!$G$64))) -> 3.5 | W41: =IF(Vaciado!$F$64>Flujos!W1,0,(Vaciado!$E$64*(1+Vaciado!$G$64))) -> 3.5 | X41: =IF(Vaciado!$F$64>Flujos!X1,0,(Vaciado!$E$64*(1+Vaciado!$G$64))) -> 3.5 | ... AB41: =IF(Vaciado!$F$64>Flujos!AB1,0,(Vaciado!$E$64*(1+Vaciado!$G$64))) -> 3.5 | AC41: =IF(Vaciado!$F$64>Flujos!AC1,0,(Vaciado!$E$64*((1+Vaciado!$G$64)^2))) -> 3.675 | AD41: =IF(Vaciado!$F$64>Flujos!AD1,0,(Vaciado!$E$64*((1+Vaciado!$G$64)^2))) -> 3.675 | AE41: =IF(Vaciado!$F$64>Flujos!AE1,0,(Vaciado!$E$64*((1+Vaciado!$G$64)^2))) -> 3.675 | AF41: =IF(Vaciado!$F$64>Flujos!AF1,0,(Vaciado!$E$64*((1+Vaciado!$G$64)^2))) -> 3.675 | AG41: =IF(Vaciado!$F$64>Flujos!AG1,0,(Vaciado!$E$64*((1+Vaciado!$G$64)^2))) -> 3.675 | AH41: =IF(Vaciado!$F$64>Flujos!AH1,0,(Vaciado!$E$64*((1+Vaciado!$G$64)^2))) -> 3.675 | AI41: =IF(Vaciado!$F$64>Flujos!AI1,0,(Vaciado!$E$64*((1+Vaciado!$G$64)^2))) -> 3.675 | AJ41: =IF(Vaciado!$F$64>Flujos!AJ1,0,(Vaciado!$E$64*((1+Vaciado!$G$64)^2))) -> 3.675 | ... AN41: =IF(Vaciado!$F$64>Flujos!AN1,0,(Vaciado!$E$64*((1+Vaciado!$G$64)^2))) -> 3.675
A42: =Vaciado!C65 -> Contadora | B42: =SUM(E42:P42) -> 13.333333 | C42: =SUM(Q42:AB42) -> 14 | D42: =SUM(AC42:AN42) -> 14.7 | E42: =IF(Vaciado!$F$65>Flujos!E1,0,Vaciado!$E$65) -> 1.1111111 | F42: =IF(Vaciado!$F$65>Flujos!F1,0,Vaciado!$E$65) -> 1.1111111 | G42: =IF(Vaciado!$F$65>Flujos!G1,0,Vaciado!$E$65) -> 1.1111111 | H42: =IF(Vaciado!$F$65>Flujos!H1,0,Vaciado!$E$65) -> 1.1111111 | I42: =IF(Vaciado!$F$65>Flujos!I1,0,Vaciado!$E$65) -> 1.1111111 | J42: =IF(Vaciado!$F$65>Flujos!J1,0,Vaciado!$E$65) -> 1.1111111 | K42: =IF(Vaciado!$F$65>Flujos!K1,0,Vaciado!$E$65) -> 1.1111111 | L42: =IF(Vaciado!$F$65>Flujos!L1,0,Vaciado!$E$65) -> 1.1111111 | ... P42: =IF(Vaciado!$F$65>Flujos!P1,0,Vaciado!$E$65) -> 1.1111111 | Q42: =IF(Vaciado!$F$65>Flujos!Q1,0,(Vaciado!$E$65*(1+Vaciado!$G$65))) -> 1.1666667 | R42: =IF(Vaciado!$F$65>Flujos!R1,0,(Vaciado!$E$65*(1+Vaciado!$G$65))) -> 1.1666667 | S42: =IF(Vaciado!$F$65>Flujos!S1,0,(Vaciado!$E$65*(1+Vaciado!$G$65))) -> 1.1666667 | T42: =IF(Vaciado!$F$65>Flujos!T1,0,(Vaciado!$E$65*(1+Vaciado!$G$65))) -> 1.1666667 | U42: =IF(Vaciado!$F$65>Flujos!U1,0,(Vaciado!$E$65*(1+Vaciado!$G$65))) -> 1.1666667 | V42: =IF(Vaciado!$F$65>Flujos!V1,0,(Vaciado!$E$65*(1+Vaciado!$G$65))) -> 1.1666667 | W42: =IF(Vaciado!$F$65>Flujos!W1,0,(Vaciado!$E$65*(1+Vaciado!$G$65))) -> 1.1666667 | X42: =IF(Vaciado!$F$65>Flujos!X1,0,(Vaciado!$E$65*(1+Vaciado!$G$65))) -> 1.1666667 | ... AB42: =IF(Vaciado!$F$65>Flujos!AB1,0,(Vaciado!$E$65*(1+Vaciado!$G$65))) -> 1.1666667 | AC42: =IF(Vaciado!$F$65>Flujos!AC1,0,(Vaciado!$E$65*((1+Vaciado!$G$65)^2))) -> 1.225 | AD42: =IF(Vaciado!$F$65>Flujos!AD1,0,(Vaciado!$E$65*((1+Vaciado!$G$65)^2))) -> 1.225 | AE42: =IF(Vaciado!$F$65>Flujos!AE1,0,(Vaciado!$E$65*((1+Vaciado!$G$65)^2))) -> 1.225 | AF42: =IF(Vaciado!$F$65>Flujos!AF1,0,(Vaciado!$E$65*((1+Vaciado!$G$65)^2))) -> 1.225 | AG42: =IF(Vaciado!$F$65>Flujos!AG1,0,(Vaciado!$E$65*((1+Vaciado!$G$65)^2))) -> 1.225 | AH42: =IF(Vaciado!$F$65>Flujos!AH1,0,(Vaciado!$E$65*((1+Vaciado!$G$65)^2))) -> 1.225 | AI42: =IF(Vaciado!$F$65>Flujos!AI1,0,(Vaciado!$E$65*((1+Vaciado!$G$65)^2))) -> 1.225 | AJ42: =IF(Vaciado!$F$65>Flujos!AJ1,0,(Vaciado!$E$65*((1+Vaciado!$G$65)^2))) -> 1.225 | ... AN42: =IF(Vaciado!$F$65>Flujos!AN1,0,(Vaciado!$E$65*((1+Vaciado!$G$65)^2))) -> 1.225
A43: =Vaciado!C68 -> Comisión del CEO | B43: =SUM(E43:P43) -> 78.228216 | C43: =SUM(Q43:AB43) -> 168.24105 | D43: =SUM(AC43:AN43) -> 258.01723 | E43: =IF(Vaciado!$F$63>Flujos!E1,0,E12*Vaciado!$D$68) -> 0.061666667 | F43: =IF(Vaciado!$F$63>Flujos!F1,0,F12*Vaciado!$D$68) -> 0 | G43: =IF(Vaciado!$F$63>Flujos!G1,0,G12*Vaciado!$D$68) -> 0.26722222 | H43: =IF(Vaciado!$F$63>Flujos!H1,0,H12*Vaciado!$D$68) -> 3.3711111 | I43: =IF(Vaciado!$F$63>Flujos!I1,0,I12*Vaciado!$D$68) -> 5.6322222 | J43: =IF(Vaciado!$F$63>Flujos!J1,0,J12*Vaciado!$D$68) -> 5.6322222 | K43: =IF(Vaciado!$F$63>Flujos!K1,0,K12*Vaciado!$D$68) -> 10.195556 | L43: =IF(Vaciado!$F$63>Flujos!L1,0,L12*Vaciado!$D$68) -> 10.442222 | ... AN43: =IF(Vaciado!$F$63>Flujos!AN1,0,AN12*Vaciado!$D$68) -> 27.117157
A44: Total GAV | B44: =SUM(B30:B43) -> 328.98422 | C44: =SUM(C30:C43) -> 429.33039 | D44: =SUM(D30:D43) -> 529.95657 | E44: =SUM(E30:E43) -> 20.958 | F44: =SUM(F30:F43) -> 20.896333 | G44: =SUM(G30:G43) -> 21.163556 | H44: =SUM(H30:H43) -> 24.267444 | I44: =SUM(I30:I43) -> 26.528556 | ... AN44: =SUM(AN30:AN43) -> 49.778768
D46: Flujo del período | E46: =E12-E20-E28-E44 -> -24.645722 | F46: =F12-F20-F28-F44 -> -25.451889 | G46: =G12-G20-G28-G44 -> -21.666833 | H46: =H12-H20-H28-H44 -> 19.857333 | I46: =I12-I20-I28-I44 -> 49.334556 | J46: =J12-J20-J28-J44 -> 49.334556 | K46: =K12-K20-K28-K44 -> 110.47722 | L46: =L12-L20-L28-L44 -> 113.35656 | ... AN46: =AN12-AN20-AN28-AN44 -> 328.50913
D47: Flujos acumulados | E47: =E46 -> -24.645722 | F47: =E46+F46 -> -50.097611 | G47: =F46+G46 -> -47.118722 | H47: =G46+H46 -> -1.8095 | I47: =H46+I46 -> 69.191889 | J47: =I46+J46 -> 98.669111 | K47: =J46+K46 -> 159.81178 | L47: =K46+L46 -> 223.83378 | M47: =L46+M46 -> 225.32422 | ... AN47: =AM46+AN46 -> 644.99287
E49: 36 | F49: 35 | G49: 34 | H49: 33 | I49: 32 | J49: 31 | K49: 30 | L49: 29 | M49: 28 | N49: 27 | O49: 26 | P49: 25 | Q49: 24 | R49: 23 | S49: 22 | T49: 21 | U49: 20 | V49: 19 | W49: 18 | X49: 17 | Y49: 16 | Z49: 15 | AA49: 14 | AB49: 13 | AC49: 12 | AD49: 11 | AE49: 10 | AF49: 9 | AG49: 8 | AH49: 7 | AI49: 6 | AJ49: 5 | AK49: 4 | AL49: 3 | AM49: 2 | AN49: 1
A50: Flujo Estocástico | B50: =SUM(E50:P50) -> 555.0989 | C50: =SUM(Q50:AB50) -> 936.42491 | D50: =SUM(AC50:AN50) -> 501.28332 | E50: =E46*(E49/36) -> -24.645722 | F50: =F46*(F49/36) -> -24.744892 | G50: =G46*(G49/36) -> -20.46312 | H50: =H46*(H49/36) -> 18.202556 | I50: =I46*(I49/36) -> 43.852938 | J50: =J46*(J49/36) -> 42.482534 | K50: =K46*(K49/36) -> 92.064352 | L50: =L46*(L49/36) -> 91.315003 | ... AN50: =AN46*(AN49/36) -> 9.1252536
A51: Ingresos Estocásticos | B51: =SUM(E51:P51) -> 1230.6203 | C51: =SUM(Q51:AB51) -> 1681.7897 | D51: =SUM(AC51:AN51) -> 854.18211 | E51: =E12*(E49/36) -> 1.2333333 | F51: =F12*(F49/36) -> 0 | G51: =G12*(G49/36) -> 5.0475309 | H51: =H12*(H49/36) -> 61.803704 | I51: =I12*(I49/36) -> 100.1284 | J51: =J12*(J49/36) -> 96.999383 | K51: =K12*(K49/36) -> 169.92593 | L51: =L12*(L49/36) -> 168.2358 | ... AN51: =AN12*(AN49/36) -> 15.065087
A52: Egresos Estocásticos | B52: =SUM(E52:P52) -> 401.54431 | C52: =SUM(Q52:AB52) -> 527.10435 | D52: =SUM(AC52:AN52) -> 261.08953 | E52: =(E20+E28)*(E49/36) -> 4.9210556 | F52: =(F20+F28)*(F49/36) -> 4.4290123 | G52: =(G20+G28)*(G49/36) -> 5.5228488 | H52: =(H20+H28)*(H49/36) -> 21.355991 | I52: =(I20+I28)*(I49/36) -> 32.694519 | J52: =(J20+J28)*(J49/36) -> 31.672815 | K52: =(K20+K28)*(K49/36) -> 51.951667 | L52: =(L20+L28)*(L49/36) -> 51.675852 | ... AN52: =(AN20+AN28)*(AN49/36) -> 4.5570899
A53: Egresos no Estocásticos | B53: =B44 -> 328.98422 | C53: =C44 -> 429.33039 | D53: =D44 -> 529.95657 | E53: =(E44)*(E49/36) -> 20.958 | F53: =(F44)*(F49/36) -> 20.31588 | G53: =(G44)*(G49/36) -> 19.987802 | H53: =(H44)*(H49/36) -> 22.245157 | I53: =(I44)*(I49/36) -> 23.580938 | J53: =(J44)*(J49/36) -> 22.844034 | K53: =(K44)*(K49/36) -> 25.909907 | L53: =(L44)*(L49/36) -> 25.244948 | ... AN53: =(AN44)*(AN49/36) -> 1.3827435
A54: Flujo Estocástico 2 | B54: =B51-B52-B53 -> 500.09175 | C54: =C51-C52-C53 -> 725.35492 | D54: =D51-D52-D53 -> 63.136012
D56: Breakeven | E56: =IF(E46<0,1,0) -> 1 | F56: =IF(F46<0,1,0) -> 1 | G56: =IF(G46<0,1,0) -> 1 | H56: =IF(H46<0,1,0) -> 0 | I56: =IF(I46<0,1,0) -> 0 | J56: =IF(J46<0,1,0) -> 0 | K56: =IF(K46<0,1,0) -> 0 | L56: =IF(L46<0,1,0) -> 0 | ... AN56: =IF(AN46<0,1,0) -> 0
D57: Flujos c/I | E57: =-(Dashboard!C32+Vaciado!D20+Vaciado!D21+Vaciado!D22)+E46 -> -619.67034 | F57: =E57+F46 -> -645.12223 | G57: =F57+G46 -> -666.78906 | H57: =G57+H46 -> -646.93173 | I57: =H57+I46 -> -597.59717 | J57: =I57+J46 -> -548.26262 | K57: =J57+K46 -> -437.78539 | L57: =K57+L46 -> -324.42884 | M57: =L57+M46 -> -212.46117 | ... AN57: =AM57+AN46 -> 5078.6907
D58: Payback | E58: =IF(E57<0,1,0) -> 1 | F58: =IF(F57<0,1,0) -> 1 | G58: =IF(G57<0,1,0) -> 1 | H58: =IF(H57<0,1,0) -> 1 | I58: =IF(I57<0,1,0) -> 1 | J58: =IF(J57<0,1,0) -> 1 | K58: =IF(K57<0,1,0) -> 1 | L58: =IF(L57<0,1,0) -> 1 | ... AN58: =IF(AN57<0,1,0) -> 0
E60: =E1 -> 1 | F60: =F1 -> 2 | G60: =G1 -> 3 | H60: =H1 -> 4 | I60: =I1 -> 5 | J60: =J1 -> 6 | K60: =K1 -> 7 | L60: =L1 -> 8 | ... AN60: =AN1 -> 36
E61: =30*E1 -> 30 | F61: =30*F1 -> 60 | G61: =30*G1 -> 90 | H61: =30*H1 -> 120 | I61: =30*I1 -> 150 | J61: =30*J1 -> 180 | K61: =30*K1 -> 210 | L61: =30*L1 -> 240 | ... AN61: =30*AN1 -> 1080
E62: =IF(Vaciado!$C$80=0,0,(INT(E61/Vaciado!$C$80))) -> 0 | F62: =IF(Vaciado!C80=0,0,INT(F61/Vaciado!$C$80)) -> 0 | G62: =IF(Vaciado!$C$80=0,0,(INT(G61/Vaciado!$C$80)+F62)) -> 1 | H62: =IF(Vaciado!$C$80=0,0,(INT(H61/Vaciado!$C$80)+G62)) -> 2 | I62: =IF(Vaciado!$C$80=0,0,(INT(I61/Vaciado!$C$80)+H62)) -> 3 | J62: =IF(Vaciado!$C$80=0,0,(INT(J61/Vaciado!$C$80)+I62)) -> 5 | K62: =IF(Vaciado!$C$80=0,0,(INT(K61/Vaciado!$C$80)+J62)) -> 7 | L62: =IF(Vaciado!$C$80=0,0,(INT(L61/Vaciado!$C$80)+K62)) -> 9 | M62: =IF(Vaciado!$C$80=0,0,(INT(M61/Vaciado!$C$80)+L62)) -> 12 | N62: =IF(Vaciado!$C$80=0,0,(INT(N61/Vaciado!$C$80)+M62)) -> 15 | ... AN62: =IF(Vaciado!$C$80=0,0,(INT(AN61/Vaciado!$C$80)+AM62)) -> 210
E63: =IF(E62=1,1,0) -> 0 | F63: =IF(F62=1,1,0) -> 0 | G63: =IF(G62=1,1,0) -> 1 | H63: =IF(H62=1,1,0) -> 0 | I63: =IF(I62=1,1,0) -> 0 | J63: =IF(J62=1,1,0) -> 0 | K63: =IF(K62=1,1,0) -> 0 | L63: =IF(L62=1,1,0) -> 0 | ... AN63: =IF(AN62=1,1,0) -> 0
E64: =E63+(IF(D64>=1,D64+1,0)) -> 0 | F64: =F63+(IF(E64>=1,E64+1,0)) -> 0 | G64: =G63+(IF(F64>=1,F64+1,0)) -> 1 | H64: =H63+(IF(G64>=1,G64+1,0)) -> 2 | I64: =I63+(IF(H64>=1,H64+1,0)) -> 3 | J64: =J63+(IF(I64>=1,I64+1,0)) -> 4 | K64: =K63+(IF(J64>=1,J64+1,0)) -> 5 | L64: =L63+(IF(K64>=1,K64+1,0)) -> 6 | ... AN64: =AN63+(IF(AM64>=1,AM64+1,0)) -> 34
D65: Ingresos Chile con desface | E65: =_xlfn.XLOOKUP(E64,$E$1:$AN$1,$E$12:$AN$12,0,0,1) -> 0 | F65: =_xlfn.XLOOKUP(F64,$E$1:$AN$1,$E$12:$AN$12,0,0,1) -> 0 | G65: =_xlfn.XLOOKUP(G64,$E$1:$AN$1,$E$12:$AN$12,0,0,1) -> 1.2333333 | H65: =_xlfn.XLOOKUP(H64,$E$1:$AN$1,$E$12:$AN$12,0,0,1) -> 0 | I65: =_xlfn.XLOOKUP(I64,$E$1:$AN$1,$E$12:$AN$12,0,0,1) -> 5.3444444 | J65: =_xlfn.XLOOKUP(J64,$E$1:$AN$1,$E$12:$AN$12,0,0,1) -> 67.422222 | K65: =_xlfn.XLOOKUP(K64,$E$1:$AN$1,$E$12:$AN$12,0,0,1) -> 112.64444 | L65: =_xlfn.XLOOKUP(L64,$E$1:$AN$1,$E$12:$AN$12,0,0,1) -> 112.64444 | ... AN65: =_xlfn.XLOOKUP(AN64,$E$1:$AN$1,$E$12:$AN$12,0,0,1) -> 498.1549
D66: Costos operacionales | E66: =E20 -> 1.2916111 | F66: =F20 -> 1.1111111 | G66: =G20 -> 1.6016111 | H66: =H20 -> 5.0201111 | I66: =I20 -> 8.5551111 | J66: =J20 -> 8.5551111 | K66: =K20 -> 14.037111 | L66: =L20 -> 14.759111 | ... AN66: =AN20 -> 40.999191
D67: Gastos del CAC | E67: =E28 -> 3.6294444 | F67: =F28 -> 3.4444444 | G67: =G28 -> 4.2461111 | H67: =H28 -> 18.277333 | I67: =I28 -> 28.226222 | J67: =J28 -> 28.226222 | K67: =K28 -> 48.304889 | L67: =L28 -> 49.390222 | ... AN67: =AN28 -> 123.05604
D68: GAV | E68: =E44 -> 20.958 | F68: =F44 -> 20.896333 | G68: =G44 -> 21.163556 | H68: =H44 -> 24.267444 | I68: =I44 -> 26.528556 | J68: =J44 -> 26.528556 | K68: =K44 -> 31.091889 | L68: =L44 -> 31.338556 | ... AN68: =AN44 -> 49.778768
D69: Flujo del período | E69: =E65-E66-E67-E68 -> -25.879056 | F69: =F65-F66-F67-F68 -> -25.451889 | G69: =G65-G66-G67-G68 -> -25.777944 | H69: =H65-H66-H67-H68 -> -47.564889 | I69: =I65-I66-I67-I68 -> -57.965444 | J69: =J65-J66-J67-J68 -> 4.1123333 | K69: =K65-K66-K67-K68 -> 19.210556 | L69: =L65-L66-L67-L68 -> 17.156556 | ... AN69: =AN65-AN66-AN67-AN68 -> 284.32089
D70: Flujo acumulado | E70: =E69 -> -25.879056 | F70: =E70+F69 -> -51.330944 | G70: =F70+G69 -> -77.108889 | H70: =G70+H69 -> -124.67378 | I70: =H70+I69 -> -182.63922 | J70: =I70+J69 -> -178.52689 | K70: =J70+K69 -> -159.31633 | L70: =K70+L69 -> -142.15978 | M70: =L70+M69 -> -35.125444 | ... AN70: =AM70+AN69 -> 4608.2267
D71: Negativos | E71: =IF(E70<0,E70,0) -> -25.879056 | F71: =IF(F70<0,F70,0) -> -51.330944 | G71: =IF(G70<0,G70,0) -> -77.108889 | H71: =IF(H70<0,H70,0) -> -124.67378 | I71: =IF(I70<0,I70,0) -> -182.63922 | J71: =IF(J70<0,J70,0) -> -178.52689 | K71: =IF(K70<0,K70,0) -> -159.31633 | L71: =IF(L70<0,L70,0) -> -142.15978 | ... AN71: =IF(AN70<0,AN70,0) -> 0
D72: Capital de trabajo | E72: =MIN(E71:AN71) -> -182.63922
A74: =Vaciado!C75 -> Brasil | B74: 2024 | C74: 2025 | D74: 2026 | F74: Ajuste por desface Brasil
A75: Ingresos (MUS$) | B75: =B12*Vaciado!$E$75 -> 2346.8465 | C75: =C12*Vaciado!$E$75 -> 5047.2316 | D75: =D12*Vaciado!$E$75 -> 7740.517 | F75: =(B75/360)*Vaciado!$F$75 -> 586.71162 | G75: =(C75/360)*Vaciado!$F$75 -> 1261.8079 | H75: =(D75/360)*Vaciado!$F$75 -> 1935.1293
A76: Gastos del CAC (MUS$) | B76: =B75*Vaciado!$D$75 -> 352.02697 | C76: =C75*Vaciado!$D$75 -> 757.08473 | D76: =D75*Vaciado!$D$75 -> 1161.0776
A77: Resultado | B77: =B75-B76 -> 1994.8195 | C77: =C75-C76 -> 4290.1468 | D77: =D75-D76 -> 6579.4395
A79: =Vaciado!C76 -> Colombia | B79: 2024 | C79: 2025 | D79: 2026 | F79: Ajuste por desface Colombia
A80: Ingresos (MUS$) | B80: =B12*Vaciado!$E$76 -> 1095.195 | C80: =C12*Vaciado!$E$76 -> 2355.3747 | D80: =D12*Vaciado!$E$76 -> 3612.2413 | F80: =(B80/360)*Vaciado!$F$76 -> 273.79875 | G80: =(C80/360)*Vaciado!$F$76 -> 588.84368 | H80: =(D80/360)*Vaciado!$F$76 -> 903.06032
A81: Gastos del CAC (MUS$) | B81: =B80*Vaciado!$D$76 -> 219.039 | C81: =C80*Vaciado!$D$76 -> 471.07494 | D81: =D80*Vaciado!$D$76 -> 722.44825
A82: Resultado | B82: =B80-B81 -> 876.15602 | C82: =C80-C81 -> 1884.2998 | D82: =D80-D81 -> 2889.793
B84: 2024 | C84: 2025 | D84: 2026
A85: Ingresos Internacionales(MUS$) | B85: =B75-F75+B80-F80 -> 2581.5311 | C85: =C75-G75+F75+C80-G80+F80 -> 6412.4651 | D85: =D75-H75+G75+D80-H80+G80 -> 10365.22
A86: Gastos del CAC Internacional (MUS$) | B86: =B76+B81 -> 571.06597 | C86: =C76+C81 -> 1228.1597 | D86: =D76+D81 -> 1883.5258
A87: Resultado | B87: =B85-B86 -> 2010.4651 | C87: =C85-C86 -> 5184.3054 | D87: =D85-D86 -> 8481.6945
E88: 1 | F88: 2 | G88: 3 | H88: 4 | I88: 5 | J88: 6 | K88: 7 | L88: 8 | M88: 9 | N88: 10 | O88: 11 | P88: 12
A89: Brasil | D89: Ingresos Brasil acumulados | E89: =B75/12 -> 195.57054 | F89: =E89+$E$89 -> 391.14108 | G89: =F89+$E$89 -> 586.71162 | H89: =G89+$E$89 -> 782.28216 | I89: =H89+$E$89 -> 977.8527 | J89: =I89+$E$89 -> 1173.4232 | K89: =J89+$E$89 -> 1368.9938 | L89: =K89+$E$89 -> 1564.5643 | M89: =L89+$E$89 -> 1760.1349 | ... P89: =O89+$E$89 -> 2346.8465
D90: Pagos directos acumulados | E90: =E89*Vaciado!$D$75 -> 29.335581 | F90: =E90+$E$90 -> 58.671162 | G90: =F90+$E$90 -> 88.006743 | H90: =G90+$E$90 -> 117.34232 | I90: =H90+$E$90 -> 146.6779 | J90: =I90+$E$90 -> 176.01349 | K90: =J90+$E$90 -> 205.34907 | L90: =K90+$E$90 -> 234.68465 | M90: =L90+$E$90 -> 264.02023 | ... P90: =O90+$E$90 -> 352.02697
A91: Colombia | D91: Ingresos reales | E91: =B85/12 -> 215.12759 | F91: =E91+$E$91 -> 430.25519 | G91: =F91+$E$91 -> 645.38278 | H91: =G91+$E$91 -> 860.51037 | I91: =H91+$E$91 -> 1075.638 | J91: =I91+$E$91 -> 1290.7656 | K91: =J91+$E$91 -> 1505.8932 | L91: =K91+$E$91 -> 1721.0207 | M91: =L91+$E$91 -> 1936.1483 | ... P91: =O91+$E$91 -> 2581.5311
D92: Costos directos acumulados | E92: =E91*Vaciado!$D$75 -> 32.269139 | F92: =E92+$E$92 -> 64.538278 | G92: =F92+$E$92 -> 96.807417 | H92: =G92+$E$92 -> 129.07656 | I92: =H92+$E$92 -> 161.34569 | J92: =I92+$E$92 -> 193.61483 | K92: =J92+$E$92 -> 225.88397 | L92: =K92+$E$92 -> 258.15311 | M92: =L92+$E$92 -> 290.42225 | ... P92: =O92+$E$92 -> 387.22967
B94: 2024 | C94: 2025 | D94: 2026
A95: Ingresos ajustados Brasil | B95: =B75-F75 -> 1760.1349 | C95: =F75+C75-G75 -> 4372.1353 | D95: =G75+D75-H75 -> 7067.1956
A96: Ingresos ajustados Colombia | B96: =B80-F80 -> 821.39626 | C96: =F80+C80-G80 -> 2040.3298 | D96: =G80+D80-H80 -> 3298.0246
A97: Ingresos totales ajustados | B97: =B95+B96 -> 2581.5311 | C97: =C95+C96 -> 6412.4651 | D97: =D95+D96 -> 10365.22
A98: Gastos Op. | B98: =B104+B110 -> 200.96057 | C98: =C104+C110 -> 511.29398 | D98: =D104+D110 -> 781.53866
A99: CAC Total | B99: =B86 -> 571.06597 | C99: =C86 -> 1228.1597 | D99: =D86 -> 1883.5258
A100: Resultado Internacional aj. | B100: =B97-B99-B98 -> 1809.5046 | C100: =C97-C99-C98 -> 4673.0114 | D100: =D97-D99-D98 -> 7700.1558
B102: 2024 | C102: 2025 | D102: 2026
A103: Ingresos ajustados Brasil | B103: =B95 -> 1760.1349 | C103: =C95 -> 4372.1353 | D103: =D95 -> 7067.1956
A104: Costos Operacionales Brasil | B104: =B103*(1-'Unit Economics'!C17) -> 137.01857 | C104: =C103*(1-'Unit Economics'!D17) -> 348.60953 | D104: =D103*(1-'Unit Economics'!E17) -> 532.86727
A105: CAC Brasil | B105: =B76 -> 352.02697 | C105: =C76 -> 757.08473 | D105: =D76 -> 1161.0776 | E105: VAN
A106: Flujos Brasil | B106: =B103-B105-B104 -> 1271.0893 | C106: =C103-C105-C104 -> 3266.441 | D106: =D103-D105-D104 -> 5373.2508 | E106: =NPV(Vaciado!D29,Flujos!B106:D106) -> 4881.6539
B108: 2024 | C108: 2025 | D108: 2026
A109: Ingresos ajustados Colombia | B109: =B96 -> 821.39626 | C109: =C96 -> 2040.3298 | D109: =D96 -> 3298.0246
A110: Costos operacionales Colombia | B110: =B109*(1-'Unit Economics'!C17) -> 63.941999 | C110: =C109*(1-'Unit Economics'!D17) -> 162.68445 | D110: =D109*(1-'Unit Economics'!E17) -> 248.67139
A111: CAC Colombia | B111: =B81 -> 219.039 | C111: =C81 -> 471.07494 | D111: =D81 -> 722.44825 | E111: VAN
A112: Flujos Colombia | B112: =B109-B111-B110 -> 538.41526 | C112: =C109-C111-C110 -> 1406.5704 | D112: =D109-D111-D110 -> 2326.905 | E112: =NPV(Vaciado!D29,Flujos!B112:D112) -> 2100.7856

Sheet P.Comercial
T2: 1 | U2: 2 | V2: 3 | W2: 4 | X2: 5 | Y2: 6 | Z2: 7 | AA2: 8 | AB2: 9 | AC2: 10 | AD2: 11 | AE2: 12 | AF2: 1 | AG2: 2 | AH2: 3 | AI2: 4 | AJ2: 5 | AK2: 6 | AL2: 7 | AM2: 8 | AN2: 9 | AO2: 10 | AP2: 11 | AQ2: 12
B3: ID | C3: Rango de usuarios | E3: Valor Paquete | G3: Tipo de cliente | H3: 2024 | T3: 2025 | AF3: 2026 | AS3: 2024 | BE3: 2025 | BQ3: 2026
E4: UF | H4: Enero | I4: Febrero | J4: Marzo | K4: Abril | L4: Mayo | M4: Junio | N4: Julio | O4: Agosto | P4: Septiembre | Q4: Octubre | R4: Noviembre | S4: Diciembre | T4: Enero | U4: Febrero | V4: Marzo | W4: Abril | X4: Mayo | Y4: Junio | Z4: Julio | AA4: Agosto | AB4: Septiembre | AC4: Octubre | AD4: Noviembre | AE4: Diciembre | AF4: Enero | AG4: Febrero | AH4: Marzo | AI4: Abril | AJ4: Mayo | AK4: Junio | AL4: Julio | AM4: Agosto | AN4: Septiembre | AO4: Octubre | AP4: Noviembre | AQ4: Diciembre | AS4: Enero | AT4: Febrero | AU4: Marzo | AV4: Abril | AW4: Mayo | AX4: Junio | AY4: Julio | AZ4: Agosto | BA4: Septiembre | BB4: Octubre | BC4: Noviembre | BD4: Diciembre | BE4: Enero | BF4: Febrero | BG4: Marzo | BH4: Abril | BI4: Mayo | BJ4: Junio | BK4: Julio | BL4: Agosto | BM4: Septiembre | BN4: Octubre | BO4: Noviembre | BP4: Diciembre | BQ4: Enero | BR4: Febrero | BS4: Marzo | BT4: Abril | BU4: Mayo | BV4: Junio | BW4: Julio | BX4: Agosto | BY4: Septiembre | BZ4: Octubre | CA4: Noviembre | CB4: Diciembre
B5: =Vaciado!B10 -> A | C5: =Vaciado!C10 -> 1 | D5: =Vaciado!D10 -> 25 | E5: =Vaciado!T18 -> 30 | G5: =B5 -> A | H5: =Vaciado!H10 -> 1 | I5: =Vaciado!I10 -> 0 | J5: =Vaciado!J10 -> 1 | K5: =Vaciado!K10 -> 3 | L5: =Vaciado!L10 -> 8 | M5: =Vaciado!M10 -> 8 | N5: =Vaciado!N10 -> 12 | O5: =Vaciado!O10 -> 16 | ... S5: =Vaciado!S10 -> 20 | T5: =INT(S5*(1+Vaciado!$H$26)^P.Comercial!T2) -> 20 | U5: =INT(T5*(1+Vaciado!$H$26)^P.Comercial!U2) -> 20 | V5: =INT(U5*(1+Vaciado!$H$26)^P.Comercial!V2) -> 20 | W5: =INT(V5*(1+Vaciado!$H$26)^P.Comercial!W2) -> 20 | X5: =INT(W5*(1+Vaciado!$H$26)^P.Comercial!X2) -> 21 | Y5: =INT(X5*(1+Vaciado!$H$26)^P.Comercial!Y2) -> 22 | Z5: =INT(Y5*(1+Vaciado!$H$26)^P.Comercial!Z2) -> 23 | AA5: =INT(Z5*(1+Vaciado!$H$26)^P.Comercial!AA2) -> 24 | ... AE5: =INT(AD5*(1+Vaciado!$H$26)^P.Comercial!AE2) -> 34 | AF5: =INT(AE5*(1+Vaciado!$I$26)^P.Comercial!AF2) -> 34 | AG5: =INT(AF5*(1+Vaciado!$I$26)^P.Comercial!AG2) -> 34 | AH5: =INT(AG5*(1+Vaciado!$I$26)^P.Comercial!AH2) -> 35 | AI5: =INT(AH5*(1+Vaciado!$I$26)^P.Comercial!AI2) -> 36 | AJ5: =INT(AI5*(1+Vaciado!$I$26)^P.Comercial!AJ2) -> 37 | AK5: =INT(AJ5*(1+Vaciado!$I$26)^P.Comercial!AK2) -> 39 | AL5: =INT(AK5*(1+Vaciado!$I$26)^P.Comercial!AL2) -> 41 | AM5: =INT(AL5*(1+Vaciado!$I$26)^P.Comercial!AM2) -> 44 | ... AQ5: =INT(AP5*(1+Vaciado!$I$26)^P.Comercial!AQ2) -> 66 | AS5: =IF(H10=0,0,H5/H10) -> 1 | AT5: =IF(I10=0,0,I5/I10) -> 0 | AU5: =IF(J10=0,0,J5/J10) -> 0.5 | AV5: =IF(K10=0,0,K5/K10) -> 0.42857143 | AW5: =IF(L10=0,0,L5/L10) -> 0.42105263 | AX5: =IF(M10=0,0,M5/M10) -> 0.42105263 | AY5: =IF(N10=0,0,N5/N10) -> 0.4 | AZ5: =IF(O10=0,0,O5/O10) -> 0.47058824 | ... CB5: =IF(AQ10=0,0,AQ5/AQ10) -> 0.6875
B6: =Vaciado!B11 -> B | C6: =Vaciado!C11 -> 1 | D6: =Vaciado!D11 -> 500 | E6: =Vaciado!T19 -> 100 | G6: =B6 -> B | H6: =Vaciado!H11 -> 0 | I6: =Vaciado!I11 -> 0 | J6: =Vaciado!J11 -> 1 | K6: =Vaciado!K11 -> 2 | L6: =Vaciado!L11 -> 8 | M6: =Vaciado!M11 -> 8 | N6: =Vaciado!N11 -> 12 | O6: =Vaciado!O11 -> 12 | ... S6: =Vaciado!S11 -> 12 | T6: =INT(S6*(1+Vaciado!$H$27)^P.Comercial!T2) -> 12 | U6: =INT(T6*(1+Vaciado!$H$27)^P.Comercial!U2) -> 12 | V6: =INT(U6*(1+Vaciado!$H$27)^P.Comercial!V2) -> 12 | W6: =INT(V6*(1+Vaciado!$H$27)^P.Comercial!W2) -> 12 | X6: =INT(W6*(1+Vaciado!$H$27)^P.Comercial!X2) -> 12 | Y6: =INT(X6*(1+Vaciado!$H$27)^P.Comercial!Y2) -> 12 | Z6: =INT(Y6*(1+Vaciado!$H$27)^P.Comercial!Z2) -> 12 | AA6: =INT(Z6*(1+Vaciado!$H$27)^P.Comercial!AA2) -> 12 | ... AE6: =INT(AD6*(1+Vaciado!$H$27)^P.Comercial!AE2) -> 16 | AF6: =INT(AE6*(1+Vaciado!$I$27)^P.Comercial!AF2) -> 16 | AG6: =INT(AF6*(1+Vaciado!$I$27)^P.Comercial!AG2) -> 16 | AH6: =INT(AG6*(1+Vaciado!$I$27)^P.Comercial!AH2) -> 16 | AI6: =INT(AH6*(1+Vaciado!$I$27)^P.Comercial!AI2) -> 16 | AJ6: =INT(AI6*(1+Vaciado!$I$27)^P.Comercial!AJ2) -> 16 | AK6: =INT(AJ6*(1+Vaciado!$I$27)^P.Comercial!AK2) -> 16 | AL6: =INT(AK6*(1+Vaciado!$I$27)^P.Comercial!AL2) -> 17 | AM6: =INT(AL6*(1+Vaciado!$I$27)^P.Comercial!AM2) -> 18 | ... AQ6: =INT(AP6*(1+Vaciado!$I$27)^P.Comercial!AQ2) -> 24 | AS6: =IF(H10=0,0,H6/H10) -> 0 | AT6: =IF(I10=0,0,I6/I10) -> 0 | AU6: =IF(J10=0,0,J6/J10) -> 0.5 | AV6: =IF(K10=0,0,K6/K10) -> 0.28571429 | AW6: =IF(L10=0,0,L6/L10) -> 0.42105263 | AX6: =IF(M10=0,0,M6/M10) -> 0.42105263 | AY6: =IF(N10=0,0,N6/N10) -> 0.4 | AZ6: =IF(O10=0,0,O6/O10) -> 0.35294118 | ... CB6: =IF(AQ10=0,0,AQ6/AQ10) -> 0.25
B7: =Vaciado!B12 -> C | C7: =Vaciado!C12 -> 501 | D7: =Vaciado!D12 -> 1000 | E7: =Vaciado!T20 -> 350 | G7: =B7 -> C | H7: =Vaciado!H12 -> 0 | I7: =Vaciado!I12 -> 0 | J7: =Vaciado!J12 -> 0 | K7: =Vaciado!K12 -> 1 | L7: =Vaciado!L12 -> 2 | M7: =Vaciado!M12 -> 2 | N7: =Vaciado!N12 -> 4 | O7: =Vaciado!O12 -> 4 | ... S7: =Vaciado!S12 -> 4 | T7: =INT(S7*(1+Vaciado!$H$28)^P.Comercial!T2) -> 4 | U7: =INT(T7*(1+Vaciado!$H$28)^P.Comercial!U2) -> 4 | V7: =INT(U7*(1+Vaciado!$H$28)^P.Comercial!V2) -> 4 | W7: =INT(V7*(1+Vaciado!$H$28)^P.Comercial!W2) -> 4 | X7: =INT(W7*(1+Vaciado!$H$28)^P.Comercial!X2) -> 4 | Y7: =INT(X7*(1+Vaciado!$H$28)^P.Comercial!Y2) -> 4 | Z7: =INT(Y7*(1+Vaciado!$H$28)^P.Comercial!Z2) -> 4 | AA7: =INT(Z7*(1+Vaciado!$H$28)^P.Comercial!AA2) -> 4 | ... AE7: =INT(AD7*(1+Vaciado!$H$28)^P.Comercial!AE2) -> 4 | AF7: =INT(AE7*(1+Vaciado!$I$28)^P.Comercial!AF2) -> 4 | AG7: =INT(AF7*(1+Vaciado!$I$28)^P.Comercial!AG2) -> 4 | AH7: =INT(AG7*(1+Vaciado!$I$28)^P.Comercial!AH2) -> 4 | AI7: =INT(AH7*(1+Vaciado!$I$28)^P.Comercial!AI2) -> 4 | AJ7: =INT(AI7*(1+Vaciado!$I$28)^P.Comercial!AJ2) -> 4 | AK7: =INT(AJ7*(1+Vaciado!$I$28)^P.Comercial!AK2) -> 4 | AL7: =INT(AK7*(1+Vaciado!$I$28)^P.Comercial!AL2) -> 4 | AM7: =INT(AL7*(1+Vaciado!$I$28)^P.Comercial!AM2) -> 4 | ... AQ7: =INT(AP7*(1+Vaciado!$I$28)^P.Comercial!AQ2) -> 4 | AS7: =IF(H10=0,0,H7/H10) -> 0 | AT7: =IF(I10=0,0,I7/I10) -> 0 | AU7: =IF(J10=0,0,J7/J10) -> 0 | AV7: =IF(K10=0,0,K7/K10) -> 0.14285714 | AW7: =IF(L10=0,0,L7/L10) -> 0.10526316 | AX7: =IF(M10=0,0,M7/M10) -> 0.10526316 | AY7: =IF(N10=0,0,N7/N10) -> 0.13333333 | AZ7: =IF(O10=0,0,O7/O10) -> 0.11764706 | ... CB7: =IF(AQ10=0,0,AQ7/AQ10) -> 0.041666667
B8: =Vaciado!B13 -> D | C8: =Vaciado!C13 -> 1001 | D8: =Vaciado!D13 -> + | E8: =Vaciado!T21 -> 1000 | G8: =B8 -> D | H8: =Vaciado!H13 -> 0 | I8: =Vaciado!I13 -> 0 | J8: =Vaciado!J13 -> 0 | K8: =Vaciado!K13 -> 1 | L8: =Vaciado!L13 -> 1 | M8: =Vaciado!M13 -> 1 | N8: =Vaciado!N13 -> 2 | O8: =Vaciado!O13 -> 2 | ... S8: =Vaciado!S13 -> 2 | T8: =INT(S8*(1+Vaciado!$H$29)^P.Comercial!T2) -> 2 | U8: =INT(T8*(1+Vaciado!$H$29)^P.Comercial!U2) -> 2 | V8: =INT(U8*(1+Vaciado!$H$29)^P.Comercial!V2) -> 2 | W8: =INT(V8*(1+Vaciado!$H$29)^P.Comercial!W2) -> 2 | X8: =INT(W8*(1+Vaciado!$H$29)^P.Comercial!X2) -> 2 | Y8: =INT(X8*(1+Vaciado!$H$29)^P.Comercial!Y2) -> 2 | Z8: =INT(Y8*(1+Vaciado!$H$29)^P.Comercial!Z2) -> 2 | AA8: =INT(Z8*(1+Vaciado!$H$29)^P.Comercial!AA2) -> 2 | ... AE8: =INT(AD8*(1+Vaciado!$H$29)^P.Comercial!AE2) -> 2 | AF8: =INT(AE8*(1+Vaciado!$I$29)^P.Comercial!AF2) -> 2 | AG8: =INT(AF8*(1+Vaciado!$I$29)^P.Comercial!AG2) -> 2 | AH8: =INT(AG8*(1+Vaciado!$I$29)^P.Comercial!AH2) -> 2 | AI8: =INT(AH8*(1+Vaciado!$I$29)^P.Comercial!AI2) -> 2 | AJ8: =INT(AI8*(1+Vaciado!$I$29)^P.Comercial!AJ2) -> 2 | AK8: =INT(AJ8*(1+Vaciado!$I$29)^P.Comercial!AK2) -> 2 | AL8: =INT(AK8*(1+Vaciado!$I$29)^P.Comercial!AL2) -> 2 | AM8: =INT(AL8*(1+Vaciado!$I$29)^P.Comercial!AM2) -> 2 | ... AQ8: =INT(AP8*(1+Vaciado!$I$29)^P.Comercial!AQ2) -> 2 | AS8: =IF(H10=0,0,H8/H10) -> 0 | AT8: =IF(I10=0,0,I8/I10) -> 0 | AU8: =IF(J10=0,0,J8/J10) -> 0 | AV8: =IF(K10=0,0,K8/K10) -> 0.14285714 | AW8: =IF(L10=0,0,L8/L10) -> 0.052631579 | AX8: =IF(M10=0,0,M8/M10) -> 0.052631579 | AY8: =IF(N10=0,0,N8/N10) -> 0.066666667 | AZ8: =IF(O10=0,0,O8/O10) -> 0.058823529 | ... CB8: =IF(AQ10=0,0,AQ8/AQ10) -> 0.020833333
B9: =Vaciado!B14 -> E | C9: =Vaciado!C14 -> 0 | D9: =Vaciado!D14 -> 0 | E9: =Vaciado!T22 -> 0 | G9: =B9 -> E | H9: =Vaciado!H14 -> 0 | I9: =Vaciado!I14 -> 0 | J9: =Vaciado!J14 -> 0 | K9: =Vaciado!K14 -> 0 | L9: =Vaciado!L14 -> 0 | M9: =Vaciado!M14 -> 0 | N9: =Vaciado!N14 -> 0 | O9: =Vaciado!O14 -> 0 | ... S9: =Vaciado!S14 -> 0 | T9: =INT(S9*(1+Vaciado!$H$30)^P.Comercial!T2) -> 0 | U9: =INT(T9*(1+Vaciado!$H$30)^P.Comercial!U2) -> 0 | V9: =INT(U9*(1+Vaciado!$H$30)^P.Comercial!V2) -> 0 | W9: =INT(V9*(1+Vaciado!$H$30)^P.Comercial!W2) -> 0 | X9: =INT(W9*(1+Vaciado!$H$30)^P.Comercial!X2) -> 0 | Y9: =INT(X9*(1+Vaciado!$H$30)^P.Comercial!Y2) -> 0 | Z9: =INT(Y9*(1+Vaciado!$H$30)^P.Comercial!Z2) -> 0 | AA9: =INT(Z9*(1+Vaciado!$H$30)^P.Comercial!AA2) -> 0 | ... AE9: =INT(AD9*(1+Vaciado!$H$30)^P.Comercial!AE2) -> 0 | AF9: =INT(AE9*(1+Vaciado!$I$30)^P.Comercial!AF2) -> 0 | AG9: =INT(AF9*(1+Vaciado!$I$30)^P.Comercial!AG2) -> 0 | AH9: =INT(AG9*(1+Vaciado!$I$30)^P.Comercial!AH2) -> 0 | AI9: =INT(AH9*(1+Vaciado!$I$30)^P.Comercial!AI2) -> 0 | AJ9: =INT(AI9*(1+Vaciado!$I$30)^P.Comercial!AJ2) -> 0 | AK9: =INT(AJ9*(1+Vaciado!$I$30)^P.Comercial!AK2) -> 0 | AL9: =INT(AK9*(1+Vaciado!$I$30)^P.Comercial!AL2) -> 0 | AM9: =INT(AL9*(1+Vaciado!$I$30)^P.Comercial!AM2) -> 0 | ... AQ9: =INT(AP9*(1+Vaciado!$I$30)^P.Comercial!AQ2) -> 0 | AS9: =IF(H10=0,0,H9/H10) -> 0 | AT9: =IF(I10=0,0,I9/I10) -> 0 | AU9: =IF(J10=0,0,J9/J10) -> 0 | AV9: =IF(K10=0,0,K9/K10) -> 0 | AW9: =IF(L10=0,0,L9/L10) -> 0 | AX9: =IF(M10=0,0,M9/M10) -> 0 | AY9: =IF(N10=0,0,N9/N10) -> 0 | AZ9: =IF(O10=0,0,O9/O10) -> 0 | ... CB9: =IF(AQ10=0,0,AQ9/AQ10) -> 0
G10: Total Clientes nuevos | H10: =SUM(H5:H9) -> 1 | I10: =SUM(I5:I9) -> 0 | J10: =SUM(J5:J9) -> 2 | K10: =SUM(K5:K9) -> 7 | L10: =SUM(L5:L9) -> 19 | M10: =SUM(M5:M9) -> 19 | N10: =SUM(N5:N9) -> 30 | O10: =SUM(O5:O9) -> 34 | ... AQ10: =SUM(AQ5:AQ9) -> 96 | AS10: =IF(H10=0,0,H10/H10) -> 1 | AT10: =IF(I10=0,0,I10/I10) -> 0 | AU10: =IF(J10=0,0,J10/J10) -> 1 | AV10: =IF(K10=0,0,K10/K10) -> 1 | AW10: =IF(L10=0,0,L10/L10) -> 1 | AX10: =IF(M10=0,0,M10/M10) -> 1 | AY10: =IF(N10=0,0,N10/N10) -> 1 | AZ10: =IF(O10=0,0,O10/O10) -> 1 | ... CB10: =IF(AQ10=0,0,AQ10/AQ10) -> 1
G12: Exp. Piloto | H12: 2024 | T12: 2025 | AF12: 2026
H13: Enero | I13: Febrero | J13: Marzo | K13: Abril | L13: Mayo | M13: Junio | N13: Julio | O13: Agosto | P13: Septiembre | Q13: Octubre | R13: Noviembre | S13: Diciembre | T13: Enero | U13: Febrero | V13: Marzo | W13: Abril | X13: Mayo | Y13: Junio | Z13: Julio | AA13: Agosto | AB13: Septiembre | AC13: Octubre | AD13: Noviembre | AE13: Diciembre | AF13: Enero | AG13: Febrero | AH13: Marzo | AI13: Abril | AJ13: Mayo | AK13: Junio | AL13: Julio | AM13: Agosto | AN13: Septiembre | AO13: Octubre | AP13: Noviembre | AQ13: Diciembre
G14: Piloto | H14: =Vaciado!H34 -> 0 | I14: =Vaciado!I34 -> 0 | J14: =Vaciado!J34 -> 0 | K14: =Vaciado!K34 -> 0 | L14: =Vaciado!L34 -> 0 | M14: =Vaciado!M34 -> 0 | N14: =Vaciado!N34 -> 0 | O14: =Vaciado!O34 -> 0 | ... S14: =Vaciado!S34 -> 0 | T14: =INT(S14*((1+Vaciado!$H$39)^P.Comercial!T2)) -> 0 | U14: =INT(T14*((1+Vaciado!$H$39)^P.Comercial!U2)) -> 0 | V14: =INT(U14*((1+Vaciado!$H$39)^P.Comercial!V2)) -> 0 | W14: =INT(V14*((1+Vaciado!$H$39)^P.Comercial!W2)) -> 0 | X14: =INT(W14*((1+Vaciado!$H$39)^P.Comercial!X2)) -> 0 | Y14: =INT(X14*((1+Vaciado!$H$39)^P.Comercial!Y2)) -> 0 | Z14: =INT(Y14*((1+Vaciado!$H$39)^P.Comercial!Z2)) -> 0 | AA14: =INT(Z14*((1+Vaciado!$H$39)^P.Comercial!AA2)) -> 0 | ... AE14: =INT(AD14*((1+Vaciado!$H$39)^P.Comercial!AE2)) -> 0 | AF14: =INT(AE14*((1+Vaciado!$H$40)^P.Comercial!AF2)) -> 0 | AG14: =INT(AF14*((1+Vaciado!$H$40)^P.Comercial!AG2)) -> 0 | AH14: =INT(AG14*((1+Vaciado!$H$40)^P.Comercial!AH2)) -> 0 | AI14: =INT(AH14*((1+Vaciado!$H$40)^P.Comercial!AI2)) -> 0 | AJ14: =INT(AI14*((1+Vaciado!$H$40)^P.Comercial!AJ2)) -> 0 | AK14: =INT(AJ14*((1+Vaciado!$H$40)^P.Comercial!AK2)) -> 0 | AL14: =INT(AK14*((1+Vaciado!$H$40)^P.Comercial!AL2)) -> 0 | AM14: =INT(AL14*((1+Vaciado!$H$40)^P.Comercial!AM2)) -> 0 | ... AQ14: =INT(AP14*((1+Vaciado!$H$40)^P.Comercial!AQ2)) -> 0
G15: Experiencia piloto traducidos a tipos de clientes:
G16: =Vaciado!B10 -> A | H16: =H14*'Para reporte'!$G$13 -> 0 | I16: =I14*'Para reporte'!$G$13 -> 0 | J16: =J14*'Para reporte'!$G$13 -> 0 | K16: =K14*'Para reporte'!$G$13 -> 0 | L16: =L14*'Para reporte'!$G$13 -> 0 | M16: =M14*'Para reporte'!$G$13 -> 0 | N16: =N14*'Para reporte'!$G$13 -> 0 | O16: =O14*'Para reporte'!$G$13 -> 0 | ... AQ16: =AQ14*'Para reporte'!$G$13 -> 0
G17: =Vaciado!B11 -> B | H17: =H14*'Para reporte'!$G$14 -> 0 | I17: =I14*'Para reporte'!$G$14 -> 0 | J17: =J14*'Para reporte'!$G$14 -> 0 | K17: =K14*'Para reporte'!$G$14 -> 0 | L17: =L14*'Para reporte'!$G$14 -> 0 | M17: =M14*'Para reporte'!$G$14 -> 0 | N17: =N14*'Para reporte'!$G$14 -> 0 | O17: =O14*'Para reporte'!$G$14 -> 0 | ... AQ17: =AQ14*'Para reporte'!$G$14 -> 0
G18: =Vaciado!B12 -> C | H18: =H14*'Para reporte'!$G$15 -> 0 | I18: =I14*'Para reporte'!$G$15 -> 0 | J18: =J14*'Para reporte'!$G$15 -> 0 | K18: =K14*'Para reporte'!$G$15 -> 0 | L18: =L14*'Para reporte'!$G$15 -> 0 | M18: =M14*'Para reporte'!$G$15 -> 0 | N18: =N14*'Para reporte'!$G$15 -> 0 | O18: =O14*'Para reporte'!$G$15 -> 0 | ... AQ18: =AQ14*'Para reporte'!$G$15 -> 0
G19: =Vaciado!B13 -> D | H19: =H14*'Para reporte'!$G$16 -> 0 | I19: =I14*'Para reporte'!$G$16 -> 0 | J19: =J14*'Para reporte'!$G$16 -> 0 | K19: =K14*'Para reporte'!$G$16 -> 0 | L19: =L14*'Para reporte'!$G$16 -> 0 | M19: =M14*'Para reporte'!$G$16 -> 0 | N19: =N14*'Para reporte'!$G$16 -> 0 | O19: =O14*'Para reporte'!$G$16 -> 0 | ... AQ19: =AQ14*'Para reporte'!$G$16 -> 0
G20: =Vaciado!B14 -> E | H20: =H14*'Para reporte'!$G$17 -> 0 | I20: =I14*'Para reporte'!$G$17 -> 0 | J20: =J14*'Para reporte'!$G$17 -> 0 | K20: =K14*'Para reporte'!$G$17 -> 0 | L20: =L14*'Para reporte'!$G$17 -> 0 | M20: =M14*'Para reporte'!$G$17 -> 0 | N20: =N14*'Para reporte'!$G$17 -> 0 | O20: =O14*'Para reporte'!$G$17 -> 0 | ... AQ20: =AQ14*'Para reporte'!$G$17 -> 0
G21: Total traducidos | H21: =SUM(H16:H20) -> 0 | I21: =SUM(I16:I20) -> 0 | J21: =SUM(J16:J20) -> 0 | K21: =SUM(K16:K20) -> 0 | L21: =SUM(L16:L20) -> 0 | M21: =SUM(M16:M20) -> 0 | N21: =SUM(N16:N20) -> 0 | O21: =SUM(O16:O20) -> 0 | ... AQ21: =SUM(AQ16:AQ20) -> 0
G23: Total de clientes nuevos | H23: =SUM(H5:H9) -> 1 | I23: =SUM(I5:I9) -> 0 | J23: =SUM(J5:J9) -> 2 | K23: =SUM(K5:K9) -> 7 | L23: =SUM(L5:L9) -> 19 | M23: =SUM(M5:M9) -> 19 | N23: =SUM(N5:N9) -> 30 | O23: =SUM(O5:O9) -> 34 | ... AQ23: =SUM(AQ5:AQ9) -> 96
G24: Total de clientes x exp. Piloto | K24: =H21*Vaciado!$K$37 -> 0 | L24: =I21*Vaciado!$K$37 -> 0 | M24: =J21*Vaciado!$K$37 -> 0 | N24: =K21*Vaciado!$K$37 -> 0 | O24: =L21*Vaciado!$K$37 -> 0 | P24: =M21*Vaciado!$K$37 -> 0 | Q24: =N21*Vaciado!$K$37 -> 0 | R24: =O21*Vaciado!$K$37 -> 0 | ... AQ24: =AN21*Vaciado!$K$37 -> 0
G25: Adqusición de Clientes (#) | H25: =H23+H24 -> 1 | I25: =I23+I24 -> 0 | J25: =J23+J24 -> 2 | K25: =K23+K24 -> 7 | L25: =L23+L24 -> 19 | M25: =M23+M24 -> 19 | N25: =N23+N24 -> 30 | O25: =O23+O24 -> 34 | ... AQ25: =AQ23+AQ24 -> 96
G26: CHURN de clientes (#) | H26: =-H25*Vaciado!$D$33 -> -0.5 | I26: =-I25*Vaciado!$D$33 -> 0 | J26: =-J25*Vaciado!$D$33 -> -1 | K26: =-K25*Vaciado!$D$33 -> -3.5 | L26: =-L25*Vaciado!$D$33 -> -9.5 | M26: =-M25*Vaciado!$D$33 -> -9.5 | N26: =-N25*Vaciado!$D$33 -> -15 | O26: =-O25*Vaciado!$D$33 -> -17 | ... AQ26: =-AQ25*Vaciado!$D$33 -> -48
G27: Clientes acumulados | H27: =H25+H26 -> 0.5 | I27: =H27+I25+I26 -> 0.5 | J27: =I27+J25+J26 -> 1.5 | K27: =J27+K25+K26 -> 5 | L27: =K27+L25+L26 -> 14.5 | M27: =L27+M25+M26 -> 24 | N27: =M27+N25+N26 -> 39 | O27: =N27+O25+O26 -> 56 | P27: =O27+P25+P26 -> 73 | ... AQ27: =AP27+AQ25+AQ26 -> 794.5
G28: Clientes del período | H28: =H25+H26 -> 0.5 | I28: =I25+I26 -> 0 | J28: =J25+J26 -> 1 | K28: =K25+K26 -> 3.5 | L28: =L25+L26 -> 9.5 | M28: =M25+M26 -> 9.5 | N28: =N25+N26 -> 15 | O28: =O25+O26 -> 17 | ... AQ28: =AQ25+AQ26 -> 48
G30: Ventas recurrentes | H30: =Recurrencia!AQ3 -> 0 | I30: =Recurrencia!AR3 -> 0 | J30: =Recurrencia!AS3 -> 0 | K30: =Recurrencia!AT3 -> 0 | L30: =Recurrencia!AU3 -> 0 | M30: =Recurrencia!AV3 -> 0 | N30: =Recurrencia!AW3 -> 0 | O30: =Recurrencia!AX3 -> 0 | ... AQ30: =Recurrencia!BZ3 -> 47.5
G31: Ventas recurrentes traducidos a tipos de clientes:
G32: =Vaciado!B10 -> A | H32: =H30*'Para reporte'!$G$13 -> 0 | I32: =I30*'Para reporte'!$G$13 -> 0 | J32: =J30*'Para reporte'!$G$13 -> 0 | K32: =K30*'Para reporte'!$G$13 -> 0 | L32: =L30*'Para reporte'!$G$13 -> 0 | M32: =M30*'Para reporte'!$G$13 -> 0 | N32: =N30*'Para reporte'!$G$13 -> 0 | O32: =O30*'Para reporte'!$G$13 -> 0 | ... AQ32: =AQ30*'Para reporte'!$G$13 -> 28.099434
G33: =Vaciado!B11 -> B | H33: =H30*'Para reporte'!$G$14 -> 0 | I33: =I30*'Para reporte'!$G$14 -> 0 | J33: =J30*'Para reporte'!$G$14 -> 0 | K33: =K30*'Para reporte'!$G$14 -> 0 | L33: =L30*'Para reporte'!$G$14 -> 0 | M33: =M30*'Para reporte'!$G$14 -> 0 | N33: =N30*'Para reporte'!$G$14 -> 0 | O33: =O30*'Para reporte'!$G$14 -> 0 | ... AQ33: =AQ30*'Para reporte'!$G$14 -> 13.78068
G34: =Vaciado!B12 -> C | H34: =H30*'Para reporte'!$G$15 -> 0 | I34: =I30*'Para reporte'!$G$15 -> 0 | J34: =J30*'Para reporte'!$G$15 -> 0 | K34: =K30*'Para reporte'!$G$15 -> 0 | L34: =L30*'Para reporte'!$G$15 -> 0 | M34: =M30*'Para reporte'!$G$15 -> 0 | N34: =N30*'Para reporte'!$G$15 -> 0 | O34: =O30*'Para reporte'!$G$15 -> 0 | ... AQ34: =AQ30*'Para reporte'!$G$15 -> 3.7366268
G35: =Vaciado!B13 -> D | H35: =H30*'Para reporte'!$G$16 -> 0 | I35: =I30*'Para reporte'!$G$16 -> 0 | J35: =J30*'Para reporte'!$G$16 -> 0 | K35: =K30*'Para reporte'!$G$16 -> 0 | L35: =L30*'Para reporte'!$G$16 -> 0 | M35: =M30*'Para reporte'!$G$16 -> 0 | N35: =N30*'Para reporte'!$G$16 -> 0 | O35: =O30*'Para reporte'!$G$16 -> 0 | ... AQ35: =AQ30*'Para reporte'!$G$16 -> 1.8832599
G36: =Vaciado!B14 -> E | H36: =H30*'Para reporte'!$G$17 -> 0 | I36: =I30*'Para reporte'!$G$17 -> 0 | J36: =J30*'Para reporte'!$G$17 -> 0 | K36: =K30*'Para reporte'!$G$17 -> 0 | L36: =L30*'Para reporte'!$G$17 -> 0 | M36: =M30*'Para reporte'!$G$17 -> 0 | N36: =N30*'Para reporte'!$G$17 -> 0 | O36: =O30*'Para reporte'!$G$17 -> 0 | ... AQ36: =AQ30*'Para reporte'!$G$17 -> 0
G38: Clientes nuevos + experiencia piloto + recurrencia (total de servicios)
G39: =Vaciado!B10 -> A | H39: =H5+H16+H32 -> 1 | I39: =I5+I16+I32 -> 0 | J39: =J5+J16+J32 -> 1 | K39: =K5+K16+K32 -> 3 | L39: =L5+L16+L32 -> 8 | M39: =M5+M16+M32 -> 8 | N39: =N5+N16+N32 -> 12 | O39: =O5+O16+O32 -> 16 | ... AQ39: =AQ5+AQ16+AQ32 -> 94.099434
G40: =Vaciado!B11 -> B | H40: =H6+H17+H33 -> 0 | I40: =I6+I17+I33 -> 0 | J40: =J6+J17+J33 -> 1 | K40: =K6+K17+K33 -> 2 | L40: =L6+L17+L33 -> 8 | M40: =M6+M17+M33 -> 8 | N40: =N6+N17+N33 -> 12 | O40: =O6+O17+O33 -> 12 | ... AQ40: =AQ6+AQ17+AQ33 -> 37.78068
G41: =Vaciado!B12 -> C | H41: =H7+H18+H34 -> 0 | I41: =I7+I18+I34 -> 0 | J41: =J7+J18+J34 -> 0 | K41: =K7+K18+K34 -> 1 | L41: =L7+L18+L34 -> 2 | M41: =M7+M18+M34 -> 2 | N41: =N7+N18+N34 -> 4 | O41: =O7+O18+O34 -> 4 | ... AQ41: =AQ7+AQ18+AQ34 -> 7.7366268
G42: =Vaciado!B13 -> D | H42: =H8+H19+H35 -> 0 | I42: =I8+I19+I35 -> 0 | J42: =J8+J19+J35 -> 0 | K42: =K8+K19+K35 -> 1 | L42: =L8+L19+L35 -> 1 | M42: =M8+M19+M35 -> 1 | N42: =N8+N19+N35 -> 2 | O42: =O8+O19+O35 -> 2 | ... AQ42: =AQ8+AQ19+AQ35 -> 3.8832599
G43: =Vaciado!B14 -> E | H43: =H9+H20+H36 -> 0 | I43: =I9+I20+I36 -> 0 | J43: =J9+J20+J36 -> 0 | K43: =K9+K20+K36 -> 0 | L43: =L9+L20+L36 -> 0 | M43: =M9+M20+M36 -> 0 | N43: =N9+N20+N36 -> 0 | O43: =O9+O20+O36 -> 0 | ... AQ43: =AQ9+AQ20+AQ36 -> 0
G44: Total de servicios | H44: =SUM(H39:H43) -> 1 | I44: =SUM(I39:I43) -> 0 | J44: =SUM(J39:J43) -> 2 | K44: =SUM(K39:K43) -> 7 | L44: =SUM(L39:L43) -> 19 | M44: =SUM(M39:M43) -> 19 | N44: =SUM(N39:N43) -> 30 | O44: =SUM(O39:O43) -> 34 | ... AQ44: =SUM(AQ39:AQ43) -> 143.5
A46: Para comprobar: | G46: Ingresos por tipo de cliente del período en MUS$
C47: 2024 | D47: 2025 | E47: 2026 | G47: =Vaciado!B10 -> A | H47: =H39*(((Vaciado!H18*Vaciado!$D$16)/Vaciado!$D$17)/1000) -> 1.2333333 | I47: =I39*(((Vaciado!I18*Vaciado!$D$16)/Vaciado!$D$17)/1000) -> 0 | J47: =J39*(((Vaciado!J18*Vaciado!$D$16)/Vaciado!$D$17)/1000) -> 1.2333333 | K47: =K39*(((Vaciado!K18*Vaciado!$D$16)/Vaciado!$D$17)/1000) -> 3.7 | L47: =L39*(((Vaciado!L18*Vaciado!$D$16)/Vaciado!$D$17)/1000) -> 9.8666667 | M47: =M39*(((Vaciado!M18*Vaciado!$D$16)/Vaciado!$D$17)/1000) -> 9.8666667 | N47: =N39*(((Vaciado!N18*Vaciado!$D$16)/Vaciado!$D$17)/1000) -> 14.8 | O47: =O39*(((Vaciado!O18*Vaciado!$D$16)/Vaciado!$D$17)/1000) -> 19.733333 | ... S47: =S39*(((Vaciado!S18*Vaciado!$D$16)/Vaciado!$D$17)/1000) -> 25.031466 | T47: =T39*'Para reporte'!$F$4 -> 24.666667 | U47: =U39*'Para reporte'!$F$4 -> 25.396266 | V47: =V39*'Para reporte'!$F$4 -> 27.220264 | W47: =W39*'Para reporte'!$F$4 -> 31.59786 | X47: =X39*'Para reporte'!$F$4 -> 32.831194 | Y47: =Y39*'Para reporte'!$F$4 -> 38.077323 | Z47: =Z39*'Para reporte'!$F$4 -> 40.769855 | AA47: =AA39*'Para reporte'!$F$4 -> 42.003189 | ... AQ47: =AQ39*'Para reporte'!$F$4 -> 116.05597
A48: =SUM(C48:E48) -> 10089.73 | C48: ='Para reporte'!J13 -> 1564.5643 | D48: ='Para reporte'!K13 -> 3364.821 | E48: ='Para reporte'!L13 -> 5160.3447 | G48: =Vaciado!B11 -> B | H48: =H40*(((Vaciado!H19*Vaciado!$D$16)/Vaciado!$D$17)/1000) -> 0 | I48: =I40*(((Vaciado!I19*Vaciado!$D$16)/Vaciado!$D$17)/1000) -> 0 | J48: =J40*(((Vaciado!J19*Vaciado!$D$16)/Vaciado!$D$17)/1000) -> 4.1111111 | K48: =K40*(((Vaciado!K19*Vaciado!$D$16)/Vaciado!$D$17)/1000) -> 8.2222222 | L48: =L40*(((Vaciado!L19*Vaciado!$D$16)/Vaciado!$D$17)/1000) -> 32.888889 | M48: =M40*(((Vaciado!M19*Vaciado!$D$16)/Vaciado!$D$17)/1000) -> 32.888889 | N48: =N40*(((Vaciado!N19*Vaciado!$D$16)/Vaciado!$D$17)/1000) -> 49.333333 | O48: =O40*(((Vaciado!O19*Vaciado!$D$16)/Vaciado!$D$17)/1000) -> 49.333333 | ... S48: =S40*(((Vaciado!S19*Vaciado!$D$16)/Vaciado!$D$17)/1000) -> 49.92969 | T48: =T40*'Para reporte'!$F$5 -> 49.333333 | U48: =U40*'Para reporte'!$F$5 -> 50.526047 | V48: =V40*'Para reporte'!$F$5 -> 53.507832 | W48: =W40*'Para reporte'!$F$5 -> 60.664114 | X48: =X40*'Para reporte'!$F$5 -> 60.664114 | Y48: =Y40*'Para reporte'!$F$5 -> 67.22404 | Z48: =Z40*'Para reporte'!$F$5 -> 69.609468 | AA48: =AA40*'Para reporte'!$F$5 -> 69.609468 | ... AQ48: =AQ40*'Para reporte'!$F$5 -> 155.32057
A49: =SUM(C49:E49) -> 10089.73 | C49: =SUM(H52:S52) -> 1564.5643 | D49: =SUM(T52:AE52) -> 3364.821 | E49: =SUM(AF52:AQ52) -> 5160.3447 | G49: =Vaciado!B12 -> C | H49: =H41*(((Vaciado!H20*Vaciado!$D$16)/Vaciado!$D$17)/1000) -> 0 | I49: =I41*(((Vaciado!I20*Vaciado!$D$16)/Vaciado!$D$17)/1000) -> 0 | J49: =J41*(((Vaciado!J20*Vaciado!$D$16)/Vaciado!$D$17)/1000) -> 0 | K49: =K41*(((Vaciado!K20*Vaciado!$D$16)/Vaciado!$D$17)/1000) -> 14.388889 | L49: =L41*(((Vaciado!L20*Vaciado!$D$16)/Vaciado!$D$17)/1000) -> 28.777778 | M49: =M41*(((Vaciado!M20*Vaciado!$D$16)/Vaciado!$D$17)/1000) -> 28.777778 | N49: =N41*(((Vaciado!N20*Vaciado!$D$16)/Vaciado!$D$17)/1000) -> 57.555556 | O49: =O41*(((Vaciado!O20*Vaciado!$D$16)/Vaciado!$D$17)/1000) -> 57.555556 | ... S49: =S41*(((Vaciado!S20*Vaciado!$D$16)/Vaciado!$D$17)/1000) -> 58.121512 | T49: =T41*'Para reporte'!$F$6 -> 57.555556 | U49: =U41*'Para reporte'!$F$6 -> 58.687469 | V49: =V41*'Para reporte'!$F$6 -> 61.517254 | W49: =W41*'Para reporte'!$F$6 -> 68.308737 | X49: =X41*'Para reporte'!$F$6 -> 68.308737 | Y49: =Y41*'Para reporte'!$F$6 -> 74.534263 | Z49: =Z41*'Para reporte'!$F$6 -> 76.798091 | AA49: =AA41*'Para reporte'!$F$6 -> 76.798091 | ... AQ49: =AQ41*'Para reporte'!$F$6 -> 111.32146
A50: =SUM(C50:E50) -> 10089.73 | C50: =C57+C65+C73 -> 1564.5643 | D50: =D57+D65+D73 -> 3364.821 | E50: =E57+E65+E73 -> 5160.3447 | G50: =Vaciado!B13 -> D | H50: =H42*(((Vaciado!H21*Vaciado!$D$16)/Vaciado!$D$17)/1000) -> 0 | I50: =I42*(((Vaciado!I21*Vaciado!$D$16)/Vaciado!$D$17)/1000) -> 0 | J50: =J42*(((Vaciado!J21*Vaciado!$D$16)/Vaciado!$D$17)/1000) -> 0 | K50: =K42*(((Vaciado!K21*Vaciado!$D$16)/Vaciado!$D$17)/1000) -> 41.111111 | L50: =L42*(((Vaciado!L21*Vaciado!$D$16)/Vaciado!$D$17)/1000) -> 41.111111 | M50: =M42*(((Vaciado!M21*Vaciado!$D$16)/Vaciado!$D$17)/1000) -> 41.111111 | N50: =N42*(((Vaciado!N21*Vaciado!$D$16)/Vaciado!$D$17)/1000) -> 82.222222 | O50: =O42*(((Vaciado!O21*Vaciado!$D$16)/Vaciado!$D$17)/1000) -> 82.222222 | ... S50: =S42*(((Vaciado!S21*Vaciado!$D$16)/Vaciado!$D$17)/1000) -> 83.0372 | T50: =T42*'Para reporte'!$F$7 -> 82.222222 | U50: =U42*'Para reporte'!$F$7 -> 83.852178 | V50: =V42*'Para reporte'!$F$7 -> 87.927068 | W50: =W42*'Para reporte'!$F$7 -> 97.706804 | X50: =X42*'Para reporte'!$F$7 -> 97.706804 | Y50: =Y42*'Para reporte'!$F$7 -> 106.67156 | Z50: =Z42*'Para reporte'!$F$7 -> 109.93147 | AA50: =AA42*'Para reporte'!$F$7 -> 109.93147 | ... AQ50: =AQ42*'Para reporte'!$F$7 -> 159.64513
G51: =Vaciado!B14 -> E | H51: =H43*(((Vaciado!H22*Vaciado!$D$16)/Vaciado!$D$17)/1000) -> 0 | I51: =I43*(((Vaciado!I22*Vaciado!$D$16)/Vaciado!$D$17)/1000) -> 0 | J51: =J43*(((Vaciado!J22*Vaciado!$D$16)/Vaciado!$D$17)/1000) -> 0 | K51: =K43*(((Vaciado!K22*Vaciado!$D$16)/Vaciado!$D$17)/1000) -> 0 | L51: =L43*(((Vaciado!L22*Vaciado!$D$16)/Vaciado!$D$17)/1000) -> 0 | M51: =M43*(((Vaciado!M22*Vaciado!$D$16)/Vaciado!$D$17)/1000) -> 0 | N51: =N43*(((Vaciado!N22*Vaciado!$D$16)/Vaciado!$D$17)/1000) -> 0 | O51: =O43*(((Vaciado!O22*Vaciado!$D$16)/Vaciado!$D$17)/1000) -> 0 | ... S51: =S43*(((Vaciado!S22*Vaciado!$D$16)/Vaciado!$D$17)/1000) -> 0 | T51: =T43*'Para reporte'!$F$8 -> 0 | U51: =U43*'Para reporte'!$F$8 -> 0 | V51: =V43*'Para reporte'!$F$8 -> 0 | W51: =W43*'Para reporte'!$F$8 -> 0 | X51: =X43*'Para reporte'!$F$8 -> 0 | Y51: =Y43*'Para reporte'!$F$8 -> 0 | Z51: =Z43*'Para reporte'!$F$8 -> 0 | AA51: =AA43*'Para reporte'!$F$8 -> 0 | ... AQ51: =AQ43*'Para reporte'!$F$8 -> 0
G52: Total de ingresos (MUS$) | H52: =SUM(H47:H51) -> 1.2333333 | I52: =SUM(I47:I51) -> 0 | J52: =SUM(J47:J51) -> 5.3444444 | K52: =SUM(K47:K51) -> 67.422222 | L52: =SUM(L47:L51) -> 112.64444 | M52: =SUM(M47:M51) -> 112.64444 | N52: =SUM(N47:N51) -> 203.91111 | O52: =SUM(O47:O51) -> 208.84444 | ... AQ52: =SUM(AQ47:AQ51) -> 542.34313
A54: Para comprobar: | G54: Ingresos de clientes nuevos en MUS$
C55: 2024 | D55: 2025 | E55: 2026 | G55: =Vaciado!B10 -> A | H55: =H5*'Para reporte'!$F$4 -> 1.2333333 | I55: =I5*'Para reporte'!$F$4 -> 0 | J55: =J5*'Para reporte'!$F$4 -> 1.2333333 | K55: =K5*'Para reporte'!$F$4 -> 3.7 | L55: =L5*'Para reporte'!$F$4 -> 9.8666667 | M55: =M5*'Para reporte'!$F$4 -> 9.8666667 | N55: =N5*'Para reporte'!$F$4 -> 14.8 | O55: =O5*'Para reporte'!$F$4 -> 19.733333 | ... AQ55: =AQ5*'Para reporte'!$F$4 -> 81.4
A56: =SUM(C56:E56) -> 7443.1667 | C56: ='Para reporte'!J26 -> 1562.2222 | D56: ='Para reporte'!K26 -> 2666.8778 | E56: ='Para reporte'!L26 -> 3214.0667 | G56: =Vaciado!B11 -> B | H56: =H6*'Para reporte'!$F$5 -> 0 | I56: =I6*'Para reporte'!$F$5 -> 0 | J56: =J6*'Para reporte'!$F$5 -> 4.1111111 | K56: =K6*'Para reporte'!$F$5 -> 8.2222222 | L56: =L6*'Para reporte'!$F$5 -> 32.888889 | M56: =M6*'Para reporte'!$F$5 -> 32.888889 | N56: =N6*'Para reporte'!$F$5 -> 49.333333 | O56: =O6*'Para reporte'!$F$5 -> 49.333333 | ... AQ56: =AQ6*'Para reporte'!$F$5 -> 98.666667
A57: =SUM(C57:E57) -> 7443.1667 | C57: =SUM(H60:S60) -> 1562.2222 | D57: =SUM(T60:AE60) -> 2666.8778 | E57: =SUM(AF60:AQ60) -> 3214.0667 | G57: =Vaciado!B12 -> C | H57: =H7*'Para reporte'!$F$6 -> 0 | I57: =I7*'Para reporte'!$F$6 -> 0 | J57: =J7*'Para reporte'!$F$6 -> 0 | K57: =K7*'Para reporte'!$F$6 -> 14.388889 | L57: =L7*'Para reporte'!$F$6 -> 28.777778 | M57: =M7*'Para reporte'!$F$6 -> 28.777778 | N57: =N7*'Para reporte'!$F$6 -> 57.555556 | O57: =O7*'Para reporte'!$F$6 -> 57.555556 | ... AQ57: =AQ7*'Para reporte'!$F$6 -> 57.555556
G58: =Vaciado!B13 -> D | H58: =H8*'Para reporte'!$F$7 -> 0 | I58: =I8*'Para reporte'!$F$7 -> 0 | J58: =J8*'Para reporte'!$F$7 -> 0 | K58: =K8*'Para reporte'!$F$7 -> 41.111111 | L58: =L8*'Para reporte'!$F$7 -> 41.111111 | M58: =M8*'Para reporte'!$F$7 -> 41.111111 | N58: =N8*'Para reporte'!$F$7 -> 82.222222 | O58: =O8*'Para reporte'!$F$7 -> 82.222222 | ... AQ58: =AQ8*'Para reporte'!$F$7 -> 82.222222
G59: =Vaciado!B14 -> E | H59: =H9*'Para reporte'!$F$8 -> 0 | I59: =I9*'Para reporte'!$F$8 -> 0 | J59: =J9*'Para reporte'!$F$8 -> 0 | K59: =K9*'Para reporte'!$F$8 -> 0 | L59: =L9*'Para reporte'!$F$8 -> 0 | M59: =M9*'Para reporte'!$F$8 -> 0 | N59: =N9*'Para reporte'!$F$8 -> 0 | O59: =O9*'Para reporte'!$F$8 -> 0 | ... AQ59: =AQ9*'Para reporte'!$F$8 -> 0
G60: Total de ingresos (MUS$) | H60: =SUM(H55:H59) -> 1.2333333 | I60: =SUM(I55:I59) -> 0 | J60: =SUM(J55:J59) -> 5.3444444 | K60: =SUM(K55:K59) -> 67.422222 | L60: =SUM(L55:L59) -> 112.64444 | M60: =SUM(M55:M59) -> 112.64444 | N60: =SUM(N55:N59) -> 203.91111 | O60: =SUM(O55:O59) -> 208.84444 | ... AQ60: =SUM(AQ55:AQ59) -> 319.84444
A62: Para comprobar: | G62: Ingresos de clientes Exp. Piloto en MUS$
C63: 2024 | D63: 2025 | E63: 2026 | G63: =Vaciado!B10 -> A | H63: =H16*'Para reporte'!$F$4 -> 0 | I63: =I16*'Para reporte'!$F$4 -> 0 | J63: =J16*'Para reporte'!$F$4 -> 0 | K63: =K16*'Para reporte'!$F$4 -> 0 | L63: =L16*'Para reporte'!$F$4 -> 0 | M63: =M16*'Para reporte'!$F$4 -> 0 | N63: =N16*'Para reporte'!$F$4 -> 0 | O63: =O16*'Para reporte'!$F$4 -> 0 | ... AQ63: =AQ16*'Para reporte'!$F$4 -> 0
A64: =SUM(C64:E64) -> #REF! | C64: ='Para reporte'!#REF! -> #REF! | D64: ='Para reporte'!#REF! -> #REF! | E64: ='Para reporte'!#REF! -> #REF! | G64: =Vaciado!B11 -> B | H64: =H17*'Para reporte'!$F$5 -> 0 | I64: =I17*'Para reporte'!$F$5 -> 0 | J64: =J17*'Para reporte'!$F$5 -> 0 | K64: =K17*'Para reporte'!$F$5 -> 0 | L64: =L17*'Para reporte'!$F$5 -> 0 | M64: =M17*'Para reporte'!$F$5 -> 0 | N64: =N17*'Para reporte'!$F$5 -> 0 | O64: =O17*'Para reporte'!$F$5 -> 0 | ... AQ64: =AQ17*'Para reporte'!$F$5 -> 0
A65: =SUM(C65:E65) -> 0 | C65: =SUM(H68:S68) -> 0 | D65: =SUM(T68:AE68) -> 0 | E65: =SUM(AF68:AQ68) -> 0 | G65: =Vaciado!B12 -> C | H65: =H18*'Para reporte'!$F$6 -> 0 | I65: =I18*'Para reporte'!$F$6 -> 0 | J65: =J18*'Para reporte'!$F$6 -> 0 | K65: =K18*'Para reporte'!$F$6 -> 0 | L65: =L18*'Para reporte'!$F$6 -> 0 | M65: =M18*'Para reporte'!$F$6 -> 0 | N65: =N18*'Para reporte'!$F$6 -> 0 | O65: =O18*'Para reporte'!$F$6 -> 0 | ... AQ65: =AQ18*'Para reporte'!$F$6 -> 0
G66: =Vaciado!B13 -> D | H66: =H19*'Para reporte'!$F$7 -> 0 | I66: =I19*'Para reporte'!$F$7 -> 0 | J66: =J19*'Para reporte'!$F$7 -> 0 | K66: =K19*'Para reporte'!$F$7 -> 0 | L66: =L19*'Para reporte'!$F$7 -> 0 | M66: =M19*'Para reporte'!$F$7 -> 0 | N66: =N19*'Para reporte'!$F$7 -> 0 | O66: =O19*'Para reporte'!$F$7 -> 0 | ... AQ66: =AQ19*'Para reporte'!$F$7 -> 0
G67: =Vaciado!B14 -> E | H67: =H20*'Para reporte'!$F$8 -> 0 | I67: =I20*'Para reporte'!$F$8 -> 0 | J67: =J20*'Para reporte'!$F$8 -> 0 | K67: =K20*'Para reporte'!$F$8 -> 0 | L67: =L20*'Para reporte'!$F$8 -> 0 | M67: =M20*'Para reporte'!$F$8 -> 0 | N67: =N20*'Para reporte'!$F$8 -> 0 | O67: =O20*'Para reporte'!$F$8 -> 0 | ... AQ67: =AQ20*'Para reporte'!$F$8 -> 0
G68: Total de ingresos (MUS$) | H68: =SUM(H63:H67) -> 0 | I68: =SUM(I63:I67) -> 0 | J68: =SUM(J63:J67) -> 0 | K68: =SUM(K63:K67) -> 0 | L68: =SUM(L63:L67) -> 0 | M68: =SUM(M63:M67) -> 0 | N68: =SUM(N63:N67) -> 0 | O68: =SUM(O63:O67) -> 0 | ... AQ68: =SUM(AQ63:AQ67) -> 0
A70: Para comprobar: | G70: Ingresos recurrentes en MUS$
C71: 2024 | D71: 2025 | E71: 2026 | G71: =Vaciado!B10 -> A | H71: =H32*'Para reporte'!$F$4 -> 0 | I71: =I32*'Para reporte'!$F$4 -> 0 | J71: =J32*'Para reporte'!$F$4 -> 0 | K71: =K32*'Para reporte'!$F$4 -> 0 | L71: =L32*'Para reporte'!$F$4 -> 0 | M71: =M32*'Para reporte'!$F$4 -> 0 | N71: =N32*'Para reporte'!$F$4 -> 0 | O71: =O32*'Para reporte'!$F$4 -> 0 | ... AQ71: =AQ32*'Para reporte'!$F$4 -> 34.655968
A72: =SUM(C72:E72) -> 2646.5634 | C72: ='Para reporte'!J27 -> 2.3420915 | D72: ='Para reporte'!K27 -> 697.94326 | E72: ='Para reporte'!L27 -> 1946.278 | G72: =Vaciado!B11 -> B | H72: =H33*'Para reporte'!$F$5 -> 0 | I72: =I33*'Para reporte'!$F$5 -> 0 | J72: =J33*'Para reporte'!$F$5 -> 0 | K72: =K33*'Para reporte'!$F$5 -> 0 | L72: =L33*'Para reporte'!$F$5 -> 0 | M72: =M33*'Para reporte'!$F$5 -> 0 | N72: =N33*'Para reporte'!$F$5 -> 0 | O72: =O33*'Para reporte'!$F$5 -> 0 | ... AQ72: =AQ33*'Para reporte'!$F$5 -> 56.653905
A73: =SUM(C73:E73) -> 2646.5634 | C73: =SUM(H76:S76) -> 2.3420915 | D73: =SUM(T76:AE76) -> 697.94326 | E73: =SUM(AF76:AQ76) -> 1946.278 | G73: =Vaciado!B12 -> C | H73: =H34*'Para reporte'!$F$6 -> 0 | I73: =I34*'Para reporte'!$F$6 -> 0 | J73: =J34*'Para reporte'!$F$6 -> 0 | K73: =K34*'Para reporte'!$F$6 -> 0 | L73: =L34*'Para reporte'!$F$6 -> 0 | M73: =M34*'Para reporte'!$F$6 -> 0 | N73: =N34*'Para reporte'!$F$6 -> 0 | O73: =O34*'Para reporte'!$F$6 -> 0 | ... AQ73: =AQ34*'Para reporte'!$F$6 -> 53.765908
G74: =Vaciado!B13 -> D | H74: =H35*'Para reporte'!$F$7 -> 0 | I74: =I35*'Para reporte'!$F$7 -> 0 | J74: =J35*'Para reporte'!$F$7 -> 0 | K74: =K35*'Para reporte'!$F$7 -> 0 | L74: =L35*'Para reporte'!$F$7 -> 0 | M74: =M35*'Para reporte'!$F$7 -> 0 | N74: =N35*'Para reporte'!$F$7 -> 0 | O74: =O35*'Para reporte'!$F$7 -> 0 | ... AQ74: =AQ35*'Para reporte'!$F$7 -> 77.422907
G75: =Vaciado!B14 -> E | H75: =H36*'Para reporte'!$F$8 -> 0 | I75: =I36*'Para reporte'!$F$8 -> 0 | J75: =J36*'Para reporte'!$F$8 -> 0 | K75: =K36*'Para reporte'!$F$8 -> 0 | L75: =L36*'Para reporte'!$F$8 -> 0 | M75: =M36*'Para reporte'!$F$8 -> 0 | N75: =N36*'Para reporte'!$F$8 -> 0 | O75: =O36*'Para reporte'!$F$8 -> 0 | ... AQ75: =AQ36*'Para reporte'!$F$8 -> 0
G76: Total de ingresos (MUS$) | H76: =SUM(H71:H75) -> 0 | I76: =SUM(I71:I75) -> 0 | J76: =SUM(J71:J75) -> 0 | K76: =SUM(K71:K75) -> 0 | L76: =SUM(L71:L75) -> 0 | M76: =SUM(M71:M75) -> 0 | N76: =SUM(N71:N75) -> 0 | O76: =SUM(O71:O75) -> 0 | ... AQ76: =SUM(AQ71:AQ75) -> 222.49869

Sheet Recurrencia
D1: Clientes nuevos del período (#) | E1: =P.Comercial!H28 -> 0.5 | F1: =P.Comercial!I28 -> 0 | G1: =P.Comercial!J28 -> 1 | H1: =P.Comercial!K28 -> 3.5 | I1: =P.Comercial!L28 -> 9.5 | J1: =P.Comercial!M28 -> 9.5 | K1: =P.Comercial!N28 -> 15 | L1: =P.Comercial!O28 -> 17 | ... AN1: =P.Comercial!AQ28 -> 48
A2: Recurrencia | C2: Mes | D2: # Nuevos | E2: 1 | F2: 2 | G2: 3 | H2: 4 | I2: 5 | J2: 6 | K2: 7 | L2: 8 | M2: 9 | N2: 10 | O2: 11 | P2: 12 | Q2: 13 | R2: 14 | S2: 15 | T2: 16 | U2: 17 | V2: 18 | W2: 19 | X2: 20 | Y2: 21 | Z2: 22 | AA2: 23 | AB2: 24 | AC2: 25 | AD2: 26 | AE2: 27 | AF2: 28 | AG2: 29 | AH2: 30 | AI2: 31 | AJ2: 32 | AK2: 33 | AL2: 34 | AM2: 35 | AN2: 36 | AO2: Clientes Recurrentes | AQ2: 1 | AR2: 2 | AS2: 3 | AT2: 4 | AU2: 5 | AV2: 6 | AW2: 7 | AX2: 8 | AY2: 9 | AZ2: 10 | BA2: 11 | BB2: 12 | BC2: 13 | BD2: 14 | BE2: 15 | BF2: 16 | BG2: 17 | BH2: 18 | BI2: 19 | BJ2: 20 | BK2: 21 | BL2: 22 | BM2: 23 | BN2: 24 | BO2: 25 | BP2: 26 | BQ2: 27 | BR2: 28 | BS2: 29 | BT2: 30 | BU2: 31 | BV2: 32 | BW2: 33 | BX2: 34 | BY2: 35 | BZ2: 36
A3: =Vaciado!D32 -> 12 | B3: =C3/$A$3 -> 0.083333333 | C3: 1 | D3: =E1 -> 0.5 | E3: =IF(B3=INT(B3),$D$3,0) -> 0 | AO3: =SUM(E3:AN3) -> 0 | AQ3: =AO3 -> 0 | AR3: =AO4 -> 0 | AS3: =AO5 -> 0 | AT3: =AO6 -> 0 | AU3: =AO7 -> 0 | AV3: =AO8 -> 0 | AW3: =AO9 -> 0 | AX3: =AO10 -> 0 | AY3: =AO11 -> 0 | AZ3: =AO12 -> 0 | BA3: =AO13 -> 0 | BB3: =AO14 -> 0.5 | BC3: =AO15 -> 0 | BD3: =AO16 -> 1 | BE3: =AO17 -> 3.5 | BF3: =AO18 -> 9.5 | BG3: =AO19 -> 9.5 | BH3: =AO20 -> 15 | BI3: =AO21 -> 17 | BJ3: =AO22 -> 17 | BK3: =AO23 -> 19 | BL3: =AO24 -> 19 | BM3: =AO25 -> 19 | BN3: =AO26 -> 19.5 | BO3: =AO27 -> 19 | BP3: =AO28 -> 20 | BQ3: =AO29 -> 22.5 | BR3: =AO30 -> 29 | BS3: =AO31 -> 29.5 | BT3: =AO32 -> 35.5 | BU3: =AO33 -> 38 | BV3: =AO34 -> 39.5 | BW3: =AO35 -> 43 | BX3: =AO36 -> 45 | BY3: =AO37 -> 47 | BZ3: =AO38 -> 47.5
B4: =C4/$A$3 -> 0.16666667 | C4: 2 | D4: =F1 -> 0 | E4: =IF(B4=INT(B4),$D$3,0) -> 0 | F4: =IF(B3=INT(B3),$D$4,0) -> 0 | AO4: =SUM(E4:AN4) -> 0
B5: =C5/$A$3 -> 0.25 | C5: 3 | D5: =G1 -> 1 | E5: =IF(B5=INT(B5),$D$3,0) -> 0 | F5: =IF(B4=INT(B4),$D$4,0) -> 0 | G5: =IF(B3=INT(B3),$D$5,0) -> 0 | AO5: =SUM(E5:AN5) -> 0
B6: =C6/$A$3 -> 0.33333333 | C6: 4 | D6: =H1 -> 3.5 | E6: =IF(B6=INT(B6),$D$3,0) -> 0 | F6: =IF(B5=INT(B5),$D$4,0) -> 0 | G6: =IF(B4=INT(B4),$D$5,0) -> 0 | H6: =IF(B3=INT(B3),$D$6,0) -> 0 | AO6: =SUM(E6:AN6) -> 0
B7: =C7/$A$3 -> 0.41666667 | C7: 5 | D7: =I1 -> 9.5 | E7: =IF(B7=INT(B7),$D$3,0) -> 0 | F7: =IF(B6=INT(B6),$D$4,0) -> 0 | G7: =IF(B5=INT(B5),$D$5,0) -> 0 | H7: =IF(B4=INT(B4),$D$6,0) -> 0 | I7: =IF(B3=INT(B3),$D$7,0) -> 0 | AO7: =SUM(E7:AN7) -> 0
B8: =C8/$A$3 -> 0.5 | C8: 6 | D8: =J1 -> 9.5 | E8: =IF(B8=INT(B8),$D$3,0) -> 0 | F8: =IF(B7=INT(B7),$D$4,0) -> 0 | G8: =IF(B6=INT(B6),$D$5,0) -> 0 | H8: =IF(B5=INT(B5),$D$6,0) -> 0 | I8: =IF(B4=INT(B4),$D$7,0) -> 0 | J8: =IF(B3=INT(B3),$D$8,0) -> 0 | AO8: =SUM(E8:AN8) -> 0
B9: =C9/$A$3 -> 0.58333333 | C9: 7 | D9: =K1 -> 15 | E9: =IF(B9=INT(B9),$D$3,0) -> 0 | F9: =IF(B8=INT(B8),$D$4,0) -> 0 | G9: =IF(B7=INT(B7),$D$5,0) -> 0 | H9: =IF(B6=INT(B6),$D$6,0) -> 0 | I9: =IF(B5=INT(B5),$D$7,0) -> 0 | J9: =IF(B4=INT(B4),$D$8,0) -> 0 | K9: =IF(B3=INT(B3),$D$9,0) -> 0 | AO9: =SUM(E9:AN9) -> 0
B10: =C10/$A$3 -> 0.66666667 | C10: 8 | D10: =L1 -> 17 | E10: =IF(B10=INT(B10),$D$3,0) -> 0 | F10: =IF(B9=INT(B9),$D$4,0) -> 0 | G10: =IF(B8=INT(B8),$D$5,0) -> 0 | H10: =IF(B7=INT(B7),$D$6,0) -> 0 | I10: =IF(B6=INT(B6),$D$7,0) -> 0 | J10: =IF(B5=INT(B5),$D$8,0) -> 0 | K10: =IF(B4=INT(B4),$D$9,0) -> 0 | L10: =IF(B3=INT(B3),$D$10,0) -> 0 | AO10: =SUM(E10:AN10) -> 0
B11: =C11/$A$3 -> 0.75 | C11: 9 | D11: =M1 -> 17 | E11: =IF(B11=INT(B11),$D$3,0) -> 0 | F11: =IF(B10=INT(B10),$D$4,0) -> 0 | G11: =IF(B9=INT(B9),$D$5,0) -> 0 | H11: =IF(B8=INT(B8),$D$6,0) -> 0 | I11: =IF(B7=INT(B7),$D$7,0) -> 0 | J11: =IF(B6=INT(B6),$D$8,0) -> 0 | K11: =IF(B5=INT(B5),$D$9,0) -> 0 | L11: =IF(B4=INT(B4),$D$10,0) -> 0 | M11: =IF(B3=INT(B3),$D$11,0) -> 0 | AO11: =SUM(E11:AN11) -> 0
B12: =C12/$A$3 -> 0.83333333 | C12: 10 | D12: =N1 -> 19 | E12: =IF(B12=INT(B12),$D$3,0) -> 0 | F12: =IF(B11=INT(B11),$D$4,0) -> 0 | G12: =IF(B10=INT(B10),$D$5,0) -> 0 | H12: =IF(B9=INT(B9),$D$6,0) -> 0 | I12: =IF(B8=INT(B8),$D$7,0) -> 0 | J12: =IF(B7=INT(B7),$D$8,0) -> 0 | K12: =IF(B6=INT(B6),$D$9,0) -> 0 | L12: =IF(B5=INT(B5),$D$10,0) -> 0 | M12: =IF(B4=INT(B4),$D$11,0) -> 0 | N12: =IF(B3=INT(B3),$D$12,0) -> 0 | AO12: =SUM(E12:AN12) -> 0
B13: =C13/$A$3 -> 0.91666667 | C13: 11 | D13: =O1 -> 19 | E13: =IF(B13=INT(B13),$D$3,0) -> 0 | F13: =IF(B12=INT(B12),$D$4,0) -> 0 | G13: =IF(B11=INT(B11),$D$5,0) -> 0 | H13: =IF(B10=INT(B10),$D$6,0) -> 0 | I13: =IF(B9=INT(B9),$D$7,0) -> 0 | J13: =IF(B8=INT(B8),$D$8,0) -> 0 | K13: =IF(B7=INT(B7),$D$9,0) -> 0 | L13: =IF(B6=INT(B6),$D$10,0) -> 0 | M13: =IF(B5=INT(B5),$D$11,0) -> 0 | N13: =IF(B4=INT(B4),$D$12,0) -> 0 | O13: =IF(B3=INT(B3),$D$13,0) -> 0 | AO13: =SUM(E13:AN13) -> 0
B14: =C14/$A$3 -> 1 | C14: 12 | D14: =P1 -> 19 | E14: =IF(B14=INT(B14),$D$3,0) -> 0.5 | F14: =IF(B13=INT(B13),$D$4,0) -> 0 | G14: =IF(B12=INT(B12),$D$5,0) -> 0 | H14: =IF(B11=INT(B11),$D$6,0) -> 0 | I14: =IF(B10=INT(B10),$D$7,0) -> 0 | J14: =IF(B9=INT(B9),$D$8,0) -> 0 | K14: =IF(B8=INT(B8),$D$9,0) -> 0 | L14: =IF(B7=INT(B7),$D$10,0) -> 0 | M14: =IF(B6=INT(B6),$D$11,0) -> 0 | N14: =IF(B5=INT(B5),$D$12,0) -> 0 | O14: =IF(B4=INT(B4),$D$13,0) -> 0 | P14: =IF(B3=INT(B3),$D$14,0) -> 0 | AO14: =SUM(E14:AN14) -> 0.5
B15: =C15/$A$3 -> 1.0833333 | C15: 13 | D15: =Q1 -> 19 | E15: =IF(B15=INT(B15),$D$3,0) -> 0 | F15: =IF(B14=INT(B14),$D$4,0) -> 0 | G15: =IF(B13=INT(B13),$D$5,0) -> 0 | H15: =IF(B12=INT(B12),$D$6,0) -> 0 | I15: =IF(B11=INT(B11),$D$7,0) -> 0 | J15: =IF(B10=INT(B10),$D$8,0) -> 0 | K15: =IF(B9=INT(B9),$D$9,0) -> 0 | L15: =IF(B8=INT(B8),$D$10,0) -> 0 | M15: =IF(B7=INT(B7),$D$11,0) -> 0 | N15: =IF(B6=INT(B6),$D$12,0) -> 0 | O15: =IF(B5=INT(B5),$D$13,0) -> 0 | P15: =IF(B4=INT(B4),$D$14,0) -> 0 | Q15: =IF(B3=INT(B3),$D$15,0) -> 0 | AO15: =SUM(E15:AN15) -> 0
B16: =C16/$A$3 -> 1.1666667 | C16: 14 | D16: =R1 -> 19 | E16: =IF(B16=INT(B16),$D$3,0) -> 0 | F16: =IF(B15=INT(B15),$D$4,0) -> 0 | G16: =IF(B14=INT(B14),$D$5,0) -> 1 | H16: =IF(B13=INT(B13),$D$6,0) -> 0 | I16: =IF(B12=INT(B12),$D$7,0) -> 0 | J16: =IF(B11=INT(B11),$D$8,0) -> 0 | K16: =IF(B10=INT(B10),$D$9,0) -> 0 | L16: =IF(B9=INT(B9),$D$10,0) -> 0 | M16: =IF(B8=INT(B8),$D$11,0) -> 0 | N16: =IF(B7=INT(B7),$D$12,0) -> 0 | O16: =IF(B6=INT(B6),$D$13,0) -> 0 | P16: =IF(B5=INT(B5),$D$14,0) -> 0 | Q16: =IF(B4=INT(B4),$D$15,0) -> 0 | R16: =IF(B3=INT(B3),$D$16,0) -> 0 | AO16: =SUM(E16:AN16) -> 1
B17: =C17/$A$3 -> 1.25 | C17: 15 | D17: =S1 -> 19 | E17: =IF(B17=INT(B17),$D$3,0) -> 0 | F17: =IF(B16=INT(B16),$D$4,0) -> 0 | G17: =IF(B15=INT(B15),$D$5,0) -> 0 | H17: =IF(B14=INT(B14),$D$6,0) -> 3.5 | I17: =IF(B13=INT(B13),$D$7,0) -> 0 | J17: =IF(B12=INT(B12),$D$8,0) -> 0 | K17: =IF(B11=INT(B11),$D$9,0) -> 0 | L17: =IF(B10=INT(B10),$D$10,0) -> 0 | M17: =IF(B9=INT(B9),$D$11,0) -> 0 | N17: =IF(B8=INT(B8),$D$12,0) -> 0 | O17: =IF(B7=INT(B7),$D$13,0) -> 0 | P17: =IF(B6=INT(B6),$D$14,0) -> 0 | Q17: =IF(B5=INT(B5),$D$15,0) -> 0 | R17: =IF(B4=INT(B4),$D$16,0) -> 0 | S17: =IF(B3=INT(B3),$D$17,0) -> 0 | AO17: =SUM(E17:AN17) -> 3.5
B18: =C18/$A$3 -> 1.3333333 | C18: 16 | D18: =T1 -> 19 | E18: =IF(B18=INT(B18),$D$3,0) -> 0 | F18: =IF(B17=INT(B17),$D$4,0) -> 0 | G18: =IF(B16=INT(B16),$D$5,0) -> 0 | H18: =IF(B15=INT(B15),$D$6,0) -> 0 | I18: =IF(B14=INT(B14),$D$7,0) -> 9.5 | J18: =IF(B13=INT(B13),$D$8,0) -> 0 | K18: =IF(B12=INT(B12),$D$9,0) -> 0 | L18: =IF(B11=INT(B11),$D$10,0) -> 0 | M18: =IF(B10=INT(B10),$D$11,0) -> 0 | N18: =IF(B9=INT(B9),$D$12,0) -> 0 | O18: =IF(B8=INT(B8),$D$13,0) -> 0 | P18: =IF(B7=INT(B7),$D$14,0) -> 0 | Q18: =IF(B6=INT(B6),$D$15,0) -> 0 | R18: =IF(B5=INT(B5),$D$16,0) -> 0 | S18: =IF(B4=INT(B4),$D$17,0) -> 0 | T18: =IF(B3=INT(B3),$D$18,0) -> 0 | AO18: =SUM(E18:AN18) -> 9.5
B19: =C19/$A$3 -> 1.4166667 | C19: 17 | D19: =U1 -> 19.5 | E19: =IF(B19=INT(B19),$D$3,0) -> 0 | F19: =IF(B18=INT(B18),$D$4,0) -> 0 | G19: =IF(B17=INT(B17),$D$5,0) -> 0 | H19: =IF(B16=INT(B16),$D$6,0) -> 0 | I19: =IF(B15=INT(B15),$D$7,0) -> 0 | J19: =IF(B14=INT(B14),$D$8,0) -> 9.5 | K19: =IF(B13=INT(B13),$D$9,0) -> 0 | L19: =IF(B12=INT(B12),$D$10,0) -> 0 | M19: =IF(B11=INT(B11),$D$11,0) -> 0 | N19: =IF(B10=INT(B10),$D$12,0) -> 0 | O19: =IF(B9=INT(B9),$D$13,0) -> 0 | P19: =IF(B8=INT(B8),$D$14,0) -> 0 | Q19: =IF(B7=INT(B7),$D$15,0) -> 0 | R19: =IF(B6=INT(B6),$D$16,0) -> 0 | S19: =IF(B5=INT(B5),$D$17,0) -> 0 | T19: =IF(B4=INT(B4),$D$18,0) -> 0 | U19: =IF(B3=INT(B3),$D$19,0) -> 0 | AO19: =SUM(E19:AN19) -> 9.5
B20: =C20/$A$3 -> 1.5 | C20: 18 | D20: =V1 -> 20 | E20: =IF(B20=INT(B20),$D$3,0) -> 0 | F20: =IF(B19=INT(B19),$D$4,0) -> 0 | G20: =IF(B18=INT(B18),$D$5,0) -> 0 | H20: =IF(B17=INT(B17),$D$6,0) -> 0 | I20: =IF(B16=INT(B16),$D$7,0) -> 0 | J20: =IF(B15=INT(B15),$D$8,0) -> 0 | K20: =IF(B14=INT(B14),$D$9,0) -> 15 | L20: =IF(B13=INT(B13),$D$10,0) -> 0 | M20: =IF(B12=INT(B12),$D$11,0) -> 0 | N20: =IF(B11=INT(B11),$D$12,0) -> 0 | O20: =IF(B10=INT(B10),$D$13,0) -> 0 | P20: =IF(B9=INT(B9),$D$14,0) -> 0 | Q20: =IF(B8=INT(B8),$D$15,0) -> 0 | R20: =IF(B7=INT(B7),$D$16,0) -> 0 | S20: =IF(B6=INT(B6),$D$17,0) -> 0 | T20: =IF(B5=INT(B5),$D$18,0) -> 0 | U20: =IF(B4=INT(B4),$D$19,0) -> 0 | V20: =IF(B3=INT(B3),$D$20,0) -> 0 | AO20: =SUM(E20:AN20) -> 15
B21: =C21/$A$3 -> 1.5833333 | C21: 19 | D21: =W1 -> 20.5 | E21: =IF(B21=INT(B21),$D$3,0) -> 0 | F21: =IF(B20=INT(B20),$D$4,0) -> 0 | G21: =IF(B19=INT(B19),$D$5,0) -> 0 | H21: =IF(B18=INT(B18),$D$6,0) -> 0 | I21: =IF(B17=INT(B17),$D$7,0) -> 0 | J21: =IF(B16=INT(B16),$D$8,0) -> 0 | K21: =IF(B15=INT(B15),$D$9,0) -> 0 | L21: =IF(B14=INT(B14),$D$10,0) -> 17 | M21: =IF(B13=INT(B13),$D$11,0) -> 0 | N21: =IF(B12=INT(B12),$D$12,0) -> 0 | O21: =IF(B11=INT(B11),$D$13,0) -> 0 | P21: =IF(B10=INT(B10),$D$14,0) -> 0 | Q21: =IF(B9=INT(B9),$D$15,0) -> 0 | R21: =IF(B8=INT(B8),$D$16,0) -> 0 | S21: =IF(B7=INT(B7),$D$17,0) -> 0 | T21: =IF(B6=INT(B6),$D$18,0) -> 0 | U21: =IF(B5=INT(B5),$D$19,0) -> 0 | V21: =IF(B4=INT(B4),$D$20,0) -> 0 | W21: =IF(B3=INT(B3),$D$21,0) -> 0 | AO21: =SUM(E21:AN21) -> 17
B22: =C22/$A$3 -> 1.6666667 | C22: 20 | D22: =X1 -> 21 | E22: =IF(B22=INT(B22),$D$3,0) -> 0 | F22: =IF(B21=INT(B21),$D$4,0) -> 0 | G22: =IF(B20=INT(B20),$D$5,0) -> 0 | H22: =IF(B19=INT(B19),$D$6,0) -> 0 | I22: =IF(B18=INT(B18),$D$7,0) -> 0 | J22: =IF(B17=INT(B17),$D$8,0) -> 0 | K22: =IF(B16=INT(B16),$D$9,0) -> 0 | L22: =IF(B15=INT(B15),$D$10,0) -> 0 | M22: =IF(B14=INT(B14),$D$11,0) -> 17 | N22: =IF(B13=INT(B13),$D$12,0) -> 0 | O22: =IF(B12=INT(B12),$D$13,0) -> 0 | P22: =IF(B11=INT(B11),$D$14,0) -> 0 | Q22: =IF(B10=INT(B10),$D$15,0) -> 0 | R22: =IF(B9=INT(B9),$D$16,0) -> 0 | S22: =IF(B8=INT(B8),$D$17,0) -> 0 | T22: =IF(B7=INT(B7),$D$18,0) -> 0 | U22: =IF(B6=INT(B6),$D$19,0) -> 0 | V22: =IF(B5=INT(B5),$D$20,0) -> 0 | W22: =IF(B4=INT(B4),$D$21,0) -> 0 | X22: =IF(B3=INT(B3),$D$22,0) -> 0 | AO22: =SUM(E22:AN22) -> 17
B23: =C23/$A$3 -> 1.75 | C23: 21 | D23: =Y1 -> 22.5 | E23: =IF(B23=INT(B23),$D$3,0) -> 0 | F23: =IF(B22=INT(B22),$D$4,0) -> 0 | G23: =IF(B21=INT(B21),$D$5,0) -> 0 | H23: =IF(B20=INT(B20),$D$6,0) -> 0 | I23: =IF(B19=INT(B19),$D$7,0) -> 0 | J23: =IF(B18=INT(B18),$D$8,0) -> 0 | K23: =IF(B17=INT(B17),$D$9,0) -> 0 | L23: =IF(B16=INT(B16),$D$10,0) -> 0 | M23: =IF(B15=INT(B15),$D$11,0) -> 0 | N23: =IF(B14=INT(B14),$D$12,0) -> 19 | O23: =IF(B13=INT(B13),$D$13,0) -> 0 | P23: =IF(B12=INT(B12),$D$14,0) -> 0 | Q23: =IF(B11=INT(B11),$D$15,0) -> 0 | R23: =IF(B10=INT(B10),$D$16,0) -> 0 | S23: =IF(B9=INT(B9),$D$17,0) -> 0 | T23: =IF(B8=INT(B8),$D$18,0) -> 0 | U23: =IF(B7=INT(B7),$D$19,0) -> 0 | V23: =IF(B6=INT(B6),$D$20,0) -> 0 | W23: =IF(B5=INT(B5),$D$21,0) -> 0 | X23: =IF(B4=INT(B4),$D$22,0) -> 0 | Y23: =IF(B3=INT(B3),$D$23,0) -> 0 | AO23: =SUM(E23:AN23) -> 19
B24: =C24/$A$3 -> 1.8333333 | C24: 22 | D24: =Z1 -> 24 | E24: =IF(B24=INT(B24),$D$3,0) -> 0 | F24: =IF(B23=INT(B23),$D$4,0) -> 0 | G24: =IF(B22=INT(B22),$D$5,0) -> 0 | H24: =IF(B21=INT(B21),$D$6,0) -> 0 | I24: =IF(B20=INT(B20),$D$7,0) -> 0 | J24: =IF(B19=INT(B19),$D$8,0) -> 0 | K24: =IF(B18=INT(B18),$D$9,0) -> 0 | L24: =IF(B17=INT(B17),$D$10,0) -> 0 | M24: =IF(B16=INT(B16),$D$11,0) -> 0 | N24: =IF(B15=INT(B15),$D$12,0) -> 0 | O24: =IF(B14=INT(B14),$D$13,0) -> 19 | P24: =IF(B13=INT(B13),$D$14,0) -> 0 | Q24: =IF(B12=INT(B12),$D$15,0) -> 0 | R24: =IF(B11=INT(B11),$D$16,0) -> 0 | S24: =IF(B10=INT(B10),$D$17,0) -> 0 | T24: =IF(B9=INT(B9),$D$18,0) -> 0 | U24: =IF(B8=INT(B8),$D$19,0) -> 0 | V24: =IF(B7=INT(B7),$D$20,0) -> 0 | W24: =IF(B6=INT(B6),$D$21,0) -> 0 | X24: =IF(B5=INT(B5),$D$22,0) -> 0 | Y24: =IF(B4=INT(B4),$D$23,0) -> 0 | Z24: =IF(B3=INT(B3),$D$24,0) -> 0 | AO24: =SUM(E24:AN24) -> 19
B25: =C25/$A$3 -> 1.9166667 | C25: 23 | D25: =AA1 -> 26 | E25: =IF(B25=INT(B25),$D$3,0) -> 0 | F25: =IF(B24=INT(B24),$D$4,0) -> 0 | G25: =IF(B23=INT(B23),$D$5,0) -> 0 | H25: =IF(B22=INT(B22),$D$6,0) -> 0 | I25: =IF(B21=INT(B21),$D$7,0) -> 0 | J25: =IF(B20=INT(B20),$D$8,0) -> 0 | K25: =IF(B19=INT(B19),$D$9,0) -> 0 | L25: =IF(B18=INT(B18),$D$10,0) -> 0 | M25: =IF(B17=INT(B17),$D$11,0) -> 0 | N25: =IF(B16=INT(B16),$D$12,0) -> 0 | O25: =IF(B15=INT(B15),$D$13,0) -> 0 | P25: =IF(B14=INT(B14),$D$14,0) -> 19 | Q25: =IF(B13=INT(B13),$D$15,0) -> 0 | R25: =IF(B12=INT(B12),$D$16,0) -> 0 | S25: =IF(B11=INT(B11),$D$17,0) -> 0 | T25: =IF(B10=INT(B10),$D$18,0) -> 0 | U25: =IF(B9=INT(B9),$D$19,0) -> 0 | V25: =IF(B8=INT(B8),$D$20,0) -> 0 | W25: =IF(B7=INT(B7),$D$21,0) -> 0 | X25: =IF(B6=INT(B6),$D$22,0) -> 0 | Y25: =IF(B5=INT(B5),$D$23,0) -> 0 | Z25: =IF(B4=INT(B4),$D$24,0) -> 0 | AA25: =IF(B3=INT(B3),$D$25,0) -> 0 | AO25: =SUM(E25:AN25) -> 19
B26: =C26/$A$3 -> 2 | C26: 24 | D26: =AB1 -> 28 | E26: =IF(B26=INT(B26),$D$3,0) -> 0.5 | F26: =IF(B25=INT(B25),$D$4,0) -> 0 | G26: =IF(B24=INT(B24),$D$5,0) -> 0 | H26: =IF(B23=INT(B23),$D$6,0) -> 0 | I26: =IF(B22=INT(B22),$D$7,0) -> 0 | J26: =IF(B21=INT(B21),$D$8,0) -> 0 | K26: =IF(B20=INT(B20),$D$9,0) -> 0 | L26: =IF(B19=INT(B19),$D$10,0) -> 0 | M26: =IF(B18=INT(B18),$D$11,0) -> 0 | N26: =IF(B17=INT(B17),$D$12,0) -> 0 | O26: =IF(B16=INT(B16),$D$13,0) -> 0 | P26: =IF(B15=INT(B15),$D$14,0) -> 0 | Q26: =IF(B14=INT(B14),$D$15,0) -> 19 | R26: =IF(B13=INT(B13),$D$16,0) -> 0 | S26: =IF(B12=INT(B12),$D$17,0) -> 0 | T26: =IF(B11=INT(B11),$D$18,0) -> 0 | U26: =IF(B10=INT(B10),$D$19,0) -> 0 | V26: =IF(B9=INT(B9),$D$20,0) -> 0 | W26: =IF(B8=INT(B8),$D$21,0) -> 0 | X26: =IF(B7=INT(B7),$D$22,0) -> 0 | Y26: =IF(B6=INT(B6),$D$23,0) -> 0 | Z26: =IF(B5=INT(B5),$D$24,0) -> 0 | AA26: =IF(B4=INT(B4),$D$25,0) -> 0 | AB26: =IF(B3=INT(B3),$D$26,0) -> 0 | AO26: =SUM(E26:AN26) -> 19.5
B27: =C27/$A$3 -> 2.0833333 | C27: 25 | D27: =AC1 -> 28 | E27: =IF(B27=INT(B27),$D$3,0) -> 0 | F27: =IF(B26=INT(B26),$D$4,0) -> 0 | G27: =IF(B25=INT(B25),$D$5,0) -> 0 | H27: =IF(B24=INT(B24),$D$6,0) -> 0 | I27: =IF(B23=INT(B23),$D$7,0) -> 0 | J27: =IF(B22=INT(B22),$D$8,0) -> 0 | K27: =IF(B21=INT(B21),$D$9,0) -> 0 | L27: =IF(B20=INT(B20),$D$10,0) -> 0 | M27: =IF(B19=INT(B19),$D$11,0) -> 0 | N27: =IF(B18=INT(B18),$D$12,0) -> 0 | O27: =IF(B17=INT(B17),$D$13,0) -> 0 | P27: =IF(B16=INT(B16),$D$14,0) -> 0 | Q27: =IF(B15=INT(B15),$D$15,0) -> 0 | R27: =IF(B14=INT(B14),$D$16,0) -> 19 | S27: =IF(B13=INT(B13),$D$17,0) -> 0 | T27: =IF(B12=INT(B12),$D$18,0) -> 0 | U27: =IF(B11=INT(B11),$D$19,0) -> 0 | V27: =IF(B10=INT(B10),$D$20,0) -> 0 | W27: =IF(B9=INT(B9),$D$21,0) -> 0 | X27: =IF(B8=INT(B8),$D$22,0) -> 0 | Y27: =IF(B7=INT(B7),$D$23,0) -> 0 | Z27: =IF(B6=INT(B6),$D$24,0) -> 0 | AA27: =IF(B5=INT(B5),$D$25,0) -> 0 | AB27: =IF(B4=INT(B4),$D$26,0) -> 0 | AC27: =IF(B3=INT(B3),$D$27,0) -> 0 | AO27: =SUM(E27:AN27) -> 19
B28: =C28/$A$3 -> 2.1666667 | C28: 26 | D28: =AD1 -> 28 | E28: =IF(B28=INT(B28),$D$3,0) -> 0 | F28: =IF(B27=INT(B27),$D$4,0) -> 0 | G28: =IF(B26=INT(B26),$D$5,0) -> 1 | H28: =IF(B25=INT(B25),$D$6,0) -> 0 | I28: =IF(B24=INT(B24),$D$7,0) -> 0 | J28: =IF(B23=INT(B23),$D$8,0) -> 0 | K28: =IF(B22=INT(B22),$D$9,0) -> 0 | L28: =IF(B21=INT(B21),$D$10,0) -> 0 | M28: =IF(B20=INT(B20),$D$11,0) -> 0 | N28: =IF(B19=INT(B19),$D$12,0) -> 0 | O28: =IF(B18=INT(B18),$D$13,0) -> 0 | P28: =IF(B17=INT(B17),$D$14,0) -> 0 | Q28: =IF(B16=INT(B16),$D$15,0) -> 0 | R28: =IF(B15=INT(B15),$D$16,0) -> 0 | S28: =IF(B14=INT(B14),$D$17,0) -> 19 | T28: =IF(B13=INT(B13),$D$18,0) -> 0 | U28: =IF(B12=INT(B12),$D$19,0) -> 0 | V28: =IF(B11=INT(B11),$D$20,0) -> 0 | W28: =IF(B10=INT(B10),$D$21,0) -> 0 | X28: =IF(B9=INT(B9),$D$22,0) -> 0 | Y28: =IF(B8=INT(B8),$D$23,0) -> 0 | Z28: =IF(B7=INT(B7),$D$24,0) -> 0 | AA28: =IF(B6=INT(B6),$D$25,0) -> 0 | AB28: =IF(B5=INT(B5),$D$26,0) -> 0 | AC28: =IF(B4=INT(B4),$D$27,0) -> 0 | AD28: =IF(B3=INT(B3),$D$28,0) -> 0 | AO28: =SUM(E28:AN28) -> 20
B29: =C29/$A$3 -> 2.25 | C29: 27 | D29: =AE1 -> 28.5 | E29: =IF(B29=INT(B29),$D$3,0) -> 0 | F29: =IF(B28=INT(B28),$D$4,0) -> 0 | G29: =IF(B27=INT(B27),$D$5,0) -> 0 | H29: =IF(B26=INT(B26),$D$6,0) -> 3.5 | I29: =IF(B25=INT(B25),$D$7,0) -> 0 | J29: =IF(B24=INT(B24),$D$8,0) -> 0 | K29: =IF(B23=INT(B23),$D$9,0) -> 0 | L29: =IF(B22=INT(B22),$D$10,0) -> 0 | M29: =IF(B21=INT(B21),$D$11,0) -> 0 | N29: =IF(B20=INT(B20),$D$12,0) -> 0 | O29: =IF(B19=INT(B19),$D$13,0) -> 0 | P29: =IF(B18=INT(B18),$D$14,0) -> 0 | Q29: =IF(B17=INT(B17),$D$15,0) -> 0 | R29: =IF(B16=INT(B16),$D$16,0) -> 0 | S29: =IF(B15=INT(B15),$D$17,0) -> 0 | T29: =IF(B14=INT(B14),$D$18,0) -> 19 | U29: =IF(B13=INT(B13),$D$19,0) -> 0 | V29: =IF(B12=INT(B12),$D$20,0) -> 0 | W29: =IF(B11=INT(B11),$D$21,0) -> 0 | X29: =IF(B10=INT(B10),$D$22,0) -> 0 | Y29: =IF(B9=INT(B9),$D$23,0) -> 0 | Z29: =IF(B8=INT(B8),$D$24,0) -> 0 | AA29: =IF(B7=INT(B7),$D$25,0) -> 0 | AB29: =IF(B6=INT(B6),$D$26,0) -> 0 | AC29: =IF(B5=INT(B5),$D$27,0) -> 0 | AD29: =IF(B4=INT(B4),$D$28,0) -> 0 | AE29: =IF(B3=INT(B3),$D$29,0) -> 0 | AO29: =SUM(E29:AN29) -> 22.5
B30: =C30/$A$3 -> 2.3333333 | C30: 28 | D30: =AF1 -> 29 | E30: =IF(B30=INT(B30),$D$3,0) -> 0 | F30: =IF(B29=INT(B29),$D$4,0) -> 0 | G30: =IF(B28=INT(B28),$D$5,0) -> 0 | H30: =IF(B27=INT(B27),$D$6,0) -> 0 | I30: =IF(B26=INT(B26),$D$7,0) -> 9.5 | J30: =IF(B25=INT(B25),$D$8,0) -> 0 | K30: =IF(B24=INT(B24),$D$9,0) -> 0 | L30: =IF(B23=INT(B23),$D$10,0) -> 0 | M30: =IF(B22=INT(B22),$D$11,0) -> 0 | N30: =IF(B21=INT(B21),$D$12,0) -> 0 | O30: =IF(B20=INT(B20),$D$13,0) -> 0 | P30: =IF(B19=INT(B19),$D$14,0) -> 0 | Q30: =IF(B18=INT(B18),$D$15,0) -> 0 | R30: =IF(B17=INT(B17),$D$16,0) -> 0 | S30: =IF(B16=INT(B16),$D$17,0) -> 0 | T30: =IF(B15=INT(B15),$D$18,0) -> 0 | U30: =IF(B14=INT(B14),$D$19,0) -> 19.5 | V30: =IF(B13=INT(B13),$D$20,0) -> 0 | W30: =IF(B12=INT(B12),$D$21,0) -> 0 | X30: =IF(B11=INT(B11),$D$22,0) -> 0 | Y30: =IF(B10=INT(B10),$D$23,0) -> 0 | Z30: =IF(B9=INT(B9),$D$24,0) -> 0 | AA30: =IF(B8=INT(B8),$D$25,0) -> 0 | AB30: =IF(B7=INT(B7),$D$26,0) -> 0 | AC30: =IF(B6=INT(B6),$D$27,0) -> 0 | AD30: =IF(B5=INT(B5),$D$28,0) -> 0 | AE30: =IF(B4=INT(B4),$D$29,0) -> 0 | AF30: =IF(B3=INT(B3),$D$30,0) -> 0 | AO30: =SUM(E30:AN30) -> 29
B31: =C31/$A$3 -> 2.4166667 | C31: 29 | D31: =AG1 -> 29.5 | E31: =IF(B31=INT(B31),$D$3,0) -> 0 | F31: =IF(B30=INT(B30),$D$4,0) -> 0 | G31: =IF(B29=INT(B29),$D$5,0) -> 0 | H31: =IF(B28=INT(B28),$D$6,0) -> 0 | I31: =IF(B27=INT(B27),$D$7,0) -> 0 | J31: =IF(B26=INT(B26),$D$8,0) -> 9.5 | K31: =IF(B25=INT(B25),$D$9,0) -> 0 | L31: =IF(B24=INT(B24),$D$10,0) -> 0 | M31: =IF(B23=INT(B23),$D$11,0) -> 0 | N31: =IF(B22=INT(B22),$D$12,0) -> 0 | O31: =IF(B21=INT(B21),$D$13,0) -> 0 | P31: =IF(B20=INT(B20),$D$14,0) -> 0 | Q31: =IF(B19=INT(B19),$D$15,0) -> 0 | R31: =IF(B18=INT(B18),$D$16,0) -> 0 | S31: =IF(B17=INT(B17),$D$17,0) -> 0 | T31: =IF(B16=INT(B16),$D$18,0) -> 0 | U31: =IF(B15=INT(B15),$D$19,0) -> 0 | V31: =IF(B14=INT(B14),$D$20,0) -> 20 | W31: =IF(B13=INT(B13),$D$21,0) -> 0 | X31: =IF(B12=INT(B12),$D$22,0) -> 0 | Y31: =IF(B11=INT(B11),$D$23,0) -> 0 | Z31: =IF(B10=INT(B10),$D$24,0) -> 0 | AA31: =IF(B9=INT(B9),$D$25,0) -> 0 | AB31: =IF(B8=INT(B8),$D$26,0) -> 0 | AC31: =IF(B7=INT(B7),$D$27,0) -> 0 | AD31: =IF(B6=INT(B6),$D$28,0) -> 0 | AE31: =IF(B5=INT(B5),$D$29,0) -> 0 | AF31: =IF(B4=INT(B4),$D$30,0) -> 0 | AG31: =IF(B3=INT(B3),$D$31,0) -> 0 | AO31: =SUM(E31:AN31) -> 29.5
B32: =C32/$A$3 -> 2.5 | C32: 30 | D32: =AH1 -> 30.5 | E32: =IF(B32=INT(B32),$D$3,0) -> 0 | F32: =IF(B31=INT(B31),$D$4,0) -> 0 | G32: =IF(B30=INT(B30),$D$5,0) -> 0 | H32: =IF(B29=INT(B29),$D$6,0) -> 0 | I32: =IF(B28=INT(B28),$D$7,0) -> 0 | J32: =IF(B27=INT(B27),$D$8,0) -> 0 | K32: =IF(B26=INT(B26),$D$9,0) -> 15 | L32: =IF(B25=INT(B25),$D$10,0) -> 0 | M32: =IF(B24=INT(B24),$D$11,0) -> 0 | N32: =IF(B23=INT(B23),$D$12,0) -> 0 | O32: =IF(B22=INT(B22),$D$13,0) -> 0 | P32: =IF(B21=INT(B21),$D$14,0) -> 0 | Q32: =IF(B20=INT(B20),$D$15,0) -> 0 | R32: =IF(B19=INT(B19),$D$16,0) -> 0 | S32: =IF(B18=INT(B18),$D$17,0) -> 0 | T32: =IF(B17=INT(B17),$D$18,0) -> 0 | U32: =IF(B16=INT(B16),$D$19,0) -> 0 | V32: =IF(B15=INT(B15),$D$20,0) -> 0 | W32: =IF(B14=INT(B14),$D$21,0) -> 20.5 | X32: =IF(B13=INT(B13),$D$22,0) -> 0 | Y32: =IF(B12=INT(B12),$D$23,0) -> 0 | Z32: =IF(B11=INT(B11),$D$24,0) -> 0 | AA32: =IF(B10=INT(B10),$D$25,0) -> 0 | AB32: =IF(B9=INT(B9),$D$26,0) -> 0 | AC32: =IF(B8=INT(B8),$D$27,0) -> 0 | AD32: =IF(B7=INT(B7),$D$28,0) -> 0 | AE32: =IF(B6=INT(B6),$D$29,0) -> 0 | AF32: =IF(B5=INT(B5),$D$30,0) -> 0 | AG32: =IF(B4=INT(B4),$D$31,0) -> 0 | AH32: =IF(B3=INT(B3),$D$32,0) -> 0 | AO32: =SUM(E32:AN32) -> 35.5
B33: =C33/$A$3 -> 2.5833333 | C33: 31 | D33: =AI1 -> 32 | E33: =IF(B33=INT(B33),$D$3,0) -> 0 | F33: =IF(B32=INT(B32),$D$4,0) -> 0 | G33: =IF(B31=INT(B31),$D$5,0) -> 0 | H33: =IF(B30=INT(B30),$D$6,0) -> 0 | I33: =IF(B29=INT(B29),$D$7,0) -> 0 | J33: =IF(B28=INT(B28),$D$8,0) -> 0 | K33: =IF(B27=INT(B27),$D$9,0) -> 0 | L33: =IF(B26=INT(B26),$D$10,0) -> 17 | M33: =IF(B25=INT(B25),$D$11,0) -> 0 | N33: =IF(B24=INT(B24),$D$12,0) -> 0 | O33: =IF(B23=INT(B23),$D$13,0) -> 0 | P33: =IF(B22=INT(B22),$D$14,0) -> 0 | Q33: =IF(B21=INT(B21),$D$15,0) -> 0 | R33: =IF(B20=INT(B20),$D$16,0) -> 0 | S33: =IF(B19=INT(B19),$D$17,0) -> 0 | T33: =IF(B18=INT(B18),$D$18,0) -> 0 | U33: =IF(B17=INT(B17),$D$19,0) -> 0 | V33: =IF(B16=INT(B16),$D$20,0) -> 0 | W33: =IF(B15=INT(B15),$D$21,0) -> 0 | X33: =IF(B14=INT(B14),$D$22,0) -> 21 | Y33: =IF(B13=INT(B13),$D$23,0) -> 0 | Z33: =IF(B12=INT(B12),$D$24,0) -> 0 | AA33: =IF(B11=INT(B11),$D$25,0) -> 0 | AB33: =IF(B10=INT(B10),$D$26,0) -> 0 | AC33: =IF(B9=INT(B9),$D$27,0) -> 0 | AD33: =IF(B8=INT(B8),$D$28,0) -> 0 | AE33: =IF(B7=INT(B7),$D$29,0) -> 0 | AF33: =IF(B6=INT(B6),$D$30,0) -> 0 | AG33: =IF(B5=INT(B5),$D$31,0) -> 0 | AH33: =IF(B4=INT(B4),$D$32,0) -> 0 | AI33: =IF(B3=INT(B3),$D$33,0) -> 0 | AO33: =SUM(E33:AN33) -> 38
B34: =C34/$A$3 -> 2.6666667 | C34: 32 | D34: =AJ1 -> 34 | E34: =IF(B34=INT(B34),$D$3,0) -> 0 | F34: =IF(B33=INT(B33),$D$4,0) -> 0 | G34: =IF(B32=INT(B32),$D$5,0) -> 0 | H34: =IF(B31=INT(B31),$D$6,0) -> 0 | I34: =IF(B30=INT(B30),$D$7,0) -> 0 | J34: =IF(B29=INT(B29),$D$8,0) -> 0 | K34: =IF(B28=INT(B28),$D$9,0) -> 0 | L34: =IF(B27=INT(B27),$D$10,0) -> 0 | M34: =IF(B26=INT(B26),$D$11,0) -> 17 | N34: =IF(B25=INT(B25),$D$12,0) -> 0 | O34: =IF(B24=INT(B24),$D$13,0) -> 0 | P34: =IF(B23=INT(B23),$D$14,0) -> 0 | Q34: =IF(B22=INT(B22),$D$15,0) -> 0 | R34: =IF(B21=INT(B21),$D$16,0) -> 0 | S34: =IF(B20=INT(B20),$D$17,0) -> 0 | T34: =IF(B19=INT(B19),$D$18,0) -> 0 | U34: =IF(B18=INT(B18),$D$19,0) -> 0 | V34: =IF(B17=INT(B17),$D$20,0) -> 0 | W34: =IF(B16=INT(B16),$D$21,0) -> 0 | X34: =IF(B15=INT(B15),$D$22,0) -> 0 | Y34: =IF(B14=INT(B14),$D$23,0) -> 22.5 | Z34: =IF(B13=INT(B13),$D$24,0) -> 0 | AA34: =IF(B12=INT(B12),$D$25,0) -> 0 | AB34: =IF(B11=INT(B11),$D$26,0) -> 0 | AC34: =IF(B10=INT(B10),$D$27,0) -> 0 | AD34: =IF(B9=INT(B9),$D$28,0) -> 0 | AE34: =IF(B8=INT(B8),$D$29,0) -> 0 | AF34: =IF(B7=INT(B7),$D$30,0) -> 0 | AG34: =IF(B6=INT(B6),$D$31,0) -> 0 | AH34: =IF(B5=INT(B5),$D$32,0) -> 0 | AI34: =IF(B4=INT(B4),$D$33,0) -> 0 | AJ34: =IF(B3=INT(B3),$D$34,0) -> 0 | AO34: =SUM(E34:AN34) -> 39.5
B35: =C35/$A$3 -> 2.75 | C35: 33 | D35: =AK1 -> 36.5 | E35: =IF(B35=INT(B35),$D$3,0) -> 0 | F35: =IF(B34=INT(B34),$D$4,0) -> 0 | G35: =IF(B33=INT(B33),$D$5,0) -> 0 | H35: =IF(B32=INT(B32),$D$6,0) -> 0 | I35: =IF(B31=INT(B31),$D$7,0) -> 0 | J35: =IF(B30=INT(B30),$D$8,0) -> 0 | K35: =IF(B29=INT(B29),$D$9,0) -> 0 | L35: =IF(B28=INT(B28),$D$10,0) -> 0 | M35: =IF(B27=INT(B27),$D$11,0) -> 0 | N35: =IF(B26=INT(B26),$D$12,0) -> 19 | O35: =IF(B25=INT(B25),$D$13,0) -> 0 | P35: =IF(B24=INT(B24),$D$14,0) -> 0 | Q35: =IF(B23=INT(B23),$D$15,0) -> 0 | R35: =IF(B22=INT(B22),$D$16,0) -> 0 | S35: =IF(B21=INT(B21),$D$17,0) -> 0 | T35: =IF(B20=INT(B20),$D$18,0) -> 0 | U35: =IF(B19=INT(B19),$D$19,0) -> 0 | V35: =IF(B18=INT(B18),$D$20,0) -> 0 | W35: =IF(B17=INT(B17),$D$21,0) -> 0 | X35: =IF(B16=INT(B16),$D$22,0) -> 0 | Y35: =IF(B15=INT(B15),$D$23,0) -> 0 | Z35: =IF(B14=INT(B14),$D$24,0) -> 24 | AA35: =IF(B13=INT(B13),$D$25,0) -> 0 | AB35: =IF(B12=INT(B12),$D$26,0) -> 0 | AC35: =IF(B11=INT(B11),$D$27,0) -> 0 | AD35: =IF(B10=INT(B10),$D$28,0) -> 0 | AE35: =IF(B9=INT(B9),$D$29,0) -> 0 | AF35: =IF(B8=INT(B8),$D$30,0) -> 0 | AG35: =IF(B7=INT(B7),$D$31,0) -> 0 | AH35: =IF(B6=INT(B6),$D$32,0) -> 0 | AI35: =IF(B5=INT(B5),$D$33,0) -> 0 | AJ35: =IF(B4=INT(B4),$D$34,0) -> 0 | AK35: =IF(B3=INT(B3),$D$35,0) -> 0 | AO35: =SUM(E35:AN35) -> 43
B36: =C36/$A$3 -> 2.8333333 | C36: 34 | D36: =AL1 -> 39.5 | E36: =IF(B36=INT(B36),$D$3,0) -> 0 | F36: =IF(B35=INT(B35),$D$4,0) -> 0 | G36: =IF(B34=INT(B34),$D$5,0) -> 0 | H36: =IF(B33=INT(B33),$D$6,0) -> 0 | I36: =IF(B32=INT(B32),$D$7,0) -> 0 | J36: =IF(B31=INT(B31),$D$8,0) -> 0 | K36: =IF(B30=INT(B30),$D$9,0) -> 0 | L36: =IF(B29=INT(B29),$D$10,0) -> 0 | M36: =IF(B28=INT(B28),$D$11,0) -> 0 | N36: =IF(B27=INT(B27),$D$12,0) -> 0 | O36: =IF(B26=INT(B26),$D$13,0) -> 19 | P36: =IF(B25=INT(B25),$D$14,0) -> 0 | Q36: =IF(B24=INT(B24),$D$15,0) -> 0 | R36: =IF(B23=INT(B23),$D$16,0) -> 0 | S36: =IF(B22=INT(B22),$D$17,0) -> 0 | T36: =IF(B21=INT(B21),$D$18,0) -> 0 | U36: =IF(B20=INT(B20),$D$19,0) -> 0 | V36: =IF(B19=INT(B19),$D$20,0) -> 0 | W36: =IF(B18=INT(B18),$D$21,0) -> 0 | X36: =IF(B17=INT(B17),$D$22,0) -> 0 | Y36: =IF(B16=INT(B16),$D$23,0) -> 0 | Z36: =IF(B15=INT(B15),$D$24,0) -> 0 | AA36: =IF(B14=INT(B14),$D$25,0) -> 26 | AB36: =IF(B13=INT(B13),$D$26,0) -> 0 | AC36: =IF(B12=INT(B12),$D$27,0) -> 0 | AD36: =IF(B11=INT(B11),$D$28,0) -> 0 | AE36: =IF(B10=INT(B10),$D$29,0) -> 0 | AF36: =IF(B9=INT(B9),$D$30,0) -> 0 | AG36: =IF(B8=INT(B8),$D$31,0) -> 0 | AH36: =IF(B7=INT(B7),$D$32,0) -> 0 | AI36: =IF(B6=INT(B6),$D$33,0) -> 0 | AJ36: =IF(B5=INT(B5),$D$34,0) -> 0 | AK36: =IF(B4=INT(B4),$D$35,0) -> 0 | AL36: =IF(B3=INT(B3),$D$36,0) -> 0 | AO36: =SUM(E36:AN36) -> 45
B37: =C37/$A$3 -> 2.9166667 | C37: 35 | D37: =AM1 -> 43.5 | E37: =IF(B37=INT(B37),$D$3,0) -> 0 | F37: =IF(B36=INT(B36),$D$4,0) -> 0 | G37: =IF(B35=INT(B35),$D$5,0) -> 0 | H37: =IF(B34=INT(B34),$D$6,0) -> 0 | I37: =IF(B33=INT(B33),$D$7,0) -> 0 | J37: =IF(B32=INT(B32),$D$8,0) -> 0 | K37: =IF(B31=INT(B31),$D$9,0) -> 0 | L37: =IF(B30=INT(B30),$D$10,0) -> 0 | M37: =IF(B29=INT(B29),$D$11,0) -> 0 | N37: =IF(B28=INT(B28),$D$12,0) -> 0 | O37: =IF(B27=INT(B27),$D$13,0) -> 0 | P37: =IF(B26=INT(B26),$D$14,0) -> 19 | Q37: =IF(B25=INT(B25),$D$15,0) -> 0 | R37: =IF(B24=INT(B24),$D$16,0) -> 0 | S37: =IF(B23=INT(B23),$D$17,0) -> 0 | T37: =IF(B22=INT(B22),$D$18,0) -> 0 | U37: =IF(B21=INT(B21),$D$19,0) -> 0 | V37: =IF(B20=INT(B20),$D$20,0) -> 0 | W37: =IF(B19=INT(B19),$D$21,0) -> 0 | X37: =IF(B18=INT(B18),$D$22,0) -> 0 | Y37: =IF(B17=INT(B17),$D$23,0) -> 0 | Z37: =IF(B16=INT(B16),$D$24,0) -> 0 | AA37: =IF(B15=INT(B15),$D$25,0) -> 0 | AB37: =IF(B14=INT(B14),$D$26,0) -> 28 | AC37: =IF(B13=INT(B13),$D$27,0) -> 0 | AD37: =IF(B12=INT(B12),$D$28,0) -> 0 | AE37: =IF(B11=INT(B11),$D$29,0) -> 0 | AF37: =IF(B10=INT(B10),$D$30,0) -> 0 | AG37: =IF(B9=INT(B9),$D$31,0) -> 0 | AH37: =IF(B8=INT(B8),$D$32,0) -> 0 | AI37: =IF(B7=INT(B7),$D$33,0) -> 0 | AJ37: =IF(B6=INT(B6),$D$34,0) -> 0 | AK37: =IF(B5=INT(B5),$D$35,0) -> 0 | AL37: =IF(B4=INT(B4),$D$36,0) -> 0 | AM37: =IF(B3=INT(B3),$D$37,0) -> 0 | AO37: =SUM(E37:AN37) -> 47
B38: =C38/$A$3 -> 3 | C38: 36 | D38: =AN1 -> 48 | E38: =IF(B38=INT(B38),$D$3,0) -> 0.5 | F38: =IF(B37=INT(B37),$D$4,0) -> 0 | G38: =IF(B36=INT(B36),$D$5,0) -> 0 | H38: =IF(B35=INT(B35),$D$6,0) -> 0 | I38: =IF(B34=INT(B34),$D$7,0) -> 0 | J38: =IF(B33=INT(B33),$D$8,0) -> 0 | K38: =IF(B32=INT(B32),$D$9,0) -> 0 | L38: =IF(B31=INT(B31),$D$10,0) -> 0 | M38: =IF(B30=INT(B30),$D$11,0) -> 0 | N38: =IF(B29=INT(B29),$D$12,0) -> 0 | O38: =IF(B28=INT(B28),$D$13,0) -> 0 | P38: =IF(B27=INT(B27),$D$14,0) -> 0 | Q38: =IF(B26=INT(B26),$D$15,0) -> 19 | R38: =IF(B25=INT(B25),$D$16,0) -> 0 | S38: =IF(B24=INT(B24),$D$17,0) -> 0 | T38: =IF(B23=INT(B23),$D$18,0) -> 0 | U38: =IF(B22=INT(B22),$D$19,0) -> 0 | V38: =IF(B21=INT(B21),$D$20,0) -> 0 | W38: =IF(B20=INT(B20),$D$21,0) -> 0 | X38: =IF(B19=INT(B19),$D$22,0) -> 0 | Y38: =IF(B18=INT(B18),$D$23,0) -> 0 | Z38: =IF(B17=INT(B17),$D$24,0) -> 0 | AA38: =IF(B16=INT(B16),$D$25,0) -> 0 | AB38: =IF(B15=INT(B15),$D$26,0) -> 0 | AC38: =IF(B14=INT(B14),$D$27,0) -> 28 | AD38: =IF(B13=INT(B13),$D$28,0) -> 0 | AE38: =IF(B12=INT(B12),$D$29,0) -> 0 | AF38: =IF(B11=INT(B11),$D$30,0) -> 0 | AG38: =IF(B10=INT(B10),$D$31,0) -> 0 | AH38: =IF(B9=INT(B9),$D$32,0) -> 0 | AI38: =IF(B8=INT(B8),$D$33,0) -> 0 | AJ38: =IF(B7=INT(B7),$D$34,0) -> 0 | AK38: =IF(B6=INT(B6),$D$35,0) -> 0 | AL38: =IF(B5=INT(B5),$D$36,0) -> 0 | AM38: =IF(B4=INT(B4),$D$37,0) -> 0 | AN38: =IF(B3=INT(B3),$D$38,0) -> 0 | AO38: =SUM(E38:AN38) -> 47.5

Sheet Metas
B2: UF | C2: 100000 | D2: 1000000
B3: Ventas en MUS$ | C3: =((C2*Vaciado!D16)/1000)/Vaciado!D17 -> 4111.1111 | D3: =((D2*Vaciado!D16)/1000)/Vaciado!D17 -> 41111.111
B5: UF 2 de enero 2024 | C5: 36806
B6: Expectativa IPC | D6: UF | E6: Min. Ventas Scale X(MUS$)
B7: 2024 | C7: 0.042 | D7: =C5*(1+C7) -> 38351.852 | E7: =((D7*$C$2)/Vaciado!$D$17)/1000 -> 4261.3169
B8: 2025 | C8: 0.03 | D8: =D7*(1+C8) -> 39502.408 | E8: =((D8*$C$2)/Vaciado!$D$17)/1000 -> 4389.1564
B9: 2026 | C9: 0.03 | D9: =D8*(1+C9) -> 40687.48 | E9: =((D9*$C$2)/Vaciado!$D$17)/1000 -> 4520.8311
E10: =SUM(E7:E9) -> 13171.304
C12: 2024 | D12: 2025 | E12: 2026
B13: Ventas Chile | C13: ='Para reporte'!K55 -> 1564.5643 | D13: ='Para reporte'!L55 -> 3364.821 | E13: ='Para reporte'!M55 -> 5160.3447
B14: Punto de Equilibrio | C14: ='Para reporte'!K94+'Para reporte'!K95+'Para reporte'!K96 -> 1406.9215 | D14: ='Para reporte'!L94+'Para reporte'!L95+'Para reporte'!L96 -> 2709.1093 | E14: ='Para reporte'!M94+'Para reporte'!M95+'Para reporte'!M96 -> 3982.7354
B15: Sobre o bajo el equilibrio | C15: =C13-C14 -> 157.6428 | D15: =D13-D14 -> 655.71173 | E15: =E13-E14 -> 1177.6093
B16: Down/Upside | C16: =C13/C14 -> 1.112048 | D16: =D13/D14 -> 1.2420396 | E16: =E13/E14 -> 1.2956785
B17: Ingresos para ser Startup | C17: 0 | D17: 0 | E17: 1000
B18: Down/Upside | C18: =IF(C17=0,0,(C13-C17)/C17) -> 0 | D18: =IF(D17=0,0,(D13-D17)/D17) -> 0 | E18: =IF(E17=0,0,(E13-E17)/E17) -> 4.1603447
B19: Ingresos ScaleX target solo Chile | C19: =E7 -> 4261.3169 | D19: =E8 -> 4389.1564 | E19: =E9 -> 4520.8311
B20: Down/Upside | C20: =C13-C19 -> -2696.7526 | D20: =D13-D19 -> -1024.3354 | E20: =E13-E19 -> 639.51358
B21: Down/Upside | C21: =C20/C19 -> -0.63284488 | D21: =D20/D19 -> -0.23337864 | E21: =E20/E19 -> 0.1414593
B22: Gastos del CAC | C22: =Dashboard!C25/'Para reporte'!J3 -> 1.4810655 | D22: =Dashboard!D25/'Para reporte'!K3 -> 1.5210239 | E22: =Dashboard!E25/'Para reporte'!L3 -> 1.4498311

Sheet Sensibilidad
A1: Variable | B1: Actual | C1: Análisis | D1: Valor | E1: Efecto sobre el valor
A2: Valor actual | B2: =Vaciado!E5 -> 2183.3686 | C2: =B2 -> 2183.3686 | D2: =B2 -> 2183.3686 | E2: =(D2-Vaciado!$E$5)/Vaciado!$E$5 -> 0
A3: Castigo por riesgo | B3: 0.1 | C3: 0 | D3: 2655 | E3: =(D3-Vaciado!$E$5)/Vaciado!$E$5 -> 0.21601088
A4: Recurrencia | B4: 12 | C4: 6 | D4: 3286 | E4: =(D4-Vaciado!$E$5)/Vaciado!$E$5 -> 0.50501385
A5: CHURN | B5: 0.5 | C5: 0.2 | D5: 2579 | E5: =(D5-Vaciado!$E$5)/Vaciado!$E$5 -> 0.18120228
A6: Impuesto efectivo | B6: ='MAP VALUE'!J20 -> 0.11459869 | C6: 0.125 | D6: 2240 | E6: =(D6-Vaciado!$E$5)/Vaciado!$E$5 -> 0.025937619
A9: Variable | B9: Actual | C9: Min. Para que EBITDA = 0 | D9: Variación Tolerable | E9: EBITDA
A10: Total de clientes | B10: ='MAP VALUE'!D11 -> 1589 | C10: 294 | D10: =(C10-B10)/B10 -> -0.81497797 | E10: 0
A11: Ticket promedio | B11: 24.79 | C11: 1.83 | D11: =(C11-B11)/B11 -> -0.92617991 | E11: 0
A12: CAC | B12: 7.3 | C12: 5 | D12: =(C12-B12)/B12 -> -0.31506849 | E12: 0
A13: Recurrencia | B13: 1.47 | C13: 0.53 | D13: =(C13-B13)/B13 -> -0.63945578 | E13: 0
